src/timer/mod10.v
`timescale 1ns/1ps

//  TODO checar o *tc*

module mod10(
    input wire [3:0] data,
    input wire loadn, clrn, clk, en,
    output reg [3:0] out,
    output reg tc, zero
);

    always @ (posedge clk or negedge clrn) begin
        
        if(!clrn) begin
            out = 0;
            tc = 0;
            zero = 0;
        end
        else if(!loadn)
            out <= data;
        else begin
            if(en) begin
                if(out == 1) begin
                    out <= out -1;
                    zero <= 0;
                    tc <= 1;
                end

                else if(out == 0) begin
                    out <= 9;
                    zero <= 1;
                    tc <= 0;
                end
                
                else begin
                    out <= out -1;
                    zero <= 0;
                    tc <= 0;
                end
            end 
            else
                tc <= 0;
        end
    end


endmodule

src/timer/mod6.v
module mod6(output reg [3:0] out,
                     output reg tc, zero,
                     input wire [3:0] data,
                     input wire loadn, clrn, clk, en);

always @(posedge clk or negedge clrn) begin

  if(!clrn)
    out <= 0;
  else if(!loadn)
    out <= data;

  else begin
    if (en)
      begin
        if(out==1)
          begin
            out<=out-1;
            #20 tc<=1;
          end
        else if(out==0)
          begin
            tc<=0;
            zero<=1;
            out<=5;
          end
        else begin
          tc<=0;
          zero<=0;
          out<=out-1;        
        end
      end  
    else
      begin
        tc<=0;
      end    
  end
end
endmodule

src/timer/timer.v
module timer(
    input wire [3:0] data,
    input wire loadn, clrn, clk, en,
    output wire [3:0] sec_ones, 
    output wire [3:0] sec_tens, 
    output wire [3:0] mins,
    output wire zero 
);
    wire tc_ones, tc_tens, tc_mins, zero_ones, zero_tens, zero_mins;

    mod10 sec_ones_module ( .data(data), .loadn(loadn), .clrn(clrn), .clk(clk), .en(en), .out(sec_ones), .tc(tc_ones), .zero(zero_ones) );
    mod6 sec_tens_module ( .data(sec_ones), .loadn(loadn), .clrn(clrn), .clk(clk), .en(tc_ones), .out(sec_tens), .tc(tc_tens), .zero(zero_tens) );
    mod10 mins_module ( .data(sec_tens), .loadn(loadn), .clrn(clrn), .clk(clk), .en(tc_tens), .out(mins), .tc(tc_mins), .zero(zero_mins) );
    
    assign zero = zero_mins & zero_ones & zero_tens;

endmodule

testbenches/tb_timer.v
`timescale 1ns / 1ps


module test_timer;
    // Inputs
    reg clk ;
    reg clrn;
  reg loadn;
  reg en;
  reg [3:0] data;
    // Output
    wire[3:0] sec_ones, sec_tens, mins;
  wire tc;
  wire zero;
    // Instantiate the Timer
  
    timer uut(
        .clk(clk), 
        .clrn(clrn),
    .loadn(loadn),
    .en(en),
    .data(data),
    .sec_ones(sec_ones),
    .sec_tens(sec_tens),
    .mins(mins),
    .zero(zero)
    );
 
always #1 clk <= ~clk;

initial 
  begin
  $dumpfile("test_timer.vcd");
  $dumpvars(0, test_timer);
  clk<=1;
  loadn<=0;
  data<=4'b1001;
  clrn<=1;
  en<=1;
  #2
  loadn<=0;
  data<=4'b0011;
  clrn<=1;
  en<=1;  
  #2
  loadn<=0;
  data<=4'b0010;
  clrn<=1;
  en<=1;  
  #2
  loadn<=1;
  data<=4'b0011;
  clrn<=1;
  en<=1;  
  #500
  $finish;
  end
 
endmodule

test_timer.vcd
$date
	Wed Apr 28 18:43:24 2021
$end
$version
	Icarus Verilog
$end
$timescale
	1ps
$end
$scope module test_timer $end
$var wire 1 ! zero $end
$var wire 4 " sec_tens [3:0] $end
$var wire 4 # sec_ones [3:0] $end
$var wire 4 $ mins [3:0] $end
$var reg 1 % clk $end
$var reg 1 & clrn $end
$var reg 4 ' data [3:0] $end
$var reg 1 ( en $end
$var reg 1 ) loadn $end
$scope module uut $end
$var wire 1 % clk $end
$var wire 1 & clrn $end
$var wire 4 * data [3:0] $end
$var wire 1 ( en $end
$var wire 1 ) loadn $end
$var wire 1 ! zero $end
$var wire 1 + zero_tens $end
$var wire 1 , zero_ones $end
$var wire 1 - zero_mins $end
$var wire 1 . tc_tens $end
$var wire 1 / tc_ones $end
$var wire 1 0 tc_mins $end
$var wire 4 1 sec_tens [3:0] $end
$var wire 4 2 sec_ones [3:0] $end
$var wire 4 3 mins [3:0] $end
$scope module mins_module $end
$var wire 1 % clk $end
$var wire 1 & clrn $end
$var wire 1 ) loadn $end
$var wire 1 . en $end
$var wire 4 4 data [3:0] $end
$var reg 4 5 out [3:0] $end
$var reg 1 0 tc $end
$var reg 1 - zero $end
$upscope $end
$scope module sec_ones_module $end
$var wire 1 % clk $end
$var wire 1 & clrn $end
$var wire 4 6 data [3:0] $end
$var wire 1 ( en $end
$var wire 1 ) loadn $end
$var reg 4 7 out [3:0] $end
$var reg 1 / tc $end
$var reg 1 , zero $end
$upscope $end
$scope module sec_tens_module $end
$var wire 1 % clk $end
$var wire 1 & clrn $end
$var wire 4 8 data [3:0] $end
$var wire 1 / en $end
$var wire 1 ) loadn $end
$var reg 4 9 out [3:0] $end
$var reg 1 . tc $end
$var reg 1 + zero $end
$upscope $end
$upscope $end
$upscope $end
$enddefinitions $end
#0
$dumpvars
bx 9
b1001 8
b1001 7
b1001 6
bx 5
bx 4
bx 3
b1001 2
bx 1
x0
x/
x.
x-
x,
x+
b1001 *
0)
1(
b1001 '
1&
1%
bx $
b1001 #
bx "
x!
$end
#1000
0%
#2000
b1001 "
b1001 1
b1001 4
b1001 9
b11 #
b11 2
b11 7
b11 8
1%
b11 '
b11 *
b11 6
#3000
0%
#4000
b10 #
b10 2
b10 7
b10 8
b11 "
b11 1
b11 4
b11 9
b1001 $
b1001 3
b1001 5
1%
b10 '
b10 *
b10 6
#5000
0%
#6000
0!
00
0.
0/
0,
b1 #
b1 2
b1 7
b1 8
1%
b11 '
b11 *
b11 6
1)
#7000
0%
#8000
1/
b0 #
b0 2
b0 7
b0 8
1%
#9000
0%
#10000
0+
b10 "
b10 1
b10 4
b10 9
0/
1,
b1001 #
b1001 2
b1001 7
b1001 8
1%
#11000
0%
#12000
0,
b1000 #
b1000 2
b1000 7
b1000 8
1%
#13000
0%
#14000
b111 #
b111 2
b111 7
b111 8
1%
#15000
0%
#16000
b110 #
b110 2
b110 7
b110 8
1%
#17000
0%
#18000
b101 #
b101 2
b101 7
b101 8
1%
#19000
0%
#20000
b100 #
b100 2
b100 7
b100 8
1%
#21000
0%
#22000
b11 #
b11 2
b11 7
b11 8
1%
#23000
0%
#24000
b10 #
b10 2
b10 7
b10 8
1%
#25000
0%
#26000
b1 #
b1 2
b1 7
b1 8
1%
#27000
0%
#28000
1/
b0 #
b0 2
b0 7
b0 8
1%
#29000
0%
#30000
b1 "
b1 1
b1 4
b1 9
0/
1,
b1001 #
b1001 2
b1001 7
b1001 8
1%
#31000
0%
#32000
0,
b1000 #
b1000 2
b1000 7
b1000 8
1%
#33000
0%
#34000
b111 #
b111 2
b111 7
b111 8
1%
#35000
0%
#36000
b110 #
b110 2
b110 7
b110 8
1%
#37000
0%
#38000
b101 #
b101 2
b101 7
b101 8
1%
#39000
0%
#40000
b100 #
b100 2
b100 7
b100 8
1%
#41000
0%
#42000
b11 #
b11 2
b11 7
b11 8
1%
#43000
0%
#44000
b10 #
b10 2
b10 7
b10 8
1%
#45000
0%
#46000
b1 #
b1 2
b1 7
b1 8
1%
#47000
0%
#48000
1/
b0 #
b0 2
b0 7
b0 8
1%
#49000
0%
#50000
b0 "
b0 1
b0 4
b0 9
0/
1,
b1001 #
b1001 2
b1001 7
b1001 8
1%
#51000
0%
#52000
0,
b1000 #
b1000 2
b1000 7
b1000 8
1%
#53000
0%
#54000
b111 #
b111 2
b111 7
b111 8
1%
#55000
0%
#56000
b110 #
b110 2
b110 7
b110 8
1%
#57000
0%
#58000
b101 #
b101 2
b101 7
b101 8
1%
#59000
0%
#60000
b100 #
b100 2
b100 7
b100 8
1%
#61000
0%
#62000
b11 #
b11 2
b11 7
b11 8
1%
#63000
0%
#64000
b10 #
b10 2
b10 7
b10 8
1%
#65000
0%
#66000
b1 #
b1 2
b1 7
b1 8
1%
#67000
0%
#68000
1/
b0 #
b0 2
b0 7
b0 8
1%
#69000
0%
#70000
0-
b1000 $
b1000 3
b1000 5
0/
1,
b1001 #
b1001 2
b1001 7
b1001 8
1+
b101 "
b101 1
b101 4
b101 9
1%
0.
#71000
0%
#72000
0,
b1000 #
b1000 2
b1000 7
b1000 8
1%
#73000
0%
#74000
b111 #
b111 2
b111 7
b111 8
1%
#75000
0%
#76000
b110 #
b110 2
b110 7
b110 8
1%
#77000
0%
#78000
b101 #
b101 2
b101 7
b101 8
1%
#79000
0%
#80000
b100 #
b100 2
b100 7
b100 8
1%
#81000
0%
#82000
b11 #
b11 2
b11 7
b11 8
1%
#83000
0%
#84000
b10 #
b10 2
b10 7
b10 8
1%
#85000
0%
#86000
b1 #
b1 2
b1 7
b1 8
1%
#87000
0%
#88000
1/
b0 #
b0 2
b0 7
b0 8
1%
#89000
0%
#90000
0/
1,
b1001 #
b1001 2
b1001 7
b1001 8
0+
b100 "
b100 1
b100 4
b100 9
1%
#91000
0%
#92000
0,
b1000 #
b1000 2
b1000 7
b1000 8
1%
#93000
0%
#94000
b111 #
b111 2
b111 7
b111 8
1%
#95000
0%
#96000
b110 #
b110 2
b110 7
b110 8
1%
#97000
0%
#98000
b101 #
b101 2
b101 7
b101 8
1%
#99000
0%
#100000
b100 #
b100 2
b100 7
b100 8
1%
#101000
0%
#102000
b11 #
b11 2
b11 7
b11 8
1%
#103000
0%
#104000
b10 #
b10 2
b10 7
b10 8
1%
#105000
0%
#106000
b1 #
b1 2
b1 7
b1 8
1%
#107000
0%
#108000
1/
b0 #
b0 2
b0 7
b0 8
1%
#109000
0%
#110000
0/
1,
b1001 #
b1001 2
b1001 7
b1001 8
b11 "
b11 1
b11 4
b11 9
1%
#111000
0%
#112000
0,
b1000 #
b1000 2
b1000 7
b1000 8
1%
#113000
0%
#114000
b111 #
b111 2
b111 7
b111 8
1%
#115000
0%
#116000
b110 #
b110 2
b110 7
b110 8
1%
#117000
0%
#118000
b101 #
b101 2
b101 7
b101 8
1%
#119000
0%
#120000
b100 #
b100 2
b100 7
b100 8
1%
#121000
0%
#122000
b11 #
b11 2
b11 7
b11 8
1%
#123000
0%
#124000
b10 #
b10 2
b10 7
b10 8
1%
#125000
0%
#126000
b1 #
b1 2
b1 7
b1 8
1%
#127000
0%
#128000
1/
b0 #
b0 2
b0 7
b0 8
1%
#129000
0%
#130000
0/
1,
b1001 #
b1001 2
b1001 7
b1001 8
b10 "
b10 1
b10 4
b10 9
1%
#131000
0%
#132000
0,
b1000 #
b1000 2
b1000 7
b1000 8
1%
#133000
0%
#134000
b111 #
b111 2
b111 7
b111 8
1%
#135000
0%
#136000
b110 #
b110 2
b110 7
b110 8
1%
#137000
0%
#138000
b101 #
b101 2
b101 7
b101 8
1%
#139000
0%
#140000
b100 #
b100 2
b100 7
b100 8
1%
#141000
0%
#142000
b11 #
b11 2
b11 7
b11 8
1%
#143000
0%
#144000
b10 #
b10 2
b10 7
b10 8
1%
#145000
0%
#146000
b1 #
b1 2
b1 7
b1 8
1%
#147000
0%
#148000
1/
b0 #
b0 2
b0 7
b0 8
1%
#149000
0%
#150000
0/
1,
b1001 #
b1001 2
b1001 7
b1001 8
b1 "
b1 1
b1 4
b1 9
1%
#151000
0%
#152000
0,
b1000 #
b1000 2
b1000 7
b1000 8
1%
#153000
0%
#154000
b111 #
b111 2
b111 7
b111 8
1%
#155000
0%
#156000
b110 #
b110 2
b110 7
b110 8
1%
#157000
0%
#158000
b101 #
b101 2
b101 7
b101 8
1%
#159000
0%
#160000
b100 #
b100 2
b100 7
b100 8
1%
#161000
0%
#162000
b11 #
b11 2
b11 7
b11 8
1%
#163000
0%
#164000
b10 #
b10 2
b10 7
b10 8
1%
#165000
0%
#166000
b1 #
b1 2
b1 7
b1 8
1%
#167000
0%
#168000
1/
b0 #
b0 2
b0 7
b0 8
1%
#169000
0%
#170000
0/
1,
b1001 #
b1001 2
b1001 7
b1001 8
b0 "
b0 1
b0 4
b0 9
1%
#171000
0%
#172000
0,
b1000 #
b1000 2
b1000 7
b1000 8
1%
#173000
0%
#174000
b111 #
b111 2
b111 7
b111 8
1%
#175000
0%
#176000
b110 #
b110 2
b110 7
b110 8
1%
#177000
0%
#178000
b101 #
b101 2
b101 7
b101 8
1%
#179000
0%
#180000
b100 #
b100 2
b100 7
b100 8
1%
#181000
0%
#182000
b11 #
b11 2
b11 7
b11 8
1%
#183000
0%
#184000
b10 #
b10 2
b10 7
b10 8
1%
#185000
0%
#186000
b1 #
b1 2
b1 7
b1 8
1%
#187000
0%
#188000
1/
b0 #
b0 2
b0 7
b0 8
1%
#189000
0%
#190000
b111 $
b111 3
b111 5
0/
1,
b1001 #
b1001 2
b1001 7
b1001 8
1+
b101 "
b101 1
b101 4
b101 9
1%
0.
#191000
0%
#192000
0,
b1000 #
b1000 2
b1000 7
b1000 8
1%
#193000
0%
#194000
b111 #
b111 2
b111 7
b111 8
1%
#195000
0%
#196000
b110 #
b110 2
b110 7
b110 8
1%
#197000
0%
#198000
b101 #
b101 2
b101 7
b101 8
1%
#199000
0%
#200000
b100 #
b100 2
b100 7
b100 8
1%
#201000
0%
#202000
b11 #
b11 2
b11 7
b11 8
1%
#203000
0%
#204000
b10 #
b10 2
b10 7
b10 8
1%
#205000
0%
#206000
b1 #
b1 2
b1 7
b1 8
1%
#207000
0%
#208000
1/
b0 #
b0 2
b0 7
b0 8
1%
#209000
0%
#210000
0/
1,
b1001 #
b1001 2
b1001 7
b1001 8
0+
b100 "
b100 1
b100 4
b100 9
1%
#211000
0%
#212000
0,
b1000 #
b1000 2
b1000 7
b1000 8
1%
#213000
0%
#214000
b111 #
b111 2
b111 7
b111 8
1%
#215000
0%
#216000
b110 #
b110 2
b110 7
b110 8
1%
#217000
0%
#218000
b101 #
b101 2
b101 7
b101 8
1%
#219000
0%
#220000
b100 #
b100 2
b100 7
b100 8
1%
#221000
0%
#222000
b11 #
b11 2
b11 7
b11 8
1%
#223000
0%
#224000
b10 #
b10 2
b10 7
b10 8
1%
#225000
0%
#226000
b1 #
b1 2
b1 7
b1 8
1%
#227000
0%
#228000
1/
b0 #
b0 2
b0 7
b0 8
1%
#229000
0%
#230000
0/
1,
b1001 #
b1001 2
b1001 7
b1001 8
b11 "
b11 1
b11 4
b11 9
1%
#231000
0%
#232000
0,
b1000 #
b1000 2
b1000 7
b1000 8
1%
#233000
0%
#234000
b111 #
b111 2
b111 7
b111 8
1%
#235000
0%
#236000
b110 #
b110 2
b110 7
b110 8
1%
#237000
0%
#238000
b101 #
b101 2
b101 7
b101 8
1%
#239000
0%
#240000
b100 #
b100 2
b100 7
b100 8
1%
#241000
0%
#242000
b11 #
b11 2
b11 7
b11 8
1%
#243000
0%
#244000
b10 #
b10 2
b10 7
b10 8
1%
#245000
0%
#246000
b1 #
b1 2
b1 7
b1 8
1%
#247000
0%
#248000
1/
b0 #
b0 2
b0 7
b0 8
1%
#249000
0%
#250000
0/
1,
b1001 #
b1001 2
b1001 7
b1001 8
b10 "
b10 1
b10 4
b10 9
1%
#251000
0%
#252000
0,
b1000 #
b1000 2
b1000 7
b1000 8
1%
#253000
0%
#254000
b111 #
b111 2
b111 7
b111 8
1%
#255000
0%
#256000
b110 #
b110 2
b110 7
b110 8
1%
#257000
0%
#258000
b101 #
b101 2
b101 7
b101 8
1%
#259000
0%
#260000
b100 #
b100 2
b100 7
b100 8
1%
#261000
0%
#262000
b11 #
b11 2
b11 7
b11 8
1%
#263000
0%
#264000
b10 #
b10 2
b10 7
b10 8
1%
#265000
0%
#266000
b1 #
b1 2
b1 7
b1 8
1%
#267000
0%
#268000
1/
b0 #
b0 2
b0 7
b0 8
1%
#269000
0%
#270000
0/
1,
b1001 #
b1001 2
b1001 7
b1001 8
b1 "
b1 1
b1 4
b1 9
1%
#271000
0%
#272000
0,
b1000 #
b1000 2
b1000 7
b1000 8
1%
#273000
0%
#274000
b111 #
b111 2
b111 7
b111 8
1%
#275000
0%
#276000
b110 #
b110 2
b110 7
b110 8
1%
#277000
0%
#278000
b101 #
b101 2
b101 7
b101 8
1%
#279000
0%
#280000
b100 #
b100 2
b100 7
b100 8
1%
#281000
0%
#282000
b11 #
b11 2
b11 7
b11 8
1%
#283000
0%
#284000
b10 #
b10 2
b10 7
b10 8
1%
#285000
0%
#286000
b1 #
b1 2
b1 7
b1 8
1%
#287000
0%
#288000
1/
b0 #
b0 2
b0 7
b0 8
1%
#289000
0%
#290000
0/
1,
b1001 #
b1001 2
b1001 7
b1001 8
b0 "
b0 1
b0 4
b0 9
1%
#291000
0%
#292000
0,
b1000 #
b1000 2
b1000 7
b1000 8
1%
#293000
0%
#294000
b111 #
b111 2
b111 7
b111 8
1%
#295000
0%
#296000
b110 #
b110 2
b110 7
b110 8
1%
#297000
0%
#298000
b101 #
b101 2
b101 7
b101 8
1%
#299000
0%
#300000
b100 #
b100 2
b100 7
b100 8
1%
#301000
0%
#302000
b11 #
b11 2
b11 7
b11 8
1%
#303000
0%
#304000
b10 #
b10 2
b10 7
b10 8
1%
#305000
0%
#306000
b1 #
b1 2
b1 7
b1 8
1%
#307000
0%
#308000
1/
b0 #
b0 2
b0 7
b0 8
1%
#309000
0%
#310000
b110 $
b110 3
b110 5
0/
1,
b1001 #
b1001 2
b1001 7
b1001 8
1+
b101 "
b101 1
b101 4
b101 9
1%
0.
#311000
0%
#312000
0,
b1000 #
b1000 2
b1000 7
b1000 8
1%
#313000
0%
#314000
b111 #
b111 2
b111 7
b111 8
1%
#315000
0%
#316000
b110 #
b110 2
b110 7
b110 8
1%
#317000
0%
#318000
b101 #
b101 2
b101 7
b101 8
1%
#319000
0%
#320000
b100 #
b100 2
b100 7
b100 8
1%
#321000
0%
#322000
b11 #
b11 2
b11 7
b11 8
1%
#323000
0%
#324000
b10 #
b10 2
b10 7
b10 8
1%
#325000
0%
#326000
b1 #
b1 2
b1 7
b1 8
1%
#327000
0%
#328000
1/
b0 #
b0 2
b0 7
b0 8
1%
#329000
0%
#330000
0/
1,
b1001 #
b1001 2
b1001 7
b1001 8
0+
b100 "
b100 1
b100 4
b100 9
1%
#331000
0%
#332000
0,
b1000 #
b1000 2
b1000 7
b1000 8
1%
#333000
0%
#334000
b111 #
b111 2
b111 7
b111 8
1%
#335000
0%
#336000
b110 #
b110 2
b110 7
b110 8
1%
#337000
0%
#338000
b101 #
b101 2
b101 7
b101 8
1%
#339000
0%
#340000
b100 #
b100 2
b100 7
b100 8
1%
#341000
0%
#342000
b11 #
b11 2
b11 7
b11 8
1%
#343000
0%
#344000
b10 #
b10 2
b10 7
b10 8
1%
#345000
0%
#346000
b1 #
b1 2
b1 7
b1 8
1%
#347000
0%
#348000
1/
b0 #
b0 2
b0 7
b0 8
1%
#349000
0%
#350000
0/
1,
b1001 #
b1001 2
b1001 7
b1001 8
b11 "
b11 1
b11 4
b11 9
1%
#351000
0%
#352000
0,
b1000 #
b1000 2
b1000 7
b1000 8
1%
#353000
0%
#354000
b111 #
b111 2
b111 7
b111 8
1%
#355000
0%
#356000
b110 #
b110 2
b110 7
b110 8
1%
#357000
0%
#358000
b101 #
b101 2
b101 7
b101 8
1%
#359000
0%
#360000
b100 #
b100 2
b100 7
b100 8
1%
#361000
0%
#362000
b11 #
b11 2
b11 7
b11 8
1%
#363000
0%
#364000
b10 #
b10 2
b10 7
b10 8
1%
#365000
0%
#366000
b1 #
b1 2
b1 7
b1 8
1%
#367000
0%
#368000
1/
b0 #
b0 2
b0 7
b0 8
1%
#369000
0%
#370000
0/
1,
b1001 #
b1001 2
b1001 7
b1001 8
b10 "
b10 1
b10 4
b10 9
1%
#371000
0%
#372000
0,
b1000 #
b1000 2
b1000 7
b1000 8
1%
#373000
0%
#374000
b111 #
b111 2
b111 7
b111 8
1%
#375000
0%
#376000
b110 #
b110 2
b110 7
b110 8
1%
#377000
0%
#378000
b101 #
b101 2
b101 7
b101 8
1%
#379000
0%
#380000
b100 #
b100 2
b100 7
b100 8
1%
#381000
0%
#382000
b11 #
b11 2
b11 7
b11 8
1%
#383000
0%
#384000
b10 #
b10 2
b10 7
b10 8
1%
#385000
0%
#386000
b1 #
b1 2
b1 7
b1 8
1%
#387000
0%
#388000
1/
b0 #
b0 2
b0 7
b0 8
1%
#389000
0%
#390000
0/
1,
b1001 #
b1001 2
b1001 7
b1001 8
b1 "
b1 1
b1 4
b1 9
1%
#391000
0%
#392000
0,
b1000 #
b1000 2
b1000 7
b1000 8
1%
#393000
0%
#394000
b111 #
b111 2
b111 7
b111 8
1%
#395000
0%
#396000
b110 #
b110 2
b110 7
b110 8
1%
#397000
0%
#398000
b101 #
b101 2
b101 7
b101 8
1%
#399000
0%
#400000
b100 #
b100 2
b100 7
b100 8
1%
#401000
0%
#402000
b11 #
b11 2
b11 7
b11 8
1%
#403000
0%
#404000
b10 #
b10 2
b10 7
b10 8
1%
#405000
0%
#406000
b1 #
b1 2
b1 7
b1 8
1%
#407000
0%
#408000
1/
b0 #
b0 2
b0 7
b0 8
1%
#409000
0%
#410000
0/
1,
b1001 #
b1001 2
b1001 7
b1001 8
b0 "
b0 1
b0 4
b0 9
1%
#411000
0%
#412000
0,
b1000 #
b1000 2
b1000 7
b1000 8
1%
#413000
0%
#414000
b111 #
b111 2
b111 7
b111 8
1%
#415000
0%
#416000
b110 #
b110 2
b110 7
b110 8
1%
#417000
0%
#418000
b101 #
b101 2
b101 7
b101 8
1%
#419000
0%
#420000
b100 #
b100 2
b100 7
b100 8
1%
#421000
0%
#422000
b11 #
b11 2
b11 7
b11 8
1%
#423000
0%
#424000
b10 #
b10 2
b10 7
b10 8
1%
#425000
0%
#426000
b1 #
b1 2
b1 7
b1 8
1%
#427000
0%
#428000
1/
b0 #
b0 2
b0 7
b0 8
1%
#429000
0%
#430000
b101 $
b101 3
b101 5
0/
1,
b1001 #
b1001 2
b1001 7
b1001 8
1+
b101 "
b101 1
b101 4
b101 9
1%
0.
#431000
0%
#432000
0,
b1000 #
b1000 2
b1000 7
b1000 8
1%
#433000
0%
#434000
b111 #
b111 2
b111 7
b111 8
1%
#435000
0%
#436000
b110 #
b110 2
b110 7
b110 8
1%
#437000
0%
#438000
b101 #
b101 2
b101 7
b101 8
1%
#439000
0%
#440000
b100 #
b100 2
b100 7
b100 8
1%
#441000
0%
#442000
b11 #
b11 2
b11 7
b11 8
1%
#443000
0%
#444000
b10 #
b10 2
b10 7
b10 8
1%
#445000
0%
#446000
b1 #
b1 2
b1 7
b1 8
1%
#447000
0%
#448000
1/
b0 #
b0 2
b0 7
b0 8
1%
#449000
0%
#450000
0/
1,
b1001 #
b1001 2
b1001 7
b1001 8
0+
b100 "
b100 1
b100 4
b100 9
1%
#451000
0%
#452000
0,
b1000 #
b1000 2
b1000 7
b1000 8
1%
#453000
0%
#454000
b111 #
b111 2
b111 7
b111 8
1%
#455000
0%
#456000
b110 #
b110 2
b110 7
b110 8
1%
#457000
0%
#458000
b101 #
b101 2
b101 7
b101 8
1%
#459000
0%
#460000
b100 #
b100 2
b100 7
b100 8
1%
#461000
0%
#462000
b11 #
b11 2
b11 7
b11 8
1%
#463000
0%
#464000
b10 #
b10 2
b10 7
b10 8
1%
#465000
0%
#466000
b1 #
b1 2
b1 7
b1 8
1%
#467000
0%
#468000
1/
b0 #
b0 2
b0 7
b0 8
1%
#469000
0%
#470000
0/
1,
b1001 #
b1001 2
b1001 7
b1001 8
b11 "
b11 1
b11 4
b11 9
1%
#471000
0%
#472000
0,
b1000 #
b1000 2
b1000 7
b1000 8
1%
#473000
0%
#474000
b111 #
b111 2
b111 7
b111 8
1%
#475000
0%
#476000
b110 #
b110 2
b110 7
b110 8
1%
#477000
0%
#478000
b101 #
b101 2
b101 7
b101 8
1%
#479000
0%
#480000
b100 #
b100 2
b100 7
b100 8
1%
#481000
0%
#482000
b11 #
b11 2
b11 7
b11 8
1%
#483000
0%
#484000
b10 #
b10 2
b10 7
b10 8
1%
#485000
0%
#486000
b1 #
b1 2
b1 7
b1 8
1%
#487000
0%
#488000
1/
b0 #
b0 2
b0 7
b0 8
1%
#489000
0%
#490000
0/
1,
b1001 #
b1001 2
b1001 7
b1001 8
b10 "
b10 1
b10 4
b10 9
1%
#491000
0%
#492000
0,
b1000 #
b1000 2
b1000 7
b1000 8
1%
#493000
0%
#494000
b111 #
b111 2
b111 7
b111 8
1%
#495000
0%
#496000
b110 #
b110 2
b110 7
b110 8
1%
#497000
0%
#498000
b101 #
b101 2
b101 7
b101 8
1%
#499000
0%
#500000
b100 #
b100 2
b100 7
b100 8
1%
#501000
0%
#502000
b11 #
b11 2
b11 7
b11 8
1%
#503000
0%
#504000
b10 #
b10 2
b10 7
b10 8
1%
#505000
0%
#506000
b1 #
b1 2
b1 7
b1 8
1%
