src/control/latch.v
`timescale 1ns/1ps

module latch (
    input wire R,
    input wire S,
    output reg mag

);

    always @(R or S)
    begin
        
        if(R && !S)
            begin
                mag <= 0;
            end
        else if(S && !R)
            begin
                mag <= 1;
            end
  
      
    end




endmodule

src/control/logic_control.v
`timescale 1ns/1ps

module logic_control (
    input wire startn,
    input wire stopn,
    input wire clearn,
    input wire door_closed,
    input wire timer_done,
    output reg R,
    output reg S

);

    

    always @(startn or stopn or clearn or door_closed or timer_done)
    begin
        if(!clearn || !stopn || timer_done || !door_closed)
            begin
                S = 0;
                R = 1;
            end
        else if(!startn && door_closed)
            begin
                S = 1;
                R = 0;
            end
        else begin
            S = 0;
            R = 0;
        end

      
    end




endmodule

src/control/control.v
`timescale 1ns/1ps

module control (
    startn,stopn,clearn,door_closed,timer_done,
    mag
);

    input  startn,stopn,clearn,door_closed,timer_done;
    output mag;
    wire  R,S;



    logic_control controle(.startn(startn),.stopn(stopn),.clearn(clearn),.door_closed(door_closed),.timer_done(timer_done),.S(S),.R(R));
    latch SR(.S(S),.R(R),.mag(mag));


endmodule

testbenches/tb_control.v
`timescale 1ns/1ps

module tb_control;

    reg startn,stopn,clearn,door_closed,timer_done;
    wire mag;
    integer i;
    
    control c(.startn(startn),.stopn(stopn),.clearn(clearn),.door_closed(door_closed),.timer_done(timer_done),.mag(mag));

    initial begin

        for(i = 0; i<3000;i = i+1)begin
            startn = 1; 
            stopn =1;
            clearn = 1;
            door_closed =  1;
            timer_done =  0;
            #2;
            $display("Start: %b, Stop: %b, clearn: %b, boor_closeb: %b, timer_bone: %b",startn,stopn,clearn,door_closed,timer_done); 
            #2;
            $display("Mag : %b",mag); 
            #20;
        end
          

    end

    initial begin
        $dumpfile("vcd/control.vcd");
        $dumpvars;
    end
    
    


endmodule

vcd/control.vcd
$date
	Thu Apr 29 16:38:11 2021
$end
$version
	Icarus Verilog
$end
$timescale
	1ps
$end
$scope module tb_control $end
$var wire 1 ! mag $end
$var reg 1 " clearn $end
$var reg 1 # door_closed $end
$var reg 1 $ startn $end
$var reg 1 % stopn $end
$var reg 1 & timer_done $end
$var integer 32 ' i [31:0] $end
$scope module c $end
$var wire 1 " clearn $end
$var wire 1 # door_closed $end
$var wire 1 $ startn $end
$var wire 1 % stopn $end
$var wire 1 & timer_done $end
$var wire 1 ! mag $end
$var wire 1 ( S $end
$var wire 1 ) R $end
$scope module SR $end
$var wire 1 ( S $end
$var wire 1 ) R $end
$var reg 1 ! mag $end
$upscope $end
$scope module controle $end
$var wire 1 " clearn $end
$var wire 1 # door_closed $end
$var wire 1 $ startn $end
$var wire 1 % stopn $end
$var wire 1 & timer_done $end
$var reg 1 ) R $end
$var reg 1 ( S $end
$upscope $end
$upscope $end
$upscope $end
$enddefinitions $end
#0
$dumpvars
1)
0(
bx '
0&
0%
1$
1#
0"
0!
$end
#24000
1!
0)
1(
1"
1%
0$
#48000
0(
1$
b0 '
#72000
b1 '
#96000
b10 '
#120000
b11 '
#144000
b100 '
#168000
b101 '
#192000
b110 '
#216000
b111 '
#240000
b1000 '
#264000
b1001 '
#288000
b1010 '
#312000
b1011 '
#336000
b1100 '
#360000
b1101 '
#384000
b1110 '
#408000
b1111 '
#432000
b10000 '
#456000
b10001 '
#480000
b10010 '
#504000
b10011 '
#528000
b10100 '
#552000
b10101 '
#576000
b10110 '
#600000
b10111 '
#624000
b11000 '
#648000
b11001 '
#672000
b11010 '
#696000
b11011 '
#720000
b11100 '
#744000
b11101 '
#768000
b11110 '
#792000
b11111 '
#816000
b100000 '
#840000
b100001 '
#864000
b100010 '
#888000
b100011 '
#912000
b100100 '
#936000
b100101 '
#960000
b100110 '
#984000
b100111 '
#1008000
b101000 '
#1032000
b101001 '
#1056000
b101010 '
#1080000
b101011 '
#1104000
b101100 '
#1128000
b101101 '
#1152000
b101110 '
#1176000
b101111 '
#1200000
b110000 '
#1224000
b110001 '
#1248000
b110010 '
#1272000
b110011 '
#1296000
b110100 '
#1320000
b110101 '
#1344000
b110110 '
#1368000
b110111 '
#1392000
b111000 '
#1416000
b111001 '
#1440000
b111010 '
#1464000
b111011 '
#1488000
b111100 '
#1512000
b111101 '
#1536000
b111110 '
#1560000
b111111 '
#1584000
b1000000 '
#1608000
b1000001 '
#1632000
b1000010 '
#1656000
b1000011 '
#1680000
b1000100 '
#1704000
b1000101 '
#1728000
b1000110 '
#1752000
b1000111 '
#1776000
b1001000 '
#1800000
b1001001 '
#1824000
b1001010 '
#1848000
b1001011 '
#1872000
b1001100 '
#1896000
b1001101 '
#1920000
b1001110 '
#1944000
b1001111 '
#1968000
b1010000 '
#1992000
b1010001 '
#2016000
b1010010 '
#2040000
b1010011 '
#2064000
b1010100 '
#2088000
b1010101 '
#2112000
b1010110 '
#2136000
b1010111 '
#2160000
b1011000 '
#2184000
b1011001 '
#2208000
b1011010 '
#2232000
b1011011 '
#2256000
b1011100 '
#2280000
b1011101 '
#2304000
b1011110 '
#2328000
b1011111 '
#2352000
b1100000 '
#2376000
b1100001 '
#2400000
b1100010 '
#2424000
b1100011 '
#2448000
b1100100 '
#2472000
b1100101 '
#2496000
b1100110 '
#2520000
b1100111 '
#2544000
b1101000 '
#2568000
b1101001 '
#2592000
b1101010 '
#2616000
b1101011 '
#2640000
b1101100 '
#2664000
b1101101 '
#2688000
b1101110 '
#2712000
b1101111 '
#2736000
b1110000 '
#2760000
b1110001 '
#2784000
b1110010 '
#2808000
b1110011 '
#2832000
b1110100 '
#2856000
b1110101 '
#2880000
b1110110 '
#2904000
b1110111 '
#2928000
b1111000 '
#2952000
b1111001 '
#2976000
b1111010 '
#3000000
b1111011 '
#3024000
b1111100 '
#3048000
b1111101 '
#3072000
b1111110 '
#3096000
b1111111 '
#3120000
b10000000 '
#3144000
b10000001 '
#3168000
b10000010 '
#3192000
b10000011 '
#3216000
b10000100 '
#3240000
b10000101 '
#3264000
b10000110 '
#3288000
b10000111 '
#3312000
b10001000 '
#3336000
b10001001 '
#3360000
b10001010 '
#3384000
b10001011 '
#3408000
b10001100 '
#3432000
b10001101 '
#3456000
b10001110 '
#3480000
b10001111 '
#3504000
b10010000 '
#3528000
b10010001 '
#3552000
b10010010 '
#3576000
b10010011 '
#3600000
b10010100 '
#3624000
b10010101 '
#3648000
b10010110 '
#3672000
b10010111 '
#3696000
b10011000 '
#3720000
b10011001 '
#3744000
b10011010 '
#3768000
b10011011 '
#3792000
b10011100 '
#3816000
b10011101 '
#3840000
b10011110 '
#3864000
b10011111 '
#3888000
b10100000 '
#3912000
b10100001 '
#3936000
b10100010 '
#3960000
b10100011 '
#3984000
b10100100 '
#4008000
b10100101 '
#4032000
b10100110 '
#4056000
b10100111 '
#4080000
b10101000 '
#4104000
b10101001 '
#4128000
b10101010 '
#4152000
b10101011 '
#4176000
b10101100 '
#4200000
b10101101 '
#4224000
b10101110 '
#4248000
b10101111 '
#4272000
b10110000 '
#4296000
b10110001 '
#4320000
b10110010 '
#4344000
b10110011 '
#4368000
b10110100 '
#4392000
b10110101 '
#4416000
b10110110 '
#4440000
b10110111 '
#4464000
b10111000 '
#4488000
b10111001 '
#4512000
b10111010 '
#4536000
b10111011 '
#4560000
b10111100 '
#4584000
b10111101 '
#4608000
b10111110 '
#4632000
b10111111 '
#4656000
b11000000 '
#4680000
b11000001 '
#4704000
b11000010 '
#4728000
b11000011 '
#4752000
b11000100 '
#4776000
b11000101 '
#4800000
b11000110 '
#4824000
b11000111 '
#4848000
b11001000 '
#4872000
b11001001 '
#4896000
b11001010 '
#4920000
b11001011 '
#4944000
b11001100 '
#4968000
b11001101 '
#4992000
b11001110 '
#5016000
b11001111 '
#5040000
b11010000 '
#5064000
b11010001 '
#5088000
b11010010 '
#5112000
b11010011 '
#5136000
b11010100 '
#5160000
b11010101 '
#5184000
b11010110 '
#5208000
b11010111 '
#5232000
b11011000 '
#5256000
b11011001 '
#5280000
b11011010 '
#5304000
b11011011 '
#5328000
b11011100 '
#5352000
b11011101 '
#5376000
b11011110 '
#5400000
b11011111 '
#5424000
b11100000 '
#5448000
b11100001 '
#5472000
b11100010 '
#5496000
b11100011 '
#5520000
b11100100 '
#5544000
b11100101 '
#5568000
b11100110 '
#5592000
b11100111 '
#5616000
b11101000 '
#5640000
b11101001 '
#5664000
b11101010 '
#5688000
b11101011 '
#5712000
b11101100 '
#5736000
b11101101 '
#5760000
b11101110 '
#5784000
b11101111 '
#5808000
b11110000 '
#5832000
b11110001 '
#5856000
b11110010 '
#5880000
b11110011 '
#5904000
b11110100 '
#5928000
b11110101 '
#5952000
b11110110 '
#5976000
b11110111 '
#6000000
b11111000 '
#6024000
b11111001 '
#6048000
b11111010 '
#6072000
b11111011 '
#6096000
b11111100 '
#6120000
b11111101 '
#6144000
b11111110 '
#6168000
b11111111 '
#6192000
b100000000 '
#6216000
b100000001 '
#6240000
b100000010 '
#6264000
b100000011 '
#6288000
b100000100 '
#6312000
b100000101 '
#6336000
b100000110 '
#6360000
b100000111 '
#6384000
b100001000 '
#6408000
b100001001 '
#6432000
b100001010 '
#6456000
b100001011 '
#6480000
b100001100 '
#6504000
b100001101 '
#6528000
b100001110 '
#6552000
b100001111 '
#6576000
b100010000 '
#6600000
b100010001 '
#6624000
b100010010 '
#6648000
b100010011 '
#6672000
b100010100 '
#6696000
b100010101 '
#6720000
b100010110 '
#6744000
b100010111 '
#6768000
b100011000 '
#6792000
b100011001 '
#6816000
b100011010 '
#6840000
b100011011 '
#6864000
b100011100 '
#6888000
b100011101 '
#6912000
b100011110 '
#6936000
b100011111 '
#6960000
b100100000 '
#6984000
b100100001 '
#7008000
b100100010 '
#7032000
b100100011 '
#7056000
b100100100 '
#7080000
b100100101 '
#7104000
b100100110 '
#7128000
b100100111 '
#7152000
b100101000 '
#7176000
b100101001 '
#7200000
b100101010 '
#7224000
b100101011 '
#7248000
b100101100 '
#7272000
b100101101 '
#7296000
b100101110 '
#7320000
b100101111 '
#7344000
b100110000 '
#7368000
b100110001 '
#7392000
b100110010 '
#7416000
b100110011 '
#7440000
b100110100 '
#7464000
b100110101 '
#7488000
b100110110 '
#7512000
b100110111 '
#7536000
b100111000 '
#7560000
b100111001 '
#7584000
b100111010 '
#7608000
b100111011 '
#7632000
b100111100 '
#7656000
b100111101 '
#7680000
b100111110 '
#7704000
b100111111 '
#7728000
b101000000 '
#7752000
b101000001 '
#7776000
b101000010 '
#7800000
b101000011 '
#7824000
b101000100 '
#7848000
b101000101 '
#7872000
b101000110 '
#7896000
b101000111 '
#7920000
b101001000 '
#7944000
b101001001 '
#7968000
b101001010 '
#7992000
b101001011 '
#8016000
b101001100 '
#8040000
b101001101 '
#8064000
b101001110 '
#8088000
b101001111 '
#8112000
b101010000 '
#8136000
b101010001 '
#8160000
b101010010 '
#8184000
b101010011 '
#8208000
b101010100 '
#8232000
b101010101 '
#8256000
b101010110 '
#8280000
b101010111 '
#8304000
b101011000 '
#8328000
b101011001 '
#8352000
b101011010 '
#8376000
b101011011 '
#8400000
b101011100 '
#8424000
b101011101 '
#8448000
b101011110 '
#8472000
b101011111 '
#8496000
b101100000 '
#8520000
b101100001 '
#8544000
b101100010 '
#8568000
b101100011 '
#8592000
b101100100 '
#8616000
b101100101 '
#8640000
b101100110 '
#8664000
b101100111 '
#8688000
b101101000 '
#8712000
b101101001 '
#8736000
b101101010 '
#8760000
b101101011 '
#8784000
b101101100 '
#8808000
b101101101 '
#8832000
b101101110 '
#8856000
b101101111 '
#8880000
b101110000 '
#8904000
b101110001 '
#8928000
b101110010 '
#8952000
b101110011 '
#8976000
b101110100 '
#9000000
b101110101 '
#9024000
b101110110 '
#9048000
b101110111 '
#9072000
b101111000 '
#9096000
b101111001 '
#9120000
b101111010 '
#9144000
b101111011 '
#9168000
b101111100 '
#9192000
b101111101 '
#9216000
b101111110 '
#9240000
b101111111 '
#9264000
b110000000 '
#9288000
b110000001 '
#9312000
b110000010 '
#9336000
b110000011 '
#9360000
b110000100 '
#9384000
b110000101 '
#9408000
b110000110 '
#9432000
b110000111 '
#9456000
b110001000 '
#9480000
b110001001 '
#9504000
b110001010 '
#9528000
b110001011 '
#9552000
b110001100 '
#9576000
b110001101 '
#9600000
b110001110 '
#9624000
b110001111 '
#9648000
b110010000 '
#9672000
b110010001 '
#9696000
b110010010 '
#9720000
b110010011 '
#9744000
b110010100 '
#9768000
b110010101 '
#9792000
b110010110 '
#9816000
b110010111 '
#9840000
b110011000 '
#9864000
b110011001 '
#9888000
b110011010 '
#9912000
b110011011 '
#9936000
b110011100 '
#9960000
b110011101 '
#9984000
b110011110 '
#10008000
b110011111 '
#10032000
b110100000 '
#10056000
b110100001 '
#10080000
b110100010 '
#10104000
b110100011 '
#10128000
b110100100 '
#10152000
b110100101 '
#10176000
b110100110 '
#10200000
b110100111 '
#10224000
b110101000 '
#10248000
b110101001 '
#10272000
b110101010 '
#10296000
b110101011 '
#10320000
b110101100 '
#10344000
b110101101 '
#10368000
b110101110 '
#10392000
b110101111 '
#10416000
b110110000 '
#10440000
b110110001 '
#10464000
b110110010 '
#10488000
b110110011 '
#10512000
b110110100 '
#10536000
b110110101 '
#10560000
b110110110 '
#10584000
b110110111 '
#10608000
b110111000 '
#10632000
b110111001 '
#10656000
b110111010 '
#10680000
b110111011 '
#10704000
b110111100 '
#10728000
b110111101 '
#10752000
b110111110 '
#10776000
b110111111 '
#10800000
b111000000 '
#10824000
b111000001 '
#10848000
b111000010 '
#10872000
b111000011 '
#10896000
b111000100 '
#10920000
b111000101 '
#10944000
b111000110 '
#10968000
b111000111 '
#10992000
b111001000 '
#11016000
b111001001 '
#11040000
b111001010 '
#11064000
b111001011 '
#11088000
b111001100 '
#11112000
b111001101 '
#11136000
b111001110 '
#11160000
b111001111 '
#11184000
b111010000 '
#11208000
b111010001 '
#11232000
b111010010 '
#11256000
b111010011 '
#11280000
b111010100 '
#11304000
b111010101 '
#11328000
b111010110 '
#11352000
b111010111 '
#11376000
b111011000 '
#11400000
b111011001 '
#11424000
b111011010 '
#11448000
b111011011 '
#11472000
b111011100 '
#11496000
b111011101 '
#11520000
b111011110 '
#11544000
b111011111 '
#11568000
b111100000 '
#11592000
b111100001 '
#11616000
b111100010 '
#11640000
b111100011 '
#11664000
b111100100 '
#11688000
b111100101 '
#11712000
b111100110 '
#11736000
b111100111 '
#11760000
b111101000 '
#11784000
b111101001 '
#11808000
b111101010 '
#11832000
b111101011 '
#11856000
b111101100 '
#11880000
b111101101 '
#11904000
b111101110 '
#11928000
b111101111 '
#11952000
b111110000 '
#11976000
b111110001 '
#12000000
b111110010 '
#12024000
b111110011 '
#12048000
b111110100 '
#12072000
b111110101 '
#12096000
b111110110 '
#12120000
b111110111 '
#12144000
b111111000 '
#12168000
b111111001 '
#12192000
b111111010 '
#12216000
b111111011 '
#12240000
b111111100 '
#12264000
b111111101 '
#12288000
b111111110 '
#12312000
b111111111 '
#12336000
b1000000000 '
#12360000
b1000000001 '
#12384000
b1000000010 '
#12408000
b1000000011 '
#12432000
b1000000100 '
#12456000
b1000000101 '
#12480000
b1000000110 '
#12504000
b1000000111 '
#12528000
b1000001000 '
#12552000
b1000001001 '
#12576000
b1000001010 '
#12600000
b1000001011 '
#12624000
b1000001100 '
#12648000
b1000001101 '
#12672000
b1000001110 '
#12696000
b1000001111 '
#12720000
b1000010000 '
#12744000
b1000010001 '
#12768000
b1000010010 '
#12792000
b1000010011 '
#12816000
b1000010100 '
#12840000
b1000010101 '
#12864000
b1000010110 '
#12888000
b1000010111 '
#12912000
b1000011000 '
#12936000
b1000011001 '
#12960000
b1000011010 '
#12984000
b1000011011 '
#13008000
b1000011100 '
#13032000
b1000011101 '
#13056000
b1000011110 '
#13080000
b1000011111 '
#13104000
b1000100000 '
#13128000
b1000100001 '
#13152000
b1000100010 '
#13176000
b1000100011 '
#13200000
b1000100100 '
#13224000
b1000100101 '
#13248000
b1000100110 '
#13272000
b1000100111 '
#13296000
b1000101000 '
#13320000
b1000101001 '
#13344000
b1000101010 '
#13368000
b1000101011 '
#13392000
b1000101100 '
#13416000
b1000101101 '
#13440000
b1000101110 '
#13464000
b1000101111 '
#13488000
b1000110000 '
#13512000
b1000110001 '
#13536000
b1000110010 '
#13560000
b1000110011 '
#13584000
b1000110100 '
#13608000
b1000110101 '
#13632000
b1000110110 '
#13656000
b1000110111 '
#13680000
b1000111000 '
#13704000
b1000111001 '
#13728000
b1000111010 '
#13752000
b1000111011 '
#13776000
b1000111100 '
#13800000
b1000111101 '
#13824000
b1000111110 '
#13848000
b1000111111 '
#13872000
b1001000000 '
#13896000
b1001000001 '
#13920000
b1001000010 '
#13944000
b1001000011 '
#13968000
b1001000100 '
#13992000
b1001000101 '
#14016000
b1001000110 '
#14040000
b1001000111 '
#14064000
b1001001000 '
#14088000
b1001001001 '
#14112000
b1001001010 '
#14136000
b1001001011 '
#14160000
b1001001100 '
#14184000
b1001001101 '
#14208000
b1001001110 '
#14232000
b1001001111 '
#14256000
b1001010000 '
#14280000
b1001010001 '
#14304000
b1001010010 '
#14328000
b1001010011 '
#14352000
b1001010100 '
#14376000
b1001010101 '
#14400000
b1001010110 '
#14424000
b1001010111 '
#14448000
b1001011000 '
#14472000
b1001011001 '
#14496000
b1001011010 '
#14520000
b1001011011 '
#14544000
b1001011100 '
#14568000
b1001011101 '
#14592000
b1001011110 '
#14616000
b1001011111 '
#14640000
b1001100000 '
#14664000
b1001100001 '
#14688000
b1001100010 '
#14712000
b1001100011 '
#14736000
b1001100100 '
#14760000
b1001100101 '
#14784000
b1001100110 '
#14808000
b1001100111 '
#14832000
b1001101000 '
#14856000
b1001101001 '
#14880000
b1001101010 '
#14904000
b1001101011 '
#14928000
b1001101100 '
#14952000
b1001101101 '
#14976000
b1001101110 '
#15000000
b1001101111 '
#15024000
b1001110000 '
#15048000
b1001110001 '
#15072000
b1001110010 '
#15096000
b1001110011 '
#15120000
b1001110100 '
#15144000
b1001110101 '
#15168000
b1001110110 '
#15192000
b1001110111 '
#15216000
b1001111000 '
#15240000
b1001111001 '
#15264000
b1001111010 '
#15288000
b1001111011 '
#15312000
b1001111100 '
#15336000
b1001111101 '
#15360000
b1001111110 '
#15384000
b1001111111 '
#15408000
b1010000000 '
#15432000
b1010000001 '
#15456000
b1010000010 '
#15480000
b1010000011 '
#15504000
b1010000100 '
#15528000
b1010000101 '
#15552000
b1010000110 '
#15576000
b1010000111 '
#15600000
b1010001000 '
#15624000
b1010001001 '
#15648000
b1010001010 '
#15672000
b1010001011 '
#15696000
b1010001100 '
#15720000
b1010001101 '
#15744000
b1010001110 '
#15768000
b1010001111 '
#15792000
b1010010000 '
#15816000
b1010010001 '
#15840000
b1010010010 '
#15864000
b1010010011 '
#15888000
b1010010100 '
#15912000
b1010010101 '
#15936000
b1010010110 '
#15960000
b1010010111 '
#15984000
b1010011000 '
#16008000
b1010011001 '
#16032000
b1010011010 '
#16056000
b1010011011 '
#16080000
b1010011100 '
#16104000
b1010011101 '
#16128000
b1010011110 '
#16152000
b1010011111 '
#16176000
b1010100000 '
#16200000
b1010100001 '
#16224000
b1010100010 '
#16248000
b1010100011 '
#16272000
b1010100100 '
#16296000
b1010100101 '
#16320000
b1010100110 '
#16344000
b1010100111 '
#16368000
b1010101000 '
#16392000
b1010101001 '
#16416000
b1010101010 '
#16440000
b1010101011 '
#16464000
b1010101100 '
#16488000
b1010101101 '
#16512000
b1010101110 '
#16536000
b1010101111 '
#16560000
b1010110000 '
#16584000
b1010110001 '
#16608000
b1010110010 '
#16632000
b1010110011 '
#16656000
b1010110100 '
#16680000
b1010110101 '
#16704000
b1010110110 '
#16728000
b1010110111 '
#16752000
b1010111000 '
#16776000
b1010111001 '
#16800000
b1010111010 '
#16824000
b1010111011 '
#16848000
b1010111100 '
#16872000
b1010111101 '
#16896000
b1010111110 '
#16920000
b1010111111 '
#16944000
b1011000000 '
#16968000
b1011000001 '
#16992000
b1011000010 '
#17016000
b1011000011 '
#17040000
b1011000100 '
#17064000
b1011000101 '
#17088000
b1011000110 '
#17112000
b1011000111 '
#17136000
b1011001000 '
#17160000
b1011001001 '
#17184000
b1011001010 '
#17208000
b1011001011 '
#17232000
b1011001100 '
#17256000
b1011001101 '
#17280000
b1011001110 '
#17304000
b1011001111 '
#17328000
b1011010000 '
#17352000
b1011010001 '
#17376000
b1011010010 '
#17400000
b1011010011 '
#17424000
b1011010100 '
#17448000
b1011010101 '
#17472000
b1011010110 '
#17496000
b1011010111 '
#17520000
b1011011000 '
#17544000
b1011011001 '
#17568000
b1011011010 '
#17592000
b1011011011 '
#17616000
b1011011100 '
#17640000
b1011011101 '
#17664000
b1011011110 '
#17688000
b1011011111 '
#17712000
b1011100000 '
#17736000
b1011100001 '
#17760000
b1011100010 '
#17784000
b1011100011 '
#17808000
b1011100100 '
#17832000
b1011100101 '
#17856000
b1011100110 '
#17880000
b1011100111 '
#17904000
b1011101000 '
#17928000
b1011101001 '
#17952000
b1011101010 '
#17976000
b1011101011 '
#18000000
b1011101100 '
#18024000
b1011101101 '
#18048000
b1011101110 '
#18072000
b1011101111 '
#18096000
b1011110000 '
#18120000
b1011110001 '
#18144000
b1011110010 '
#18168000
b1011110011 '
#18192000
b1011110100 '
#18216000
b1011110101 '
#18240000
b1011110110 '
#18264000
b1011110111 '
#18288000
b1011111000 '
#18312000
b1011111001 '
#18336000
b1011111010 '
#18360000
b1011111011 '
#18384000
b1011111100 '
#18408000
b1011111101 '
#18432000
b1011111110 '
#18456000
b1011111111 '
#18480000
b1100000000 '
#18504000
b1100000001 '
#18528000
b1100000010 '
#18552000
b1100000011 '
#18576000
b1100000100 '
#18600000
b1100000101 '
#18624000
b1100000110 '
#18648000
b1100000111 '
#18672000
b1100001000 '
#18696000
b1100001001 '
#18720000
b1100001010 '
#18744000
b1100001011 '
#18768000
b1100001100 '
#18792000
b1100001101 '
#18816000
b1100001110 '
#18840000
b1100001111 '
#18864000
b1100010000 '
#18888000
b1100010001 '
#18912000
b1100010010 '
#18936000
b1100010011 '
#18960000
b1100010100 '
#18984000
b1100010101 '
#19008000
b1100010110 '
#19032000
b1100010111 '
#19056000
b1100011000 '
#19080000
b1100011001 '
#19104000
b1100011010 '
#19128000
b1100011011 '
#19152000
b1100011100 '
#19176000
b1100011101 '
#19200000
b1100011110 '
#19224000
b1100011111 '
#19248000
b1100100000 '
#19272000
b1100100001 '
#19296000
b1100100010 '
#19320000
b1100100011 '
#19344000
b1100100100 '
#19368000
b1100100101 '
#19392000
b1100100110 '
#19416000
b1100100111 '
#19440000
b1100101000 '
#19464000
b1100101001 '
#19488000
b1100101010 '
#19512000
b1100101011 '
#19536000
b1100101100 '
#19560000
b1100101101 '
#19584000
b1100101110 '
#19608000
b1100101111 '
#19632000
b1100110000 '
#19656000
b1100110001 '
#19680000
b1100110010 '
#19704000
b1100110011 '
#19728000
b1100110100 '
#19752000
b1100110101 '
#19776000
b1100110110 '
#19800000
b1100110111 '
#19824000
b1100111000 '
#19848000
b1100111001 '
#19872000
b1100111010 '
#19896000
b1100111011 '
#19920000
b1100111100 '
#19944000
b1100111101 '
#19968000
b1100111110 '
#19992000
b1100111111 '
#20016000
b1101000000 '
#20040000
b1101000001 '
#20064000
b1101000010 '
#20088000
b1101000011 '
#20112000
b1101000100 '
#20136000
b1101000101 '
#20160000
b1101000110 '
#20184000
b1101000111 '
#20208000
b1101001000 '
#20232000
b1101001001 '
#20256000
b1101001010 '
#20280000
b1101001011 '
#20304000
b1101001100 '
#20328000
b1101001101 '
#20352000
b1101001110 '
#20376000
b1101001111 '
#20400000
b1101010000 '
#20424000
b1101010001 '
#20448000
b1101010010 '
#20472000
b1101010011 '
#20496000
b1101010100 '
#20520000
b1101010101 '
#20544000
b1101010110 '
#20568000
b1101010111 '
#20592000
b1101011000 '
#20616000
b1101011001 '
#20640000
b1101011010 '
#20664000
b1101011011 '
#20688000
b1101011100 '
#20712000
b1101011101 '
#20736000
b1101011110 '
#20760000
b1101011111 '
#20784000
b1101100000 '
#20808000
b1101100001 '
#20832000
b1101100010 '
#20856000
b1101100011 '
#20880000
b1101100100 '
#20904000
b1101100101 '
#20928000
b1101100110 '
#20952000
b1101100111 '
#20976000
b1101101000 '
#21000000
b1101101001 '
#21024000
b1101101010 '
#21048000
b1101101011 '
#21072000
b1101101100 '
#21096000
b1101101101 '
#21120000
b1101101110 '
#21144000
b1101101111 '
#21168000
b1101110000 '
#21192000
b1101110001 '
#21216000
b1101110010 '
#21240000
b1101110011 '
#21264000
b1101110100 '
#21288000
b1101110101 '
#21312000
b1101110110 '
#21336000
b1101110111 '
#21360000
b1101111000 '
#21384000
b1101111001 '
#21408000
b1101111010 '
#21432000
b1101111011 '
#21456000
b1101111100 '
#21480000
b1101111101 '
#21504000
b1101111110 '
#21528000
b1101111111 '
#21552000
b1110000000 '
#21576000
b1110000001 '
#21600000
b1110000010 '
#21624000
b1110000011 '
#21648000
b1110000100 '
#21672000
b1110000101 '
#21696000
b1110000110 '
#21720000
b1110000111 '
#21744000
b1110001000 '
#21768000
b1110001001 '
#21792000
b1110001010 '
#21816000
b1110001011 '
#21840000
b1110001100 '
#21864000
b1110001101 '
#21888000
b1110001110 '
#21912000
b1110001111 '
#21936000
b1110010000 '
#21960000
b1110010001 '
#21984000
b1110010010 '
#22008000
b1110010011 '
#22032000
b1110010100 '
#22056000
b1110010101 '
#22080000
b1110010110 '
#22104000
b1110010111 '
#22128000
b1110011000 '
#22152000
b1110011001 '
#22176000
b1110011010 '
#22200000
b1110011011 '
#22224000
b1110011100 '
#22248000
b1110011101 '
#22272000
b1110011110 '
#22296000
b1110011111 '
#22320000
b1110100000 '
#22344000
b1110100001 '
#22368000
b1110100010 '
#22392000
b1110100011 '
#22416000
b1110100100 '
#22440000
b1110100101 '
#22464000
b1110100110 '
#22488000
b1110100111 '
#22512000
b1110101000 '
#22536000
b1110101001 '
#22560000
b1110101010 '
#22584000
b1110101011 '
#22608000
b1110101100 '
#22632000
b1110101101 '
#22656000
b1110101110 '
#22680000
b1110101111 '
#22704000
b1110110000 '
#22728000
b1110110001 '
#22752000
b1110110010 '
#22776000
b1110110011 '
#22800000
b1110110100 '
#22824000
b1110110101 '
#22848000
b1110110110 '
#22872000
b1110110111 '
#22896000
b1110111000 '
#22920000
b1110111001 '
#22944000
b1110111010 '
#22968000
b1110111011 '
#22992000
b1110111100 '
#23016000
b1110111101 '
#23040000
b1110111110 '
#23064000
b1110111111 '
#23088000
b1111000000 '
#23112000
b1111000001 '
#23136000
b1111000010 '
#23160000
b1111000011 '
#23184000
b1111000100 '
#23208000
b1111000101 '
#23232000
b1111000110 '
#23256000
b1111000111 '
#23280000
b1111001000 '
#23304000
b1111001001 '
#23328000
b1111001010 '
#23352000
b1111001011 '
#23376000
b1111001100 '
#23400000
b1111001101 '
#23424000
b1111001110 '
#23448000
b1111001111 '
#23472000
b1111010000 '
#23496000
b1111010001 '
#23520000
b1111010010 '
#23544000
b1111010011 '
#23568000
b1111010100 '
#23592000
b1111010101 '
#23616000
b1111010110 '
#23640000
b1111010111 '
#23664000
b1111011000 '
#23688000
b1111011001 '
#23712000
b1111011010 '
#23736000
b1111011011 '
#23760000
b1111011100 '
#23784000
b1111011101 '
#23808000
b1111011110 '
#23832000
b1111011111 '
#23856000
b1111100000 '
#23880000
b1111100001 '
#23904000
b1111100010 '
#23928000
b1111100011 '
#23952000
b1111100100 '
#23976000
b1111100101 '
#24000000
b1111100110 '
#24024000
b1111100111 '
#24048000
b1111101000 '
#24072000
b1111101001 '
#24096000
b1111101010 '
#24120000
b1111101011 '
#24144000
b1111101100 '
#24168000
b1111101101 '
#24192000
b1111101110 '
#24216000
b1111101111 '
#24240000
b1111110000 '
#24264000
b1111110001 '
#24288000
b1111110010 '
#24312000
b1111110011 '
#24336000
b1111110100 '
#24360000
b1111110101 '
#24384000
b1111110110 '
#24408000
b1111110111 '
#24432000
b1111111000 '
#24456000
b1111111001 '
#24480000
b1111111010 '
#24504000
b1111111011 '
#24528000
b1111111100 '
#24552000
b1111111101 '
#24576000
b1111111110 '
#24600000
b1111111111 '
#24624000
b10000000000 '
#24648000
b10000000001 '
#24672000
b10000000010 '
#24696000
b10000000011 '
#24720000
b10000000100 '
#24744000
b10000000101 '
#24768000
b10000000110 '
#24792000
b10000000111 '
#24816000
b10000001000 '
#24840000
b10000001001 '
#24864000
b10000001010 '
#24888000
b10000001011 '
#24912000
b10000001100 '
#24936000
b10000001101 '
#24960000
b10000001110 '
#24984000
b10000001111 '
#25008000
b10000010000 '
#25032000
b10000010001 '
#25056000
b10000010010 '
#25080000
b10000010011 '
#25104000
b10000010100 '
#25128000
b10000010101 '
#25152000
b10000010110 '
#25176000
b10000010111 '
#25200000
b10000011000 '
#25224000
b10000011001 '
#25248000
b10000011010 '
#25272000
b10000011011 '
#25296000
b10000011100 '
#25320000
b10000011101 '
#25344000
b10000011110 '
#25368000
b10000011111 '
#25392000
b10000100000 '
#25416000
b10000100001 '
#25440000
b10000100010 '
#25464000
b10000100011 '
#25488000
b10000100100 '
#25512000
b10000100101 '
#25536000
b10000100110 '
#25560000
b10000100111 '
#25584000
b10000101000 '
#25608000
b10000101001 '
#25632000
b10000101010 '
#25656000
b10000101011 '
#25680000
b10000101100 '
#25704000
b10000101101 '
#25728000
b10000101110 '
#25752000
b10000101111 '
#25776000
b10000110000 '
#25800000
b10000110001 '
#25824000
b10000110010 '
#25848000
b10000110011 '
#25872000
b10000110100 '
#25896000
b10000110101 '
#25920000
b10000110110 '
#25944000
b10000110111 '
#25968000
b10000111000 '
#25992000
b10000111001 '
#26016000
b10000111010 '
#26040000
b10000111011 '
#26064000
b10000111100 '
#26088000
b10000111101 '
#26112000
b10000111110 '
#26136000
b10000111111 '
