src/control/latch.v
//`timescale 1ns/1ps

module latch (
    input wire R,
    input wire S,
    output reg mag

);

    always @(R or S)
    begin
        
        if(R && !S)
            begin
                mag <= 0;
            end
        else if(S && !R)
            begin
                mag <= 1;
            end
  
      
    end




endmodule

src/control/logic_control.v
//`timescale 1ns/1ps

module logic_control (
    input wire startn,
    input wire stopn,
    input wire clearn,
    input wire door_closed,
    input wire timer_done,
    output reg R,
    output reg S

);

    

    always @(startn or stopn or clearn or door_closed or timer_done)
    begin
        if(!clearn || !stopn || timer_done || !door_closed)
            begin
                S = 0;
                R = 1;
            end
        else if(!startn && door_closed)
            begin
                S = 1;
                R = 0;
            end
        else begin
            S = 0;
            R = 1;
        end

      
    end




endmodule

src/control/control.v
//`timescale 1ns/1ps

module control (
    startn,stopn,clearn,door_closed,timer_done,
    mag
);

    input  startn,stopn,clearn,door_closed,timer_done;
    output wire mag;
    wire  R,S;

       

    logic_control controle(.startn(startn),.stopn(stopn),.clearn(clearn),.door_closed(door_closed),.timer_done(timer_done),.S(S),.R(R));
    latch SR(.S(S),.R(R),.mag(mag));


endmodule

testbenches/tb_control.v
`timescale 1ns/1ps

module tb_control;

    reg startn,stopn,clearn,door_closed,timer_done;
    wire mag;
    integer i;
    
    control c(.startn(startn),.stopn(stopn),.clearn(clearn),.door_closed(door_closed),.timer_done(timer_done),.mag(mag));

    initial begin

        startn = 1; 
        stopn = 0;
        clearn = 0;
        door_closed = 1;
        timer_done = 0;
        #2
        $display("Start: %b, Stop: %b, clearn: %b, boor_closeb: %b, timer_bone: %b",startn,stopn,clearn,door_closed,timer_done);
        #2;
        $display("Mag : %b",mag);  
        for(i = 0; i<10;i = i+1)begin
            startn = $urandom%2; 
            stopn =$urandom%2;
            clearn = $urandom%2;
            door_closed =  $urandom%2;
            timer_done =  $urandom%2;
            #2;
            $display("Start: %b, Stop: %b, clearn: %b, boor_closeb: %b, timer_bone: %b",startn,stopn,clearn,door_closed,timer_done); 
            #2;
            $display("Mag : %b",mag); 
            #20;
        end


    end

    initial begin
        $dumpfile("vcd/control.vcd");
        $dumpvars;
    end
    
    


endmodule

vcd/control.vcd
$date
	Wed Apr 28 23:08:58 2021
$end
$version
	Icarus Verilog
$end
$timescale
	1ps
$end
$scope module tb_control $end
$var wire 1 ! mag $end
$var reg 1 " clearn $end
$var reg 1 # door_closed $end
$var reg 1 $ startn $end
$var reg 1 % stopn $end
$var reg 1 & timer_done $end
$var integer 32 ' i [31:0] $end
$scope module c $end
$var wire 1 " clearn $end
$var wire 1 # door_closed $end
$var wire 1 $ startn $end
$var wire 1 % stopn $end
$var wire 1 & timer_done $end
$var wire 1 ! mag $end
$var wire 1 ( S $end
$var wire 1 ) R $end
$scope module SR $end
$var wire 1 ( S $end
$var wire 1 ) R $end
$var reg 1 ! mag $end
$upscope $end
$scope module controle $end
$var wire 1 " clearn $end
$var wire 1 # door_closed $end
$var wire 1 $ startn $end
$var wire 1 % stopn $end
$var wire 1 & timer_done $end
$var reg 1 ) R $end
$var reg 1 ( S $end
$upscope $end
$upscope $end
$upscope $end
$enddefinitions $end
#0
$dumpvars
0)
1(
bx '
0&
0%
1$
1#
0"
1!
$end
#4000
0!
1)
0(
1&
1"
1%
0$
b0 '
#28000
0"
1$
b1 '
#52000
0#
1"
0$
b10 '
#76000
1#
0"
b11 '
#100000
0&
0#
b100 '
#124000
1&
1#
1"
0%
1$
b101 '
#148000
0&
0#
0"
b110 '
#172000
1&
1#
1"
b111 '
#196000
0#
0"
1%
b1000 '
#220000
0&
b1001 '
#244000
b1010 '
