src/control/latch.v
//`timescale 1ns/1ps

module latch (
    input wire R,
    input wire S,
    output reg mag

);

    always @(R or S)
    begin
        
        if(R && !S)
            begin
                mag <= 0;
            end
        else if(S && !R)
            begin
                mag <= 1;
            end
  
      
    end




endmodule

src/control/logic_control.v
`timescale 1ns/1ps

module logic_control (
    input wire startn,
    input wire stopn,
    input wire clearn,
    input wire door_closed,
    input wire timer_done,
    output reg R,
    output reg S

);

    

    always @(startn or stopn or clearn or door_closed or timer_done)
    begin
        if(!clearn || !stopn || timer_done || !door_closed)
            begin
                S = 0;
                R = 1;
            end
        else if(!startn && door_closed)
            begin
                S = 1;
                R = 0;
            end
        else begin
            S = 0;
            R = 1;
        end

      
    end




endmodule

src/control/control.v
//`timescale 1ns/1ps

module control (
    startn,stopn,clearn,door_closed,timer_done,
    mag
);

    input  startn,stopn,clearn,door_closed,timer_done;
    output wire mag;
    wire  R,S;

       

    logic_control controle(.startn(startn),.stopn(stopn),.clearn(clearn),.door_closed(door_closed),.timer_done(timer_done),.S(S),.R(R));
    latch SR(.S(S),.R(R),.mag(mag));


endmodule

testbenches/tb_control.v
`timescale 1ns/1ps

module tb_control;

    reg startn,stopn,clearn,door_closed,timer_done;
    wire mag;
    integer i;
    
    control c(.startn(startn),.stopn(stopn),.clearn(clearn),.door_closed(door_closed),.timer_done(timer_done),.mag(mag));

    initial begin

        startn = 1; 
        stopn = 0;
        clearn = 0;
        door_closed = 1;
        timer_done = 0;
        #2
        $display("Start: %b, Stop: %b, clearn: %b, boor_closeb: %b, timer_bone: %b",startn,stopn,clearn,door_closed,timer_done);
        #2;
        $display("Mag : %b",mag);  
        for(i = 0; i<3000;i = i+1)begin
            startn = $urandom%2; 
            stopn =$urandom%2;
            clearn = $urandom%2;
            door_closed =  $urandom%2;
            timer_done =  $urandom%2;
            #2;
            $display("Start: %b, Stop: %b, clearn: %b, boor_closeb: %b, timer_bone: %b",startn,stopn,clearn,door_closed,timer_done); 
            #2;
            $display("Mag : %b",mag); 
            #20;
        end


    end

    initial begin
        $dumpfile("vcd/control.vcd");
        $dumpvars;
    end
    
    


endmodule

vcd/control.vcd
$date
	Thu Apr 29 01:32:58 2021
$end
$version
	Icarus Verilog
$end
$timescale
	1ps
$end
$scope module tb_control $end
$var wire 1 ! mag $end
$var reg 1 " clearn $end
$var reg 1 # door_closed $end
$var reg 1 $ startn $end
$var reg 1 % stopn $end
$var reg 1 & timer_done $end
$var integer 32 ' i [31:0] $end
$scope module c $end
$var wire 1 " clearn $end
$var wire 1 # door_closed $end
$var wire 1 $ startn $end
$var wire 1 % stopn $end
$var wire 1 & timer_done $end
$var wire 1 ! mag $end
$var wire 1 ( S $end
$var wire 1 ) R $end
$scope module SR $end
$var wire 1 ( S $end
$var wire 1 ) R $end
$var reg 1 ! mag $end
$upscope $end
$scope module controle $end
$var wire 1 " clearn $end
$var wire 1 # door_closed $end
$var wire 1 $ startn $end
$var wire 1 % stopn $end
$var wire 1 & timer_done $end
$var reg 1 ) R $end
$var reg 1 ( S $end
$upscope $end
$upscope $end
$upscope $end
$enddefinitions $end
#0
$dumpvars
1)
0(
bx '
0&
0%
1$
1#
0"
0!
$end
#4000
1&
1"
1%
0$
b0 '
#28000
0"
1$
b1 '
#52000
0#
1"
0$
b10 '
#76000
1#
0"
b11 '
#100000
0&
0#
b100 '
#124000
1&
1#
1"
0%
1$
b101 '
#148000
0&
0#
0"
b110 '
#172000
1&
1#
1"
b111 '
#196000
0#
0"
1%
b1000 '
#220000
0&
b1001 '
#244000
1"
0%
0$
b1010 '
#268000
0"
1%
1$
b1011 '
#292000
1&
1#
1"
0%
0$
b1100 '
#316000
0#
0"
1%
1$
b1101 '
#340000
b1110 '
#364000
0&
1#
1"
0%
b1111 '
#388000
1&
0#
1%
b10000 '
#412000
0&
0"
0%
b10001 '
#436000
1&
1%
b10010 '
#460000
0&
1#
1"
b10011 '
#484000
0#
b10100 '
#508000
0"
0%
0$
b10101 '
#532000
1&
1#
1"
1%
1$
b10110 '
#556000
0&
0#
0$
b10111 '
#580000
1&
1#
0"
1$
b11000 '
#604000
0&
0#
b11001 '
#628000
1&
0%
b11010 '
#652000
0&
1#
b11011 '
#676000
0#
1"
0$
b11100 '
#700000
1&
1#
1$
b11101 '
#724000
0&
0#
0"
1%
b11110 '
#748000
1&
1#
0%
b11111 '
#772000
0$
b100000 '
#796000
b100001 '
#820000
0&
b100010 '
#844000
0#
1%
b100011 '
#868000
1#
1"
0%
1$
b100100 '
#892000
0"
0$
b100101 '
#916000
1&
b100110 '
#940000
1"
1$
b100111 '
#964000
0$
b101000 '
#988000
0"
1%
1$
b101001 '
#1012000
0#
0%
0$
b101010 '
#1036000
0&
1#
1$
b101011 '
#1060000
1&
0#
1%
0$
b101100 '
#1084000
1#
1"
0%
b101101 '
#1108000
0&
0"
b101110 '
#1132000
0#
1%
b101111 '
#1156000
b110000 '
#1180000
1&
1#
1$
b110001 '
#1204000
b110010 '
#1228000
0&
0%
b110011 '
#1252000
0#
1"
1%
0$
b110100 '
#1276000
1#
0"
0%
1$
b110101 '
#1300000
1%
b110110 '
#1324000
0%
b110111 '
#1348000
1&
1"
0$
b111000 '
#1372000
0"
1%
1$
b111001 '
#1396000
0&
0#
0%
b111010 '
#1420000
1&
1#
1"
0$
b111011 '
#1444000
0&
1%
1$
b111100 '
#1468000
1&
b111101 '
#1492000
0&
0#
b111110 '
#1516000
0"
b111111 '
#1540000
0$
b1000000 '
#1564000
1#
0%
b1000001 '
#1588000
0#
1%
b1000010 '
#1612000
1&
1#
1"
b1000011 '
#1636000
0%
1$
b1000100 '
#1660000
0#
0"
1%
0$
b1000101 '
#1684000
0&
1"
0%
1$
b1000110 '
#1708000
0"
b1000111 '
#1732000
1#
1"
1%
b1001000 '
#1756000
1&
b1001001 '
#1780000
0&
0"
b1001010 '
#1804000
0%
b1001011 '
#1828000
1&
0#
0$
b1001100 '
#1852000
0&
b1001101 '
#1876000
1#
1%
b1001110 '
#1900000
1&
b1001111 '
#1924000
0&
b1010000 '
#1948000
0%
b1010001 '
#1972000
1"
1$
b1010010 '
#1996000
1&
b1010011 '
#2020000
0&
0#
1%
0$
b1010100 '
#2044000
1&
0"
1$
b1010101 '
#2068000
0&
1#
0%
b1010110 '
#2092000
0#
1"
1%
0$
b1010111 '
#2116000
1&
1#
0"
0%
1$
b1011000 '
#2140000
1%
0$
b1011001 '
#2164000
1!
0)
1(
0&
1"
b1011010 '
#2188000
0!
1)
0(
0#
1$
b1011011 '
#2212000
1#
0"
0%
b1011100 '
#2236000
1&
0#
1"
1%
0$
b1011101 '
#2260000
1#
b1011110 '
#2284000
0#
0%
b1011111 '
#2308000
0&
1%
b1100000 '
#2332000
1$
b1100001 '
#2356000
1&
1#
0"
0%
b1100010 '
#2380000
0&
1"
b1100011 '
#2404000
1&
0$
b1100100 '
#2428000
0"
b1100101 '
#2452000
1%
1$
b1100110 '
#2476000
1"
b1100111 '
#2500000
0&
0#
0"
0$
b1101000 '
#2524000
1&
1#
1"
1$
b1101001 '
#2548000
0&
b1101010 '
#2572000
0#
0%
0$
b1101011 '
#2596000
1%
b1101100 '
#2620000
1&
b1101101 '
#2644000
0&
0"
b1101110 '
#2668000
1&
1"
1$
b1101111 '
#2692000
1#
0"
0$
b1110000 '
#2716000
0#
0%
b1110001 '
#2740000
0&
1#
1$
b1110010 '
#2764000
1"
b1110011 '
#2788000
0#
0"
1%
b1110100 '
#2812000
1&
1#
1"
0$
b1110101 '
#2836000
0&
0#
0"
0%
1$
b1110110 '
#2860000
1&
1#
0$
b1110111 '
#2884000
1"
1%
1$
b1111000 '
#2908000
0&
0#
0"
0%
0$
b1111001 '
#2932000
1&
1"
1%
b1111010 '
#2956000
1!
0)
1(
0&
1#
b1111011 '
#2980000
0!
1)
0(
0%
b1111100 '
#3004000
0#
0"
1$
b1111101 '
#3028000
1"
0$
b1111110 '
#3052000
1&
1#
0"
1$
b1111111 '
#3076000
b10000000 '
#3100000
1%
b10000001 '
#3124000
0&
b10000010 '
#3148000
1&
0#
0$
b10000011 '
#3172000
0&
0%
b10000100 '
#3196000
1"
1%
b10000101 '
#3220000
1&
1#
1$
b10000110 '
#3244000
0&
0"
b10000111 '
#3268000
1"
0%
0$
b10001000 '
#3292000
0#
1%
1$
b10001001 '
#3316000
1&
1#
0%
0$
b10001010 '
#3340000
0&
0#
0"
1%
b10001011 '
#3364000
1&
0%
b10001100 '
#3388000
1#
1"
b10001101 '
#3412000
0&
0#
0"
1%
1$
b10001110 '
#3436000
1"
0$
b10001111 '
#3460000
1&
1#
1$
b10010000 '
#3484000
0&
0"
0%
0$
b10010001 '
#3508000
0#
1$
b10010010 '
#3532000
1&
1#
1%
0$
b10010011 '
#3556000
0#
1"
b10010100 '
#3580000
0&
b10010101 '
#3604000
0"
1$
b10010110 '
#3628000
1!
0)
1(
1#
1"
0$
b10010111 '
#3652000
0!
1)
0(
1&
b10011000 '
#3676000
0&
0%
b10011001 '
#3700000
0"
1%
b10011010 '
#3724000
0#
1$
b10011011 '
#3748000
1&
1"
0%
0$
b10011100 '
#3772000
0&
1#
0"
b10011101 '
#3796000
1&
1%
b10011110 '
#3820000
0#
1"
1$
b10011111 '
#3844000
0&
1#
0"
0%
b10100000 '
#3868000
1&
1"
1%
b10100001 '
#3892000
0&
0"
0$
b10100010 '
#3916000
0#
1$
b10100011 '
#3940000
1"
0$
b10100100 '
#3964000
1&
1#
1$
b10100101 '
#3988000
0#
0"
0%
0$
b10100110 '
#4012000
1"
b10100111 '
#4036000
0&
b10101000 '
#4060000
1&
b10101001 '
#4084000
0&
1#
0"
1$
b10101010 '
#4108000
1"
1%
b10101011 '
#4132000
1&
0"
0%
b10101100 '
#4156000
1"
b10101101 '
#4180000
0#
1%
b10101110 '
#4204000
0&
1#
0"
0%
0$
b10101111 '
#4228000
0#
1"
1$
b10110000 '
#4252000
0$
b10110001 '
#4276000
1$
b10110010 '
#4300000
1&
0"
1%
b10110011 '
#4324000
1#
1"
0%
b10110100 '
#4348000
0&
0#
b10110101 '
#4372000
1&
1#
0"
1%
b10110110 '
#4396000
1!
0)
1(
0&
1"
0$
b10110111 '
#4420000
0!
1)
0(
0#
0%
1$
b10111000 '
#4444000
0"
0$
b10111001 '
#4468000
1&
1#
1"
b10111010 '
#4492000
0"
b10111011 '
#4516000
1!
0)
1(
0&
1"
1%
b10111100 '
#4540000
0!
1)
0(
0#
b10111101 '
#4564000
1&
0%
b10111110 '
#4588000
1$
b10111111 '
#4612000
1#
b11000000 '
#4636000
0#
b11000001 '
#4660000
0"
0$
b11000010 '
#4684000
1%
b11000011 '
#4708000
1"
1$
b11000100 '
#4732000
0"
b11000101 '
#4756000
1#
b11000110 '
#4780000
0&
0#
1"
0%
0$
b11000111 '
#4804000
1&
0"
1%
1$
b11001000 '
#4828000
1#
0%
0$
b11001001 '
#4852000
0&
1"
1%
1$
b11001010 '
#4876000
1&
0#
0%
b11001011 '
#4900000
0&
1#
0"
1%
0$
b11001100 '
#4924000
0#
1"
0%
1$
b11001101 '
#4948000
1&
0"
1%
0$
b11001110 '
#4972000
0&
1#
1"
1$
b11001111 '
#4996000
0"
b11010000 '
#5020000
1&
1"
b11010001 '
#5044000
0"
0$
b11010010 '
#5068000
1$
b11010011 '
#5092000
0&
0#
b11010100 '
#5116000
b11010101 '
#5140000
1"
b11010110 '
#5164000
0"
0%
b11010111 '
#5188000
1#
1"
0$
b11011000 '
#5212000
1&
0#
0"
b11011001 '
#5236000
0&
1#
1"
1%
1$
b11011010 '
#5260000
1&
0"
0%
0$
b11011011 '
#5284000
0&
0#
1"
1%
1$
b11011100 '
#5308000
0"
0$
b11011101 '
#5332000
1&
1#
1"
0%
1$
b11011110 '
#5356000
0#
0"
b11011111 '
#5380000
0&
1%
b11100000 '
#5404000
1&
1#
1"
0%
0$
b11100001 '
#5428000
0&
0"
b11100010 '
#5452000
1&
1"
1$
b11100011 '
#5476000
0&
b11100100 '
#5500000
0#
0"
1%
0$
b11100101 '
#5524000
1#
0%
1$
b11100110 '
#5548000
1&
0#
1"
1%
b11100111 '
#5572000
1!
0)
1(
0&
1#
0$
b11101000 '
#5596000
0!
1)
0(
0#
0"
0%
b11101001 '
#5620000
1&
1#
1"
1%
b11101010 '
#5644000
0&
0#
1$
b11101011 '
#5668000
1&
b11101100 '
#5692000
0%
b11101101 '
#5716000
0&
1#
0"
1%
b11101110 '
#5740000
0#
b11101111 '
#5764000
0%
b11110000 '
#5788000
1%
0$
b11110001 '
#5812000
1#
1"
0%
1$
b11110010 '
#5836000
0#
0"
b11110011 '
#5860000
1#
1"
1%
b11110100 '
#5884000
1&
0"
0$
b11110101 '
#5908000
0&
1"
0%
1$
b11110110 '
#5932000
1%
b11110111 '
#5956000
1&
0%
0$
b11111000 '
#5980000
0#
0"
1%
b11111001 '
#6004000
0&
1#
0%
1$
b11111010 '
#6028000
1"
b11111011 '
#6052000
0#
1%
b11111100 '
#6076000
1&
0"
0$
b11111101 '
#6100000
0&
1"
0%
b11111110 '
#6124000
0"
1%
1$
b11111111 '
#6148000
1&
1#
b100000000 '
#6172000
0$
b100000001 '
#6196000
0&
1"
0%
1$
b100000010 '
#6220000
0#
b100000011 '
#6244000
1#
1%
b100000100 '
#6268000
1!
0)
1(
0$
b100000101 '
#6292000
0!
1)
0(
1&
0#
b100000110 '
#6316000
1$
b100000111 '
#6340000
0&
1#
0"
0%
0$
b100001000 '
#6364000
1%
b100001001 '
#6388000
0#
1"
0%
b100001010 '
#6412000
1&
1%
b100001011 '
#6436000
0"
0%
1$
b100001100 '
#6460000
1"
1%
0$
b100001101 '
#6484000
0&
1#
0"
b100001110 '
#6508000
1&
1$
b100001111 '
#6532000
0&
0$
b100010000 '
#6556000
0#
b100010001 '
#6580000
0%
1$
b100010010 '
#6604000
1&
1#
0$
b100010011 '
#6628000
0&
1$
b100010100 '
#6652000
1&
1"
1%
b100010101 '
#6676000
0&
0#
0"
0%
0$
b100010110 '
#6700000
1#
1"
1%
1$
b100010111 '
#6724000
1&
0%
0$
b100011000 '
#6748000
0&
0"
1%
b100011001 '
#6772000
0#
0%
b100011010 '
#6796000
1&
b100011011 '
#6820000
0&
1#
1"
1%
1$
b100011100 '
#6844000
1&
0#
0$
b100011101 '
#6868000
0&
0"
b100011110 '
#6892000
1!
0)
1(
1#
1"
b100011111 '
#6916000
0!
1)
0(
0"
1$
b100100000 '
#6940000
1"
0%
0$
b100100001 '
#6964000
1&
1%
b100100010 '
#6988000
0#
0"
0%
1$
b100100011 '
#7012000
1"
b100100100 '
#7036000
0&
1#
0"
1%
b100100101 '
#7060000
0%
0$
b100100110 '
#7084000
0#
1%
1$
b100100111 '
#7108000
1#
b100101000 '
#7132000
1&
b100101001 '
#7156000
1"
0%
b100101010 '
#7180000
b100101011 '
#7204000
0"
1%
b100101100 '
#7228000
0#
1"
0%
b100101101 '
#7252000
0&
b100101110 '
#7276000
1&
0$
b100101111 '
#7300000
0&
1%
b100110000 '
#7324000
1&
1#
0%
1$
b100110001 '
#7348000
0&
b100110010 '
#7372000
b100110011 '
#7396000
1&
0#
0"
1%
b100110100 '
#7420000
0%
0$
b100110101 '
#7444000
1%
1$
b100110110 '
#7468000
0&
1#
0%
0$
b100110111 '
#7492000
0#
1%
b100111000 '
#7516000
1&
1#
1"
0%
1$
b100111001 '
#7540000
0"
b100111010 '
#7564000
0#
1%
0$
b100111011 '
#7588000
1#
1"
b100111100 '
#7612000
0&
0"
1$
b100111101 '
#7636000
1&
0#
1"
0%
b100111110 '
#7660000
0&
1#
0"
1%
b100111111 '
#7684000
1&
0#
0%
b101000000 '
#7708000
0&
1#
1%
b101000001 '
#7732000
0#
1"
0$
b101000010 '
#7756000
0%
1$
b101000011 '
#7780000
1&
1#
1%
b101000100 '
#7804000
0#
0"
0$
b101000101 '
#7828000
0&
1#
1"
0%
b101000110 '
#7852000
1&
0#
b101000111 '
#7876000
0&
1#
1$
b101001000 '
#7900000
0#
1%
b101001001 '
#7924000
1#
0"
b101001010 '
#7948000
1"
b101001011 '
#7972000
1&
0%
0$
b101001100 '
#7996000
0&
0#
0"
1%
1$
b101001101 '
#8020000
1&
0$
b101001110 '
#8044000
0&
1#
1"
0%
b101001111 '
#8068000
1&
0#
1$
b101010000 '
#8092000
0&
0"
0$
b101010001 '
#8116000
1#
1%
b101010010 '
#8140000
1&
0#
b101010011 '
#8164000
0&
1#
0%
1$
b101010100 '
#8188000
0#
1"
0$
b101010101 '
#8212000
1&
1#
0"
b101010110 '
#8236000
0&
0#
1"
1%
b101010111 '
#8260000
0"
0%
b101011000 '
#8284000
1&
1%
1$
b101011001 '
#8308000
0&
1"
b101011010 '
#8332000
1&
0%
0$
b101011011 '
#8356000
1#
1%
b101011100 '
#8380000
0#
0%
1$
b101011101 '
#8404000
0"
1%
b101011110 '
#8428000
0&
1#
1"
0%
b101011111 '
#8452000
0#
1%
0$
b101100000 '
#8476000
1&
0%
1$
b101100001 '
#8500000
1#
b101100010 '
#8524000
0&
1%
b101100011 '
#8548000
1&
b101100100 '
#8572000
0$
b101100101 '
#8596000
0&
0%
b101100110 '
#8620000
0"
1%
1$
b101100111 '
#8644000
0#
1"
0%
b101101000 '
#8668000
0"
0$
b101101001 '
#8692000
1&
1"
1%
b101101010 '
#8716000
1#
0%
b101101011 '
#8740000
0#
0"
1$
b101101100 '
#8764000
0&
1%
b101101101 '
#8788000
1&
1"
0%
b101101110 '
#8812000
0&
1#
b101101111 '
#8836000
0#
0"
1%
b101110000 '
#8860000
0$
b101110001 '
#8884000
1&
0%
b101110010 '
#8908000
1#
1%
1$
b101110011 '
#8932000
0&
0#
1"
0%
0$
b101110100 '
#8956000
1#
0"
b101110101 '
#8980000
1&
1"
b101110110 '
#9004000
1%
1$
b101110111 '
#9028000
0&
0#
0%
b101111000 '
#9052000
1%
b101111001 '
#9076000
1#
0"
0%
b101111010 '
#9100000
1&
0#
0$
b101111011 '
#9124000
1%
1$
b101111100 '
#9148000
1!
0)
1(
0&
1#
1"
0$
b101111101 '
#9172000
0!
1)
0(
0#
0"
0%
1$
b101111110 '
#9196000
1&
1#
1"
1%
0$
b101111111 '
#9220000
0"
0%
1$
b110000000 '
#9244000
0&
0#
b110000001 '
#9268000
1#
1"
0$
b110000010 '
#9292000
0"
1$
b110000011 '
#9316000
0#
0$
b110000100 '
#9340000
1&
1#
1"
1%
b110000101 '
#9364000
0&
0#
0"
b110000110 '
#9388000
1#
b110000111 '
#9412000
0#
1"
b110001000 '
#9436000
1#
0"
1$
b110001001 '
#9460000
0%
b110001010 '
#9484000
b110001011 '
#9508000
0#
b110001100 '
#9532000
1#
1"
0$
b110001101 '
#9556000
1&
b110001110 '
#9580000
0&
1%
1$
b110001111 '
#9604000
1&
0"
0$
b110010000 '
#9628000
1$
b110010001 '
#9652000
0&
b110010010 '
#9676000
1&
1"
0%
0$
b110010011 '
#9700000
0&
0#
b110010100 '
#9724000
0"
1$
b110010101 '
#9748000
1#
b110010110 '
#9772000
0#
b110010111 '
#9796000
1#
1"
b110011000 '
#9820000
1%
b110011001 '
#9844000
0#
0"
b110011010 '
#9868000
1&
1#
1"
0$
b110011011 '
#9892000
0#
0%
1$
b110011100 '
#9916000
0&
0"
1%
0$
b110011101 '
#9940000
1#
1$
b110011110 '
#9964000
1"
b110011111 '
#9988000
1&
0#
0%
0$
b110100000 '
#10012000
b110100001 '
#10036000
b110100010 '
#10060000
1#
b110100011 '
#10084000
1$
b110100100 '
#10108000
0&
0#
0"
0$
b110100101 '
#10132000
1%
b110100110 '
#10156000
1&
b110100111 '
#10180000
b110101000 '
#10204000
0%
b110101001 '
#10228000
1%
b110101010 '
#10252000
1#
1"
0%
b110101011 '
#10276000
b110101100 '
#10300000
1%
b110101101 '
#10324000
0#
0"
0%
b110101110 '
#10348000
1#
1%
1$
b110101111 '
#10372000
0&
0#
0%
0$
b110110000 '
#10396000
1$
b110110001 '
#10420000
0$
b110110010 '
#10444000
1#
b110110011 '
#10468000
1&
0#
b110110100 '
#10492000
1#
1$
b110110101 '
#10516000
0&
0#
1%
0$
b110110110 '
#10540000
1&
1"
b110110111 '
#10564000
0&
1#
1$
b110111000 '
#10588000
0"
0%
0$
b110111001 '
#10612000
1&
1"
1%
1$
b110111010 '
#10636000
0&
0#
0"
0%
0$
b110111011 '
#10660000
1#
1%
b110111100 '
#10684000
1"
0%
1$
b110111101 '
#10708000
1&
0"
1%
0$
b110111110 '
#10732000
0&
0#
0%
b110111111 '
#10756000
1$
b111000000 '
#10780000
1#
1%
b111000001 '
#10804000
0%
0$
b111000010 '
#10828000
0#
1"
1$
b111000011 '
#10852000
b111000100 '
#10876000
1!
0)
1(
1#
1%
0$
b111000101 '
#10900000
0!
1)
0(
1&
0#
0%
1$
b111000110 '
#10924000
0&
1#
0"
1%
b111000111 '
#10948000
1&
0$
b111001000 '
#10972000
0#
0%
b111001001 '
#10996000
1"
1$
b111001010 '
#11020000
0&
0"
b111001011 '
#11044000
1&
1"
1%
0$
b111001100 '
#11068000
0"
1$
b111001101 '
#11092000
0&
0%
b111001110 '
#11116000
1"
0$
b111001111 '
#11140000
1&
1#
1%
b111010000 '
#11164000
1$
b111010001 '
#11188000
0"
b111010010 '
#11212000
0&
0#
0%
b111010011 '
#11236000
1&
0$
b111010100 '
#11260000
1#
1"
1$
b111010101 '
#11284000
0&
0#
1%
0$
b111010110 '
#11308000
1&
1#
0%
b111010111 '
#11332000
0"
b111011000 '
#11356000
0&
0#
1%
1$
b111011001 '
#11380000
1&
1#
1"
0%
0$
b111011010 '
#11404000
0&
b111011011 '
#11428000
1&
0"
1%
b111011100 '
#11452000
0#
b111011101 '
#11476000
1#
1"
0%
b111011110 '
#11500000
1!
0)
1(
0&
1%
b111011111 '
#11524000
0!
1)
0(
0#
0%
1$
b111100000 '
#11548000
1&
1#
0"
1%
b111100001 '
#11572000
0&
0#
1"
0%
b111100010 '
#11596000
1&
1#
0"
1%
0$
b111100011 '
#11620000
0&
1"
1$
b111100100 '
#11644000
1&
0#
0%
b111100101 '
#11668000
0"
b111100110 '
#11692000
1#
1"
1%
0$
b111100111 '
#11716000
0&
0#
b111101000 '
#11740000
1&
1#
b111101001 '
#11764000
b111101010 '
#11788000
0"
1$
b111101011 '
#11812000
0%
b111101100 '
#11836000
1"
b111101101 '
#11860000
0#
0"
0$
b111101110 '
#11884000
0&
1$
b111101111 '
#11908000
1!
0)
1(
1#
1"
1%
0$
b111110000 '
#11932000
0!
1)
0(
1&
0#
0%
1$
b111110001 '
#11956000
1#
1%
0$
b111110010 '
#11980000
0#
1$
b111110011 '
#12004000
1#
0$
b111110100 '
#12028000
0%
b111110101 '
#12052000
0&
0#
0"
1%
b111110110 '
#12076000
1&
1#
b111110111 '
#12100000
0#
1"
b111111000 '
#12124000
0"
1$
b111111001 '
#12148000
0&
1#
1"
b111111010 '
#12172000
0#
b111111011 '
#12196000
1#
0"
b111111100 '
#12220000
1&
0#
0%
0$
b111111101 '
#12244000
1"
b111111110 '
#12268000
1$
b111111111 '
#12292000
0&
1#
b1000000000 '
#12316000
1&
0#
0"
1%
b1000000001 '
#12340000
1#
1"
0%
b1000000010 '
#12364000
0"
0$
b1000000011 '
#12388000
0&
0#
1"
1%
b1000000100 '
#12412000
0"
0%
b1000000101 '
#12436000
1&
1#
1%
b1000000110 '
#12460000
0&
0#
1$
b1000000111 '
#12484000
1#
0%
b1000001000 '
#12508000
1&
0#
b1000001001 '
#12532000
1#
1"
0$
b1000001010 '
#12556000
0&
0#
1$
b1000001011 '
#12580000
1#
0"
1%
b1000001100 '
#12604000
0#
1"
0%
b1000001101 '
#12628000
1#
0"
0$
b1000001110 '
#12652000
1&
0#
1"
1%
b1000001111 '
#12676000
0&
1#
0"
b1000010000 '
#12700000
0#
1"
0%
1$
b1000010001 '
#12724000
1&
1#
0$
b1000010010 '
#12748000
0&
0"
1%
1$
b1000010011 '
#12772000
1&
0#
1"
0$
b1000010100 '
#12796000
1#
0"
0%
1$
b1000010101 '
#12820000
1"
1%
0$
b1000010110 '
#12844000
0&
0#
0"
0%
1$
b1000010111 '
#12868000
1&
1"
1%
0$
b1000011000 '
#12892000
0&
b1000011001 '
#12916000
1&
0"
0%
1$
b1000011010 '
#12940000
1#
1%
0$
b1000011011 '
#12964000
0&
0%
b1000011100 '
#12988000
1&
0#
1"
1%
b1000011101 '
#13012000
0&
0%
1$
b1000011110 '
#13036000
0$
b1000011111 '
#13060000
1&
1#
b1000100000 '
#13084000
1%
b1000100001 '
#13108000
0&
0#
0%
1$
b1000100010 '
#13132000
1&
0"
b1000100011 '
#13156000
1%
b1000100100 '
#13180000
1#
0%
b1000100101 '
#13204000
0&
b1000100110 '
#13228000
1&
1%
b1000100111 '
#13252000
1"
0$
b1000101000 '
#13276000
b1000101001 '
#13300000
0&
0#
0%
1$
b1000101010 '
#13324000
1&
1#
0$
b1000101011 '
#13348000
0&
0"
1%
1$
b1000101100 '
#13372000
0#
b1000101101 '
#13396000
1&
1#
1"
0%
0$
b1000101110 '
#13420000
0#
0"
1%
1$
b1000101111 '
#13444000
0%
b1000110000 '
#13468000
0$
b1000110001 '
#13492000
1#
b1000110010 '
#13516000
0&
1"
1%
1$
b1000110011 '
#13540000
1&
0%
0$
b1000110100 '
#13564000
0&
0#
0"
1%
b1000110101 '
#13588000
1&
1#
1"
1$
b1000110110 '
#13612000
0#
0"
0%
0$
b1000110111 '
#13636000
1#
b1000111000 '
#13660000
b1000111001 '
#13684000
0&
0#
1$
b1000111010 '
#13708000
1"
b1000111011 '
#13732000
1!
0)
1(
1#
1%
0$
b1000111100 '
#13756000
0!
1)
0(
0#
0"
1$
b1000111101 '
#13780000
1&
1#
0%
0$
b1000111110 '
#13804000
0&
b1000111111 '
#13828000
0#
1$
b1001000000 '
#13852000
1#
1"
1%
b1001000001 '
#13876000
1&
0#
0"
b1001000010 '
#13900000
0$
b1001000011 '
#13924000
1#
1"
0%
b1001000100 '
#13948000
0&
0#
1$
b1001000101 '
#13972000
1#
b1001000110 '
#13996000
0#
1%
0$
b1001000111 '
#14020000
1$
b1001001000 '
#14044000
1#
0%
0$
b1001001001 '
#14068000
1&
0#
1%
b1001001010 '
#14092000
0&
b1001001011 '
#14116000
1&
1#
0"
0%
1$
b1001001100 '
#14140000
0&
b1001001101 '
#14164000
1&
1"
1%
0$
b1001001110 '
#14188000
0&
1$
b1001001111 '
#14212000
1&
0#
0$
b1001010000 '
#14236000
0"
0%
b1001010001 '
#14260000
1"
b1001010010 '
#14284000
1#
1%
1$
b1001010011 '
#14308000
b1001010100 '
#14332000
0&
0#
0"
b1001010101 '
#14356000
1&
1"
b1001010110 '
#14380000
0&
1#
0"
0%
b1001010111 '
#14404000
0#
b1001011000 '
#14428000
1&
1#
1"
b1001011001 '
#14452000
0&
0#
1%
0$
b1001011010 '
#14476000
1&
1#
b1001011011 '
#14500000
0#
0"
1$
b1001011100 '
#14524000
0&
1"
0%
0$
b1001011101 '
#14548000
0"
1$
b1001011110 '
#14572000
1%
b1001011111 '
#14596000
1#
0%
0$
b1001100000 '
#14620000
1!
0)
1(
1"
1%
b1001100001 '
#14644000
0!
1)
0(
0%
1$
b1001100010 '
#14668000
0#
1%
0$
b1001100011 '
#14692000
1#
0%
b1001100100 '
#14716000
0#
1$
b1001100101 '
#14740000
1#
0"
1%
0$
b1001100110 '
#14764000
1&
0#
1"
0%
b1001100111 '
#14788000
1!
0)
1(
0&
1#
1%
b1001101000 '
#14812000
0!
1)
0(
0#
1$
b1001101001 '
#14836000
1&
0%
b1001101010 '
#14860000
1#
0"
b1001101011 '
#14884000
0#
0$
b1001101100 '
#14908000
1#
1%
b1001101101 '
#14932000
0&
1$
b1001101110 '
#14956000
1&
b1001101111 '
#14980000
1"
0$
b1001110000 '
#15004000
0"
0%
1$
b1001110001 '
#15028000
0#
1"
0$
b1001110010 '
#15052000
1#
b1001110011 '
#15076000
0&
1$
b1001110100 '
#15100000
1&
0#
0$
b1001110101 '
#15124000
0&
1$
b1001110110 '
#15148000
1#
0"
1%
b1001110111 '
#15172000
0#
1"
0$
b1001111000 '
#15196000
1&
0"
b1001111001 '
#15220000
1#
1"
0%
1$
b1001111010 '
#15244000
0"
0$
b1001111011 '
#15268000
0&
1"
b1001111100 '
#15292000
1&
0#
0"
1%
1$
b1001111101 '
#15316000
0&
1#
b1001111110 '
#15340000
0#
0%
0$
b1001111111 '
#15364000
1#
1"
1$
b1010000000 '
#15388000
1&
0#
0"
1%
b1010000001 '
#15412000
0&
0$
b1010000010 '
#15436000
1&
1#
1"
0%
b1010000011 '
#15460000
1$
b1010000100 '
#15484000
0"
b1010000101 '
#15508000
0#
1"
b1010000110 '
#15532000
0&
0"
1%
0$
b1010000111 '
#15556000
1"
b1010001000 '
#15580000
1&
1$
b1010001001 '
#15604000
0&
0%
b1010001010 '
#15628000
1&
1#
0"
0$
b1010001011 '
#15652000
0&
0#
1"
1%
b1010001100 '
#15676000
0"
1$
b1010001101 '
#15700000
1&
1#
0%
0$
b1010001110 '
#15724000
1%
b1010001111 '
#15748000
0&
0#
1"
0%
1$
b1010010000 '
#15772000
1&
1#
1%
0$
b1010010001 '
#15796000
b1010010010 '
#15820000
0"
1$
b1010010011 '
#15844000
0#
1"
b1010010100 '
#15868000
0&
0"
b1010010101 '
#15892000
1#
1"
0%
0$
b1010010110 '
#15916000
1&
1%
1$
b1010010111 '
#15940000
0&
0"
0%
b1010011000 '
#15964000
1&
0#
1"
1%
b1010011001 '
#15988000
0&
1#
0"
0%
b1010011010 '
#16012000
1&
b1010011011 '
#16036000
0&
1"
b1010011100 '
#16060000
0"
0$
b1010011101 '
#16084000
1&
b1010011110 '
