src/encoder/Debounce.v
module Debounce (input wire clock, clear,
                   output reg out);
    reg [2:0] cont=0;
    always @(posedge clock && !clear) begin
        cont <= (cont==3'd7? cont: cont +1);
        if(cont == 3'd4) begin
            out <= 1;
        end
    end
    always @(posedge clock && clear) begin
        out<=0;
        cont<=0;
    end
endmodule

testbenches/tb_Debounce.v
`timescale 1ns/1ps

module tb_Debounce;

    reg clk, clear;
    wire out;
    integer contador=0;
    Debounce DUT(.clock(clk), .clear(clear), .out(out));
    
    initial begin
        clk = 0;
        clear = 0;
    end
        
    always begin
       #1 clk = ~clk;
       if(contador%18 == 0) begin
           clear = ~clear;
       end
       contador++;
       if(contador==103) begin
           $finish;
       end 
    end

    
    initial begin
        $dumpfile("vcd/Debounce.vcd");
        $dumpvars;
    end

    
    initial begin
        #1 $monitor("Contador: %d,  clock: %d,  clear: %d, saida: %d", contador, clk, clear, out);
    end
        
    


endmodule

vcd/Debounce.vcd
$date
	Thu Apr 29 17:12:48 2021
$end
$version
	Icarus Verilog
$end
$timescale
	1ps
$end
$scope module tb_Debounce $end
$var wire 1 ! out $end
$var reg 1 " clear $end
$var reg 1 # clk $end
$var integer 32 $ contador [31:0] $end
$scope module DUT $end
$var wire 1 " clear $end
$var wire 1 # clock $end
$var reg 3 % cont [2:0] $end
$var reg 1 ! out $end
$upscope $end
$upscope $end
$enddefinitions $end
#0
$dumpvars
b0 %
b0 $
0#
0"
x!
$end
#1000
0!
b1 $
1"
1#
#2000
b10 $
0#
#3000
b11 $
1#
#4000
b100 $
0#
#5000
b101 $
1#
#6000
b110 $
0#
#7000
b111 $
1#
#8000
b1000 $
0#
#9000
b1001 $
1#
#10000
b1010 $
0#
#11000
b1011 $
1#
#12000
b1100 $
0#
#13000
b1101 $
1#
#14000
b1110 $
0#
#15000
b1111 $
1#
#16000
b10000 $
0#
#17000
b10001 $
1#
#18000
b10010 $
0#
#19000
b1 %
b10011 $
0"
1#
#20000
b10100 $
0#
#21000
b10 %
b10101 $
1#
#22000
b10110 $
0#
#23000
b11 %
b10111 $
1#
#24000
b11000 $
0#
#25000
b100 %
b11001 $
1#
#26000
b11010 $
0#
#27000
1!
b101 %
b11011 $
1#
#28000
b11100 $
0#
#29000
b110 %
b11101 $
1#
#30000
b11110 $
0#
#31000
b111 %
b11111 $
1#
#32000
b100000 $
0#
#33000
b100001 $
1#
#34000
b100010 $
0#
#35000
b100011 $
1#
#36000
b100100 $
0#
#37000
b0 %
0!
b100101 $
1"
1#
#38000
b100110 $
0#
#39000
b100111 $
1#
#40000
b101000 $
0#
#41000
b101001 $
1#
#42000
b101010 $
0#
#43000
b101011 $
1#
#44000
b101100 $
0#
#45000
b101101 $
1#
#46000
b101110 $
0#
#47000
b101111 $
1#
#48000
b110000 $
0#
#49000
b110001 $
1#
#50000
b110010 $
0#
#51000
b110011 $
1#
#52000
b110100 $
0#
#53000
b110101 $
1#
#54000
b110110 $
0#
#55000
b1 %
b110111 $
0"
1#
#56000
b111000 $
0#
#57000
b10 %
b111001 $
1#
#58000
b111010 $
0#
#59000
b11 %
b111011 $
1#
#60000
b111100 $
0#
#61000
b100 %
b111101 $
1#
#62000
b111110 $
0#
#63000
1!
b101 %
b111111 $
1#
#64000
b1000000 $
0#
#65000
b110 %
b1000001 $
1#
#66000
b1000010 $
0#
#67000
b111 %
b1000011 $
1#
#68000
b1000100 $
0#
#69000
b1000101 $
1#
#70000
b1000110 $
0#
#71000
b1000111 $
1#
#72000
b1001000 $
0#
#73000
b0 %
0!
b1001001 $
1"
1#
#74000
b1001010 $
0#
#75000
b1001011 $
1#
#76000
b1001100 $
0#
#77000
b1001101 $
1#
#78000
b1001110 $
0#
#79000
b1001111 $
1#
#80000
b1010000 $
0#
#81000
b1010001 $
1#
#82000
b1010010 $
0#
#83000
b1010011 $
1#
#84000
b1010100 $
0#
#85000
b1010101 $
1#
#86000
b1010110 $
0#
#87000
b1010111 $
1#
#88000
b1011000 $
0#
#89000
b1011001 $
1#
#90000
b1011010 $
0#
#91000
b1 %
b1011011 $
0"
1#
#92000
b1011100 $
0#
#93000
b10 %
b1011101 $
1#
#94000
b1011110 $
0#
#95000
b11 %
b1011111 $
1#
#96000
b1100000 $
0#
#97000
b100 %
b1100001 $
1#
#98000
b1100010 $
0#
#99000
1!
b101 %
b1100011 $
1#
#100000
b1100100 $
0#
#101000
b110 %
b1100101 $
1#
#102000
b1100110 $
0#
#103000
b111 %
b1100111 $
1#
