src/bcd_seven.v
`timescale 1ns/1ps

module bcd_seven (bcd, seven);

    input [3:0] bcd;
    output[7:1] seven;

    reg [7:1] seven;

    always @(bcd)
    begin
        case (bcd)
        4'b0000 : seven = 7'b0111111; 
        4'b0001 : seven = 7'b0000110;
        4'b0010 : seven = 7'b1011011;
        4'b0011 : seven = 7'b1001111;
        4'b0100 : seven = 7'b1100110;
        4'b0101 : seven = 7'b1101101;
        4'b0110 : seven = 7'b1111101;
        4'b0111 : seven = 7'b0000111;
        4'b1000 : seven = 7'b1111111;
        4'b1001 : seven = 7'b1101111;
        default : seven = 7'b0000000;

        endcase
    end

endmodule

src/decoder/decoder.v
`timescale 1ns/1ps

module decoder (
    sec_ones, sec_tens,min,
    sec_ones_segs,sec_tens_segs,min_segs

);

    input [3:0] sec_ones, sec_tens,min;
    output[6:0] sec_ones_segs,sec_tens_segs, min_segs;

    bcd_seven sec_ones_module(.bcd(sec_ones),.seven(sec_ones_segs));

    bcd_seven sec_tens_module(.bcd(sec_tens),.seven(sec_tens_segs));

    bcd_seven min_module(.bcd(min),.seven(min_segs));

endmodule

testbenches/tb_decoder.v
`timescale 1ns/1ps

module tb_decoder;

    reg [3:0] sec_ones, sec_tens,min,i;
    wire [6:0] sec_ones_segs,sec_tens_segs,min_segs;

    decoder t(.sec_ones(sec_ones),.sec_tens(sec_tens),.min(min),.sec_ones_segs(sec_ones_segs),.sec_tens_segs(sec_tens_segs),.min_segs(min_segs));


    initial begin
        
        for(i = 0; i<10;i = i+1)begin
            sec_ones=$urandom%10; 
            sec_tens=$urandom%10;
            min = $urandom%10;
            #2;
            $display("A %d, B: %d",min,sec_ones); 
            #2;
            $display("C %b, D: %b",min_segs,sec_ones_segs); 
            #20;
        end


    end

    initial begin
        $dumpfile("decoder.vcd");
        $dumpvars;
    end
    
    


endmodule

vcd/decoder.vcd
$date
	Thu Apr 29 23:55:47 2021
$end
$version
	Icarus Verilog
$end
$timescale
	1ps
$end
$scope module tb_decoder $end
$var wire 7 ! sec_tens_segs [6:0] $end
$var wire 7 " sec_ones_segs [6:0] $end
$var wire 7 # min_segs [6:0] $end
$var reg 4 $ i [3:0] $end
$var reg 4 % min [3:0] $end
$var reg 4 & sec_ones [3:0] $end
$var reg 4 ' sec_tens [3:0] $end
$scope module t $end
$var wire 4 ( min [3:0] $end
$var wire 4 ) sec_ones [3:0] $end
$var wire 4 * sec_tens [3:0] $end
$var wire 7 + sec_tens_segs [6:0] $end
$var wire 7 , sec_ones_segs [6:0] $end
$var wire 7 - min_segs [6:0] $end
$scope module min_module $end
$var wire 4 . bcd [3:0] $end
$var reg 7 / seven [6:0] $end
$upscope $end
$scope module sec_ones_module $end
$var wire 4 0 bcd [3:0] $end
$var reg 7 1 seven [6:0] $end
$upscope $end
$scope module sec_tens_module $end
$var wire 4 2 bcd [3:0] $end
$var reg 7 3 seven [6:0] $end
$upscope $end
$upscope $end
$upscope $end
$enddefinitions $end
#0
$dumpvars
b1111011 3
b1001 2
b1011111 1
b110 0
b1111011 /
b1001 .
b1111011 -
b1011111 ,
b1111011 +
b1001 *
b110 )
b1001 (
b1001 '
b110 &
b1001 %
b0 $
b1111011 #
b1011111 "
b1111011 !
$end
#24000
b1011011 #
b1011011 -
b1011011 /
b1011011 !
b1011011 +
b1011011 3
b1111011 "
b1111011 ,
b1111011 1
b101 %
b101 (
b101 .
b101 '
b101 *
b101 2
b1001 &
b1001 )
b1001 0
b1 $
#48000
b1111011 #
b1111011 -
b1111011 /
b110011 !
b110011 +
b110011 3
b1110000 "
b1110000 ,
b1110000 1
b1001 %
b1001 (
b1001 .
b100 '
b100 *
b100 2
b111 &
b111 )
b111 0
b10 $
#72000
b1011011 #
b1011011 -
b1011011 /
b1011111 !
b1011111 +
b1011111 3
b101 %
b101 (
b101 .
b110 '
b110 *
b110 2
b11 $
#96000
b1110000 #
b1110000 -
b1110000 /
b111111 !
b111111 +
b111111 3
b111 %
b111 (
b111 .
b0 '
b0 *
b0 2
b100 $
#120000
b110011 #
b110011 -
b110011 /
b1111011 !
b1111011 +
b1111011 3
b1111111 "
b1111111 ,
b1111111 1
b100 %
b100 (
b100 .
b1001 '
b1001 *
b1001 2
b1000 &
b1000 )
b1000 0
b101 $
#144000
b1011111 #
b1011111 -
b1011111 /
b1110000 !
b1110000 +
b1110000 3
b1111001 "
b1111001 ,
b1111001 1
b110 %
b110 (
b110 .
b111 '
b111 *
b111 2
b11 &
b11 )
b11 0
b110 $
#168000
b1101101 #
b1101101 -
b1101101 /
b110011 !
b110011 +
b110011 3
b1110000 "
b1110000 ,
b1110000 1
b10 %
b10 (
b10 .
b100 '
b100 *
b100 2
b111 &
b111 )
b111 0
b111 $
#192000
b1011011 !
b1011011 +
b1011011 3
b111111 "
b111111 ,
b111111 1
b101 '
b101 *
b101 2
b0 &
b0 )
b0 0
b1000 $
#216000
b110000 #
b110000 -
b110000 /
b110000 !
b110000 +
b110000 3
b1011011 "
b1011011 ,
b1011011 1
b1 %
b1 (
b1 .
b1 '
b1 *
b1 2
b101 &
b101 )
b101 0
b1001 $
#240000
b1010 $
