src/encoder/mux_2to1.v
module mux_2to1 (
    input wire DelayIn, DivideBy100, sel,
    output wire out
);
    assign out = (sel ==0? DelayIn: DivideBy100);
endmodule

src/encoder/Debounce.v
module Debounce (input wire clock, clear,
                   output reg out);
    reg [2:0] cont=0;
    always @(posedge clock && !clear) begin
        cont <= (cont==3'd7? cont: cont +1);
        if(cont == 3'd4) begin
            out <= 1;
        end
    end
    always @(posedge clock && clear) begin
        out<=0;
        cont<=0;
    end
endmodule

src/encoder/DivideBy100.v
module DivideBy100 (input wire clk,
                    output reg clkOut);
    reg [6:0] cont = 7'd1;
    always @(posedge clk) begin
        if(cont == 7'd50) begin
            cont <=1;
            clkOut <=1;
        end
        else begin
            clkOut <=0;
            cont <= cont +1;
        end
    end
endmodule

src/encoder/priority_encoder.v
module priority_encoder(
    input wire [9:0] keypad,
    input wire enablen,
    output reg [3:0] bcd,
    output reg data_valid
);

    always @ (*) begin
        if(!enablen) begin
            case(keypad) 
                10'b1000000000: bcd = 9;
                10'b0100000000: bcd = 8;
                10'b0010000000: bcd = 7;
                10'b0001000000: bcd = 6;
                10'b0000100000: bcd = 5;
                10'b0000010000: bcd = 4;
                10'b0000001000: bcd = 3;
                10'b0000000100: bcd = 2;
                10'b0000000010: bcd = 1;
                10'b0000000001: bcd = 0;
                default: bcd = 1'bxxx;
            endcase
        end
        
        data_valid = (keypad == 10'b0000000000)? 1 : 0;
    end

     


endmodule

src/encoder/encoder.v
module encoder(
    input wire [9:0]Keypad,
    input wire Clk,
    input wire Enablen,
    output wire [3:0]D,
    output wire loadn,
    output wire pgt_1Hz
);
    wire DataValid, outFreq, outDebounce;
    
    priority_encoder DUT1(.keypad(Keypad), .enablen(Enablen), .bcd(D), .data_valid(DataValid));
    
    DivideBy100 Dut2(.clk(clk), .clkOut(outFreq));
    
    Debounce Dut3(.clock(Clk), .clear(DataValid), .out(outDebounce));
    
    mux_2to1 Dut4(.DelayIn(outDebounce), .DivideBy100(outFreq), .sel(Enablen), .out(pgt_1Hz));
    
    assign loadn = DataValid;
    

endmodule

testbenches/tb_encoder.v
`timescale 1ns/1ps

module tb_encoder;
    
    reg [9:0]Keypad;
    reg Clk, Enablen;
    wire [3:0]D;
    wire loadn, pgt_1Hz;
    integer contador=0;
    
    encoder DUT(.Keypad(Keypad), .Clk(Clk), .Enablen(Enablen), .D(D), .loadn(loadn), .pgt_1Hz(pgt_1Hz));
    
    initial begin
        Keypad=1;
        Clk = 0;
        Enablen = 0;
    end
        
     
       

    always begin 
        #1 Clk = ~Clk;
        contador++;
        if(contador==103) begin
           $finish;
        end
        Keypad <= Keypad*2;
        if(contador%19 == 0) begin
            Keypad <= 0;
        end
        if(contador%10 == 0) begin
            Enablen <= 1;
        end 
        else begin
            Enablen <= 0;
        end
        if(Keypad==0) begin
            Keypad <= 1;
        end
       
        
    end

    
    initial begin
        $dumpfile("vcd/Encoder.vcd");
        $dumpvars;
    end

    
    initial begin
        #1 $monitor("Contador: %d, clk: %d, Enablen: %d, Keypad: %b, DadoSaida: %d, loadn: %d, pgt_1Hz: %d", contador, Clk, Enablen, Keypad, D, loadn, pgt_1Hz);
    end
        
    


endmodule

vcd/Encoder.vcd
$date
	Fri Apr 30 00:08:10 2021
$end
$version
	Icarus Verilog
$end
$timescale
	1ps
$end
$scope module tb_encoder $end
$var wire 1 ! pgt_1Hz $end
$var wire 1 " loadn $end
$var wire 4 # D [3:0] $end
$var reg 1 $ Clk $end
$var reg 1 % Enablen $end
$var reg 10 & Keypad [9:0] $end
$var integer 32 ' contador [31:0] $end
$scope module DUT $end
$var wire 1 $ Clk $end
$var wire 1 % Enablen $end
$var wire 10 ( Keypad [9:0] $end
$var wire 1 ) clk $end
$var wire 1 " loadn $end
$var wire 1 ! pgt_1Hz $end
$var wire 1 * outFreq $end
$var wire 1 + outDebounce $end
$var wire 1 , DataValid $end
$var wire 4 - D [3:0] $end
$scope module DUT1 $end
$var wire 1 % enablen $end
$var wire 10 . keypad [9:0] $end
$var reg 4 / bcd [3:0] $end
$var reg 1 , data_valid $end
$upscope $end
$scope module Dut2 $end
$var wire 1 ) clk $end
$var reg 1 * clkOut $end
$var reg 7 0 cont [6:0] $end
$upscope $end
$scope module Dut3 $end
$var wire 1 , clear $end
$var wire 1 $ clock $end
$var reg 3 1 cont [2:0] $end
$var reg 1 + out $end
$upscope $end
$scope module Dut4 $end
$var wire 1 + DelayIn $end
$var wire 1 * DivideBy100 $end
$var wire 1 % sel $end
$var wire 1 ! out $end
$upscope $end
$upscope $end
$upscope $end
$enddefinitions $end
#0
$dumpvars
b0 1
b1 0
b0 /
b1 .
b0 -
0,
x+
x*
z)
b1 (
b0 '
b1 &
0%
0$
b0 #
0"
x!
$end
#1000
b1 #
b1 -
b1 /
b1 1
b10 &
b10 (
b10 .
b1 '
1$
#2000
b10 #
b10 -
b10 /
b100 &
b100 (
b100 .
b10 '
0$
#3000
b11 #
b11 -
b11 /
b10 1
b1000 &
b1000 (
b1000 .
b11 '
1$
#4000
b100 #
b100 -
b100 /
b10000 &
b10000 (
b10000 .
b100 '
0$
#5000
b101 #
b101 -
b101 /
b11 1
b100000 &
b100000 (
b100000 .
b101 '
1$
#6000
b110 #
b110 -
b110 /
b1000000 &
b1000000 (
b1000000 .
b110 '
0$
#7000
b111 #
b111 -
b111 /
b100 1
b10000000 &
b10000000 (
b10000000 .
b111 '
1$
#8000
b1000 #
b1000 -
b1000 /
b100000000 &
b100000000 (
b100000000 .
b1000 '
0$
#9000
1!
b1001 #
b1001 -
b1001 /
1+
b101 1
b1000000000 &
b1000000000 (
b1000000000 .
b1001 '
1$
#10000
x!
1"
1,
1%
b0 &
b0 (
b0 .
b1010 '
0$
#11000
0"
0,
b0 #
b0 -
b0 /
0!
b1 1
0+
b1 &
b1 (
b1 .
0%
b1011 '
1$
#12000
b1 #
b1 -
b1 /
b10 &
b10 (
b10 .
b1100 '
0$
#13000
b10 #
b10 -
b10 /
b10 1
b100 &
b100 (
b100 .
b1101 '
1$
#14000
b11 #
b11 -
b11 /
b1000 &
b1000 (
b1000 .
b1110 '
0$
#15000
b100 #
b100 -
b100 /
b11 1
b10000 &
b10000 (
b10000 .
b1111 '
1$
#16000
b101 #
b101 -
b101 /
b100000 &
b100000 (
b100000 .
b10000 '
0$
#17000
b110 #
b110 -
b110 /
b100 1
b1000000 &
b1000000 (
b1000000 .
b10001 '
1$
#18000
b111 #
b111 -
b111 /
b10000000 &
b10000000 (
b10000000 .
b10010 '
0$
#19000
0!
1"
1,
b0xxx #
b0xxx -
b0xxx /
0+
b0 1
b0 &
b0 (
b0 .
b10011 '
1$
#20000
0"
0,
x!
b1 &
b1 (
b1 .
1%
b10100 '
0$
#21000
0!
b1 #
b1 -
b1 /
b1 1
0%
b10 &
b10 (
b10 .
b10101 '
1$
#22000
b10 #
b10 -
b10 /
b100 &
b100 (
b100 .
b10110 '
0$
#23000
b11 #
b11 -
b11 /
b10 1
b1000 &
b1000 (
b1000 .
b10111 '
1$
#24000
b100 #
b100 -
b100 /
b10000 &
b10000 (
b10000 .
b11000 '
0$
#25000
b101 #
b101 -
b101 /
b11 1
b100000 &
b100000 (
b100000 .
b11001 '
1$
#26000
b110 #
b110 -
b110 /
b1000000 &
b1000000 (
b1000000 .
b11010 '
0$
#27000
b111 #
b111 -
b111 /
b100 1
b10000000 &
b10000000 (
b10000000 .
b11011 '
1$
#28000
b1000 #
b1000 -
b1000 /
b100000000 &
b100000000 (
b100000000 .
b11100 '
0$
#29000
1!
b1001 #
b1001 -
b1001 /
1+
b101 1
b1000000000 &
b1000000000 (
b1000000000 .
b11101 '
1$
#30000
x!
1"
1,
1%
b0 &
b0 (
b0 .
b11110 '
0$
#31000
0"
0,
b0 #
b0 -
b0 /
0!
b1 1
0+
b1 &
b1 (
b1 .
0%
b11111 '
1$
#32000
b1 #
b1 -
b1 /
b10 &
b10 (
b10 .
b100000 '
0$
#33000
b10 #
b10 -
b10 /
b10 1
b100 &
b100 (
b100 .
b100001 '
1$
#34000
b11 #
b11 -
b11 /
b1000 &
b1000 (
b1000 .
b100010 '
0$
#35000
b100 #
b100 -
b100 /
b11 1
b10000 &
b10000 (
b10000 .
b100011 '
1$
#36000
b101 #
b101 -
b101 /
b100000 &
b100000 (
b100000 .
b100100 '
0$
#37000
b110 #
b110 -
b110 /
b100 1
b1000000 &
b1000000 (
b1000000 .
b100101 '
1$
#38000
1"
1,
b0xxx #
b0xxx -
b0xxx /
b0 &
b0 (
b0 .
b100110 '
0$
#39000
0"
0,
b0 #
b0 -
b0 /
b1 1
b1 &
b1 (
b1 .
b100111 '
1$
#40000
x!
1%
b10 &
b10 (
b10 .
b101000 '
0$
#41000
0!
b10 #
b10 -
b10 /
b10 1
0%
b100 &
b100 (
b100 .
b101001 '
1$
#42000
b11 #
b11 -
b11 /
b1000 &
b1000 (
b1000 .
b101010 '
0$
#43000
b100 #
b100 -
b100 /
b11 1
b10000 &
b10000 (
b10000 .
b101011 '
1$
#44000
b101 #
b101 -
b101 /
b100000 &
b100000 (
b100000 .
b101100 '
0$
#45000
b110 #
b110 -
b110 /
b100 1
b1000000 &
b1000000 (
b1000000 .
b101101 '
1$
#46000
b111 #
b111 -
b111 /
b10000000 &
b10000000 (
b10000000 .
b101110 '
0$
#47000
1!
b1000 #
b1000 -
b1000 /
1+
b101 1
b100000000 &
b100000000 (
b100000000 .
b101111 '
1$
#48000
b1001 #
b1001 -
b1001 /
b1000000000 &
b1000000000 (
b1000000000 .
b110000 '
0$
#49000
0!
0+
1"
1,
b0xxx #
b0xxx -
b0xxx /
b0 1
b0 &
b0 (
b0 .
b110001 '
1$
#50000
0"
0,
x!
b1 &
b1 (
b1 .
1%
b110010 '
0$
#51000
0!
b1 #
b1 -
b1 /
b1 1
0%
b10 &
b10 (
b10 .
b110011 '
1$
#52000
b10 #
b10 -
b10 /
b100 &
b100 (
b100 .
b110100 '
0$
#53000
b11 #
b11 -
b11 /
b10 1
b1000 &
b1000 (
b1000 .
b110101 '
1$
#54000
b100 #
b100 -
b100 /
b10000 &
b10000 (
b10000 .
b110110 '
0$
#55000
b101 #
b101 -
b101 /
b11 1
b100000 &
b100000 (
b100000 .
b110111 '
1$
#56000
b110 #
b110 -
b110 /
b1000000 &
b1000000 (
b1000000 .
b111000 '
0$
#57000
1"
1,
b0xxx #
b0xxx -
b0xxx /
b0 1
b0 &
b0 (
b0 .
b111001 '
1$
#58000
0"
0,
b0 #
b0 -
b0 /
b1 &
b1 (
b1 .
b111010 '
0$
#59000
b1 #
b1 -
b1 /
b1 1
b10 &
b10 (
b10 .
b111011 '
1$
#60000
x!
1%
b100 &
b100 (
b100 .
b111100 '
0$
#61000
0!
b11 #
b11 -
b11 /
b10 1
0%
b1000 &
b1000 (
b1000 .
b111101 '
1$
#62000
b100 #
b100 -
b100 /
b10000 &
b10000 (
b10000 .
b111110 '
0$
#63000
b101 #
b101 -
b101 /
b11 1
b100000 &
b100000 (
b100000 .
b111111 '
1$
#64000
b110 #
b110 -
b110 /
b1000000 &
b1000000 (
b1000000 .
b1000000 '
0$
#65000
b111 #
b111 -
b111 /
b100 1
b10000000 &
b10000000 (
b10000000 .
b1000001 '
1$
#66000
b1000 #
b1000 -
b1000 /
b100000000 &
b100000000 (
b100000000 .
b1000010 '
0$
#67000
1!
b1001 #
b1001 -
b1001 /
1+
b101 1
b1000000000 &
b1000000000 (
b1000000000 .
b1000011 '
1$
#68000
1"
1,
b0xxx #
b0xxx -
b0xxx /
b0 &
b0 (
b0 .
b1000100 '
0$
#69000
0!
0"
0,
b0 #
b0 -
b0 /
b1 1
0+
b1 &
b1 (
b1 .
b1000101 '
1$
#70000
x!
1%
b10 &
b10 (
b10 .
b1000110 '
0$
#71000
0!
b10 #
b10 -
b10 /
b10 1
0%
b100 &
b100 (
b100 .
b1000111 '
1$
#72000
b11 #
b11 -
b11 /
b1000 &
b1000 (
b1000 .
b1001000 '
0$
#73000
b100 #
b100 -
b100 /
b11 1
b10000 &
b10000 (
b10000 .
b1001001 '
1$
#74000
b101 #
b101 -
b101 /
b100000 &
b100000 (
b100000 .
b1001010 '
0$
#75000
b110 #
b110 -
b110 /
b100 1
b1000000 &
b1000000 (
b1000000 .
b1001011 '
1$
#76000
1"
1,
b0xxx #
b0xxx -
b0xxx /
b0 &
b0 (
b0 .
b1001100 '
0$
#77000
0"
0,
b0 #
b0 -
b0 /
b1 1
b1 &
b1 (
b1 .
b1001101 '
1$
#78000
b1 #
b1 -
b1 /
b10 &
b10 (
b10 .
b1001110 '
0$
#79000
b10 #
b10 -
b10 /
b10 1
b100 &
b100 (
b100 .
b1001111 '
1$
#80000
x!
1%
b1000 &
b1000 (
b1000 .
b1010000 '
0$
#81000
0!
b100 #
b100 -
b100 /
b11 1
0%
b10000 &
b10000 (
b10000 .
b1010001 '
1$
#82000
b101 #
b101 -
b101 /
b100000 &
b100000 (
b100000 .
b1010010 '
0$
#83000
b110 #
b110 -
b110 /
b100 1
b1000000 &
b1000000 (
b1000000 .
b1010011 '
1$
#84000
b111 #
b111 -
b111 /
b10000000 &
b10000000 (
b10000000 .
b1010100 '
0$
#85000
1!
b1000 #
b1000 -
b1000 /
1+
b101 1
b100000000 &
b100000000 (
b100000000 .
b1010101 '
1$
#86000
b1001 #
b1001 -
b1001 /
b1000000000 &
b1000000000 (
b1000000000 .
b1010110 '
0$
#87000
0!
0+
1"
1,
b0xxx #
b0xxx -
b0xxx /
b0 1
b0 &
b0 (
b0 .
b1010111 '
1$
#88000
0"
0,
b0 #
b0 -
b0 /
b1 &
b1 (
b1 .
b1011000 '
0$
#89000
b1 #
b1 -
b1 /
b1 1
b10 &
b10 (
b10 .
b1011001 '
1$
#90000
x!
1%
b100 &
b100 (
b100 .
b1011010 '
0$
#91000
0!
b11 #
b11 -
b11 /
b10 1
0%
b1000 &
b1000 (
b1000 .
b1011011 '
1$
#92000
b100 #
b100 -
b100 /
b10000 &
b10000 (
b10000 .
b1011100 '
0$
#93000
b101 #
b101 -
b101 /
b11 1
b100000 &
b100000 (
b100000 .
b1011101 '
1$
#94000
b110 #
b110 -
b110 /
b1000000 &
b1000000 (
b1000000 .
b1011110 '
0$
#95000
1"
1,
b0xxx #
b0xxx -
b0xxx /
b0 1
b0 &
b0 (
b0 .
b1011111 '
1$
#96000
0"
0,
b0 #
b0 -
b0 /
b1 &
b1 (
b1 .
b1100000 '
0$
#97000
b1 #
b1 -
b1 /
b1 1
b10 &
b10 (
b10 .
b1100001 '
1$
#98000
b10 #
b10 -
b10 /
b100 &
b100 (
b100 .
b1100010 '
0$
#99000
b11 #
b11 -
b11 /
b10 1
b1000 &
b1000 (
b1000 .
b1100011 '
1$
#100000
x!
1%
b10000 &
b10000 (
b10000 .
b1100100 '
0$
#101000
0!
b101 #
b101 -
b101 /
b11 1
0%
b100000 &
b100000 (
b100000 .
b1100101 '
1$
#102000
b110 #
b110 -
b110 /
b1000000 &
b1000000 (
b1000000 .
b1100110 '
0$
#103000
b100 1
b1100111 '
1$
