src/timer/mod10.v
`timescale 1ns/1ps

module mod10(
    input wire [3:0] data,
    input wire loadn, clrn, clk, en,
    output reg [3:0] ones,
    output reg tc, zero
);

    always @ (posedge clk, negedge clrn) begin
        
        if(~en);
        else if(~loadn) begin
            ones <= data;
            if(data == 4'b0000)
                zero <= tc <= 1;
            else 
                zero <= tc <= 0;
        end
        else if(clrn) begin
            ones <= 4'b0000;
            tc <= 1;
            zero <= 1;
        end
        else begin
                
            if(ones == 0) begin
                ones <= 9;
                tc <= 1;
                zero <= 1;
            end
            else begin
                ones <= (ones-1)%10;
                tc <= 0;
                zero <= 0;
            end
        end
    end


endmodule

testbenches/tb_mod10.v
`timescale 1ns/1ps

module tb_mod10;

    reg [3:0] data;
    reg loadn;
    reg clk;
    reg en;
    reg clrn;
    wire [3:0] ones;
    wire tc, zero;
    integer ticks=0;
    initial begin
        data = 4'b1001; clk = 0; en = 1; clrn = 0; 
        #5 loadn = 0;
        #5 loadn = 1; 
        #40 clrn = 1;
        #10 en = 0;
        #20;
        $stop;
    end

    mod10 countdown(.data(data), .loadn(loadn), .clrn(clrn), .clk(clk), .en(en), .ones(ones), .tc(tc), .zero(zero) );

    
    initial begin
        $dumpfile("vcd/mod10.vcd");
        $dumpvars;
    end

    always begin
         #5 clk = ~clk; ticks++;
    end
    initial
    #1 $monitor("%b ", ones);
    


endmodule

vcd/mod10.vcd
$date
	Sat Apr 24 23:04:09 2021
$end
$version
	Icarus Verilog
$end
$timescale
	1ps
$end
$scope module tb_mod10 $end
$var wire 1 ! zero $end
$var wire 1 " tc $end
$var wire 4 # ones [3:0] $end
$var reg 1 $ clk $end
$var reg 1 % clrn $end
$var reg 4 & data [3:0] $end
$var reg 1 ' en $end
$var reg 1 ( loadn $end
$var integer 32 ) ticks [31:0] $end
$scope module countdown $end
$var wire 1 $ clk $end
$var wire 1 % clrn $end
$var wire 4 * data [3:0] $end
$var wire 1 ' en $end
$var wire 1 ( loadn $end
$var reg 4 + ones [3:0] $end
$var reg 1 " tc $end
$var reg 1 ! zero $end
$upscope $end
$upscope $end
$enddefinitions $end
#0
$dumpvars
bx +
b1001 *
b0 )
x(
1'
b1001 &
0%
0$
bx #
0"
0!
$end
#5000
1!
b1001 #
b1001 +
b1 )
1$
0(
#10000
b10 )
0$
1(
#15000
0!
b1000 #
b1000 +
b11 )
1$
#20000
b100 )
0$
#25000
b111 #
b111 +
b101 )
1$
#30000
b110 )
0$
#35000
b110 #
b110 +
b111 )
1$
#40000
b1000 )
0$
#45000
b101 #
b101 +
b1001 )
1$
#50000
b1010 )
0$
1%
#55000
1!
1"
b0 #
b0 +
b1011 )
1$
#60000
b1100 )
0$
0'
#65000
b1101 )
1$
#70000
b1110 )
0$
#75000
b1111 )
1$
