src/timer/mod10.v
`timescale 1ns/1ps

//  TODO checar o *tc*

module mod10(
    input wire [3:0] data,
    input wire loadn, clrn, clk, en,
    output reg [3:0] out,
    output reg tc, zero
);

    always @ (posedge clk or negedge clrn) begin
        
        if(!clrn) begin
            out = 0;
            tc = 0;
            zero = 0;
        end
        else if(!loadn) begin
            out <= data;
        end 
        else begin
            if(en) begin
               if(out == 0)  begin
                    out <= 9;
                    tc <= 0;
                    zero <= 0;
                end
                else begin
                    out <= out-1;
                    tc <= (out-1 == 0?  1: 0);
                    zero <= (out-1== 0? 1: 0);
                end 
            end
            else
                tc <= 0;
        end
    end


endmodule

testbenches/tb_mod10.v
`timescale 1ns/1ps

module tb_mod10;

    reg [3:0] data;
    reg loadn, clk, en, clrn;
    wire [3:0] ones;
    wire tc, zero;
    integer ticks=0;

    mod10 countdown(.data(data), .loadn(loadn), .clrn(clrn), .clk(clk), .en(en), .out(ones), .tc(tc), .zero(zero) );

    initial begin
        clrn = 0;
        #5 clrn = 1;
    end
    
    initial 
        clk = 0;
    
    always begin 
        #10 clk = ~clk; ticks++;
        if(ticks == 300) 
            $finish;
    end
    initial begin
        loadn = 1; data = 4; en = 1;
        #10 loadn = 0; loadn = #5 1;


    end
    initial begin
        $dumpfile("vcd/mod10.vcd");
        $dumpvars;
    end

    initial
    #1 $monitor("%b ", ones);
    


endmodule

vcd/mod10.vcd
$date
	Wed Apr 28 16:53:57 2021
$end
$version
	Icarus Verilog
$end
$timescale
	1ps
$end
$scope module tb_mod10 $end
$var wire 1 ! zero $end
$var wire 1 " tc $end
$var wire 4 # ones [3:0] $end
$var reg 1 $ clk $end
$var reg 1 % clrn $end
$var reg 4 & data [3:0] $end
$var reg 1 ' en $end
$var reg 1 ( loadn $end
$var integer 32 ) ticks [31:0] $end
$scope module countdown $end
$var wire 1 $ clk $end
$var wire 1 % clrn $end
$var wire 4 * data [3:0] $end
$var wire 1 ' en $end
$var wire 1 ( loadn $end
$var reg 4 + out [3:0] $end
$var reg 1 " tc $end
$var reg 1 ! zero $end
$upscope $end
$upscope $end
$enddefinitions $end
#0
$dumpvars
b0 +
b100 *
b0 )
1(
1'
b100 &
0%
0$
b0 #
0"
0!
$end
#5000
1%
#10000
b100 #
b100 +
0(
b1 )
1$
#15000
1(
#20000
b10 )
0$
#30000
b11 #
b11 +
b11 )
1$
#40000
b100 )
0$
#50000
b10 #
b10 +
b101 )
1$
#60000
b110 )
0$
#70000
b1 #
b1 +
b111 )
1$
#80000
b1000 )
0$
#90000
b0 #
b0 +
b1001 )
1$
#100000
b1010 )
0$
#110000
1!
1"
b1001 #
b1001 +
b1011 )
1$
#120000
b1100 )
0$
#130000
0!
0"
b1000 #
b1000 +
b1101 )
1$
#140000
b1110 )
0$
#150000
b111 #
b111 +
b1111 )
1$
#160000
b10000 )
0$
#170000
b110 #
b110 +
b10001 )
1$
#180000
b10010 )
0$
#190000
b101 #
b101 +
b10011 )
1$
#200000
b10100 )
0$
#210000
b100 #
b100 +
b10101 )
1$
#220000
b10110 )
0$
#230000
b11 #
b11 +
b10111 )
1$
#240000
b11000 )
0$
#250000
b10 #
b10 +
b11001 )
1$
#260000
b11010 )
0$
#270000
b1 #
b1 +
b11011 )
1$
#280000
b11100 )
0$
#290000
b0 #
b0 +
b11101 )
1$
#300000
b11110 )
0$
#310000
1!
1"
b1001 #
b1001 +
b11111 )
1$
#320000
b100000 )
0$
#330000
0!
0"
b1000 #
b1000 +
b100001 )
1$
#340000
b100010 )
0$
#350000
b111 #
b111 +
b100011 )
1$
#360000
b100100 )
0$
#370000
b110 #
b110 +
b100101 )
1$
#380000
b100110 )
0$
#390000
b101 #
b101 +
b100111 )
1$
#400000
b101000 )
0$
#410000
b100 #
b100 +
b101001 )
1$
#420000
b101010 )
0$
#430000
b11 #
b11 +
b101011 )
1$
#440000
b101100 )
0$
#450000
b10 #
b10 +
b101101 )
1$
#460000
b101110 )
0$
#470000
b1 #
b1 +
b101111 )
1$
#480000
b110000 )
0$
#490000
b0 #
b0 +
b110001 )
1$
#500000
b110010 )
0$
#510000
1!
1"
b1001 #
b1001 +
b110011 )
1$
#520000
b110100 )
0$
#530000
0!
0"
b1000 #
b1000 +
b110101 )
1$
#540000
b110110 )
0$
#550000
b111 #
b111 +
b110111 )
1$
#560000
b111000 )
0$
#570000
b110 #
b110 +
b111001 )
1$
#580000
b111010 )
0$
#590000
b101 #
b101 +
b111011 )
1$
#600000
b111100 )
0$
#610000
b100 #
b100 +
b111101 )
1$
#620000
b111110 )
0$
#630000
b11 #
b11 +
b111111 )
1$
#640000
b1000000 )
0$
#650000
b10 #
b10 +
b1000001 )
1$
#660000
b1000010 )
0$
#670000
b1 #
b1 +
b1000011 )
1$
#680000
b1000100 )
0$
#690000
b0 #
b0 +
b1000101 )
1$
#700000
b1000110 )
0$
#710000
1!
1"
b1001 #
b1001 +
b1000111 )
1$
#720000
b1001000 )
0$
#730000
0!
0"
b1000 #
b1000 +
b1001001 )
1$
#740000
b1001010 )
0$
#750000
b111 #
b111 +
b1001011 )
1$
#760000
b1001100 )
0$
#770000
b110 #
b110 +
b1001101 )
1$
#780000
b1001110 )
0$
#790000
b101 #
b101 +
b1001111 )
1$
#800000
b1010000 )
0$
#810000
b100 #
b100 +
b1010001 )
1$
#820000
b1010010 )
0$
#830000
b11 #
b11 +
b1010011 )
1$
#840000
b1010100 )
0$
#850000
b10 #
b10 +
b1010101 )
1$
#860000
b1010110 )
0$
#870000
b1 #
b1 +
b1010111 )
1$
#880000
b1011000 )
0$
#890000
b0 #
b0 +
b1011001 )
1$
#900000
b1011010 )
0$
#910000
1!
1"
b1001 #
b1001 +
b1011011 )
1$
#920000
b1011100 )
0$
#930000
0!
0"
b1000 #
b1000 +
b1011101 )
1$
#940000
b1011110 )
0$
#950000
b111 #
b111 +
b1011111 )
1$
#960000
b1100000 )
0$
#970000
b110 #
b110 +
b1100001 )
1$
#980000
b1100010 )
0$
#990000
b101 #
b101 +
b1100011 )
1$
#1000000
b1100100 )
0$
#1010000
b100 #
b100 +
b1100101 )
1$
#1020000
b1100110 )
0$
#1030000
b11 #
b11 +
b1100111 )
1$
#1040000
b1101000 )
0$
#1050000
b10 #
b10 +
b1101001 )
1$
#1060000
b1101010 )
0$
#1070000
b1 #
b1 +
b1101011 )
1$
#1080000
b1101100 )
0$
#1090000
b0 #
b0 +
b1101101 )
1$
#1100000
b1101110 )
0$
#1110000
1!
1"
b1001 #
b1001 +
b1101111 )
1$
#1120000
b1110000 )
0$
#1130000
0!
0"
b1000 #
b1000 +
b1110001 )
1$
#1140000
b1110010 )
0$
#1150000
b111 #
b111 +
b1110011 )
1$
#1160000
b1110100 )
0$
#1170000
b110 #
b110 +
b1110101 )
1$
#1180000
b1110110 )
0$
#1190000
b101 #
b101 +
b1110111 )
1$
#1200000
b1111000 )
0$
#1210000
b100 #
b100 +
b1111001 )
1$
#1220000
b1111010 )
0$
#1230000
b11 #
b11 +
b1111011 )
1$
#1240000
b1111100 )
0$
#1250000
b10 #
b10 +
b1111101 )
1$
#1260000
b1111110 )
0$
#1270000
b1 #
b1 +
b1111111 )
1$
#1280000
b10000000 )
0$
#1290000
b0 #
b0 +
b10000001 )
1$
#1300000
b10000010 )
0$
#1310000
1!
1"
b1001 #
b1001 +
b10000011 )
1$
#1320000
b10000100 )
0$
#1330000
0!
0"
b1000 #
b1000 +
b10000101 )
1$
#1340000
b10000110 )
0$
#1350000
b111 #
b111 +
b10000111 )
1$
#1360000
b10001000 )
0$
#1370000
b110 #
b110 +
b10001001 )
1$
#1380000
b10001010 )
0$
#1390000
b101 #
b101 +
b10001011 )
1$
#1400000
b10001100 )
0$
#1410000
b100 #
b100 +
b10001101 )
1$
#1420000
b10001110 )
0$
#1430000
b11 #
b11 +
b10001111 )
1$
#1440000
b10010000 )
0$
#1450000
b10 #
b10 +
b10010001 )
1$
#1460000
b10010010 )
0$
#1470000
b1 #
b1 +
b10010011 )
1$
#1480000
b10010100 )
0$
#1490000
b0 #
b0 +
b10010101 )
1$
#1500000
b10010110 )
0$
#1510000
1!
1"
b1001 #
b1001 +
b10010111 )
1$
#1520000
b10011000 )
0$
#1530000
0!
0"
b1000 #
b1000 +
b10011001 )
1$
#1540000
b10011010 )
0$
#1550000
b111 #
b111 +
b10011011 )
1$
#1560000
b10011100 )
0$
#1570000
b110 #
b110 +
b10011101 )
1$
#1580000
b10011110 )
0$
#1590000
b101 #
b101 +
b10011111 )
1$
#1600000
b10100000 )
0$
#1610000
b100 #
b100 +
b10100001 )
1$
#1620000
b10100010 )
0$
#1630000
b11 #
b11 +
b10100011 )
1$
#1640000
b10100100 )
0$
#1650000
b10 #
b10 +
b10100101 )
1$
#1660000
b10100110 )
0$
#1670000
b1 #
b1 +
b10100111 )
1$
#1680000
b10101000 )
0$
#1690000
b0 #
b0 +
b10101001 )
1$
#1700000
b10101010 )
0$
#1710000
1!
1"
b1001 #
b1001 +
b10101011 )
1$
#1720000
b10101100 )
0$
#1730000
0!
0"
b1000 #
b1000 +
b10101101 )
1$
#1740000
b10101110 )
0$
#1750000
b111 #
b111 +
b10101111 )
1$
#1760000
b10110000 )
0$
#1770000
b110 #
b110 +
b10110001 )
1$
#1780000
b10110010 )
0$
#1790000
b101 #
b101 +
b10110011 )
1$
#1800000
b10110100 )
0$
#1810000
b100 #
b100 +
b10110101 )
1$
#1820000
b10110110 )
0$
#1830000
b11 #
b11 +
b10110111 )
1$
#1840000
b10111000 )
0$
#1850000
b10 #
b10 +
b10111001 )
1$
#1860000
b10111010 )
0$
#1870000
b1 #
b1 +
b10111011 )
1$
#1880000
b10111100 )
0$
#1890000
b0 #
b0 +
b10111101 )
1$
#1900000
b10111110 )
0$
#1910000
1!
1"
b1001 #
b1001 +
b10111111 )
1$
#1920000
b11000000 )
0$
#1930000
0!
0"
b1000 #
b1000 +
b11000001 )
1$
#1940000
b11000010 )
0$
#1950000
b111 #
b111 +
b11000011 )
1$
#1960000
b11000100 )
0$
#1970000
b110 #
b110 +
b11000101 )
1$
#1980000
b11000110 )
0$
#1990000
b101 #
b101 +
b11000111 )
1$
#2000000
b11001000 )
0$
#2010000
b100 #
b100 +
b11001001 )
1$
#2020000
b11001010 )
0$
#2030000
b11 #
b11 +
b11001011 )
1$
#2040000
b11001100 )
0$
#2050000
b10 #
b10 +
b11001101 )
1$
#2060000
b11001110 )
0$
#2070000
b1 #
b1 +
b11001111 )
1$
#2080000
b11010000 )
0$
#2090000
b0 #
b0 +
b11010001 )
1$
#2100000
b11010010 )
0$
#2110000
1!
1"
b1001 #
b1001 +
b11010011 )
1$
#2120000
b11010100 )
0$
#2130000
0!
0"
b1000 #
b1000 +
b11010101 )
1$
#2140000
b11010110 )
0$
#2150000
b111 #
b111 +
b11010111 )
1$
#2160000
b11011000 )
0$
#2170000
b110 #
b110 +
b11011001 )
1$
#2180000
b11011010 )
0$
#2190000
b101 #
b101 +
b11011011 )
1$
#2200000
b11011100 )
0$
#2210000
b100 #
b100 +
b11011101 )
1$
#2220000
b11011110 )
0$
#2230000
b11 #
b11 +
b11011111 )
1$
#2240000
b11100000 )
0$
#2250000
b10 #
b10 +
b11100001 )
1$
#2260000
b11100010 )
0$
#2270000
b1 #
b1 +
b11100011 )
1$
#2280000
b11100100 )
0$
#2290000
b0 #
b0 +
b11100101 )
1$
#2300000
b11100110 )
0$
#2310000
1!
1"
b1001 #
b1001 +
b11100111 )
1$
#2320000
b11101000 )
0$
#2330000
0!
0"
b1000 #
b1000 +
b11101001 )
1$
#2340000
b11101010 )
0$
#2350000
b111 #
b111 +
b11101011 )
1$
#2360000
b11101100 )
0$
#2370000
b110 #
b110 +
b11101101 )
1$
#2380000
b11101110 )
0$
#2390000
b101 #
b101 +
b11101111 )
1$
#2400000
b11110000 )
0$
#2410000
b100 #
b100 +
b11110001 )
1$
#2420000
b11110010 )
0$
#2430000
b11 #
b11 +
b11110011 )
1$
#2440000
b11110100 )
0$
#2450000
b10 #
b10 +
b11110101 )
1$
#2460000
b11110110 )
0$
#2470000
b1 #
b1 +
b11110111 )
1$
#2480000
b11111000 )
0$
#2490000
b0 #
b0 +
b11111001 )
1$
#2500000
b11111010 )
0$
#2510000
1!
1"
b1001 #
b1001 +
b11111011 )
1$
#2520000
b11111100 )
0$
#2530000
0!
0"
b1000 #
b1000 +
b11111101 )
1$
#2540000
b11111110 )
0$
#2550000
b111 #
b111 +
b11111111 )
1$
#2560000
b100000000 )
0$
#2570000
b110 #
b110 +
b100000001 )
1$
#2580000
b100000010 )
0$
#2590000
b101 #
b101 +
b100000011 )
1$
#2600000
b100000100 )
0$
#2610000
b100 #
b100 +
b100000101 )
1$
#2620000
b100000110 )
0$
#2630000
b11 #
b11 +
b100000111 )
1$
#2640000
b100001000 )
0$
#2650000
b10 #
b10 +
b100001001 )
1$
#2660000
b100001010 )
0$
#2670000
b1 #
b1 +
b100001011 )
1$
#2680000
b100001100 )
0$
#2690000
b0 #
b0 +
b100001101 )
1$
#2700000
b100001110 )
0$
#2710000
1!
1"
b1001 #
b1001 +
b100001111 )
1$
#2720000
b100010000 )
0$
#2730000
0!
0"
b1000 #
b1000 +
b100010001 )
1$
#2740000
b100010010 )
0$
#2750000
b111 #
b111 +
b100010011 )
1$
#2760000
b100010100 )
0$
#2770000
b110 #
b110 +
b100010101 )
1$
#2780000
b100010110 )
0$
#2790000
b101 #
b101 +
b100010111 )
1$
#2800000
b100011000 )
0$
#2810000
b100 #
b100 +
b100011001 )
1$
#2820000
b100011010 )
0$
#2830000
b11 #
b11 +
b100011011 )
1$
#2840000
b100011100 )
0$
#2850000
b10 #
b10 +
b100011101 )
1$
#2860000
b100011110 )
0$
#2870000
b1 #
b1 +
b100011111 )
1$
#2880000
b100100000 )
0$
#2890000
b0 #
b0 +
b100100001 )
1$
#2900000
b100100010 )
0$
#2910000
1!
1"
b1001 #
b1001 +
b100100011 )
1$
#2920000
b100100100 )
0$
#2930000
0!
0"
b1000 #
b1000 +
b100100101 )
1$
#2940000
b100100110 )
0$
#2950000
b111 #
b111 +
b100100111 )
1$
#2960000
b100101000 )
0$
#2970000
b110 #
b110 +
b100101001 )
1$
#2980000
b100101010 )
0$
#2990000
b101 #
b101 +
b100101011 )
1$
#3000000
b100101100 )
0$
