src/timer/mod10.v
`timescale 1ns/1ps

//  TODO checar o *tc*

module mod10(
    input wire [3:0] data,
    input wire loadn, clrn, clk, en,
    output reg [3:0] out,
    output wire tc, output reg zero
);

    assign tc = (en & ~out[0] & ~out[1] & ~out[2] & ~out[3]);

    always @ (posedge clk or negedge clrn) begin
        
        if(~clrn) begin
            out <= 0;
          
            zero <= 0;
        end
        else if(~loadn) begin
            out <= data;
            zero <= (data == 0)? 1 : 0;
        end
        else begin
            if(en) begin
                if(out == 1) begin
                    out <= out -1;
                    zero <= 1;   
                end
                else if(out == 0) begin
                    out <= 9;
                    zero <= 0;
                end
                else begin
                    out <= out -1;
                    zero <= 0;    
                end
            end 
        end
    end


endmodule

src/timer/mod6.v
`timescale 1ns/1ps

//  TODO checar o *tc*

module mod6(
    input wire [3:0] data,
    input wire loadn, clrn, clk, en,
    output reg [3:0] out,
    output wire tc, 
    output reg zero
);

    assign tc = (en & ~out[0] & ~out[1] & ~out[2] & ~out[3]);
    
    always @ (posedge clk or negedge clrn) begin
        
        if(~clrn) begin
            out <= 0;
            zero <= 0;
        end
        else if(~loadn) begin
            out <= data;
            zero <= (data == 0)? 1: 0;
        end
        else begin
            if(en) begin
                if(out == 1) begin
                    out <= out -1;
                    zero <= 1;
                end
                else if(out == 0) begin
                    out <= 5;
                    zero <= 0;
                end
                else begin
                    out <= out -1;
                    zero <= 0; 
                end
            end
        end
    end


endmodule

src/timer/timer.v
module timer(
    input wire [3:0] data,
    input wire loadn, clrn, clk, en,
    output wire [3:0] sec_ones, 
    output wire [3:0] sec_tens, 
    output wire [3:0] mins,
    output wire zero 
);
    wire tc_ones, tc_tens, tc_mins, zero_ones, zero_tens, zero_mins;

    mod10 sec_ones_module ( .data(data), .loadn(loadn), .clrn(clrn), .clk(clk), .en(en), .out(sec_ones), .tc(tc_ones), .zero(zero_ones) );

    mod6 sec_tens_module ( .data(sec_ones), .loadn(loadn), .clrn(clrn), .clk(clk), .en(tc_ones), .out(sec_tens), .tc(tc_tens), .zero(zero_tens) );
    
    mod10 mins_module ( .data(sec_tens), .loadn(loadn), .clrn(clrn), .clk(clk), .en(tc_mins), .out(mins), .tc(tc_mins), .zero(zero_mins) );

    assign zero = zero_mins & zero_ones & zero_tens;

endmodule

testbenches/tb_timer.v
`timescale 1ns / 1ps


module tb_timer;
    // Inputs
  reg clk ;
  reg clrn;
  reg loadn;
  reg en;
  reg [3:0] data;
  // Output
  wire[3:0] sec_ones, sec_tens, mins;
  wire tc;
  wire zero;
  integer ticks = 0;
  // Instantiate the Timer
   timer t(
      .clk(clk), 
      .clrn(clrn),
      .loadn(loadn),
      .en(en),
      .data(data),
      .sec_ones(sec_ones),
      .sec_tens(sec_tens),
      .mins(mins),
      .zero(zero)
  );
 
 	initial begin
 	     clrn = 0;
 	     #2 clrn = 1;
 	end
	
	initial clk = 1;

	always begin
		#5 clk = ~clk; ticks++;
		if(loadn & zero) $finish;
	end

  	initial begin
  	  	$dumpfile("vcd/timer.vcd");
  	  	$dumpvars;
		loadn=0;
  	  	#10 data = 9;
  	  	#10 data = 8;
  	  	#10 loadn = 1; en = 1;
  	end

  //always @(zero) begin
  //  if(zero==1 & loadn==1) $finish;
  //end


  initial
    #1 $monitor(sec_ones, sec_tens, mins);

 
endmodule

vcd/timer.vcd
$date
	Thu Apr 29 11:48:17 2021
$end
$version
	Icarus Verilog
$end
$timescale
	1ps
$end
$scope module tb_timer $end
$var wire 1 ! zero $end
$var wire 4 " sec_tens [3:0] $end
$var wire 4 # sec_ones [3:0] $end
$var wire 4 $ mins [3:0] $end
$var reg 1 % clk $end
$var reg 1 & clrn $end
$var reg 4 ' data [3:0] $end
$var reg 1 ( en $end
$var reg 1 ) loadn $end
$var integer 32 * ticks [31:0] $end
$scope module t $end
$var wire 1 % clk $end
$var wire 1 & clrn $end
$var wire 4 + data [3:0] $end
$var wire 1 ( en $end
$var wire 1 ) loadn $end
$var wire 1 ! zero $end
$var wire 1 , zero_tens $end
$var wire 1 - zero_ones $end
$var wire 1 . zero_mins $end
$var wire 1 / tc_tens $end
$var wire 1 0 tc_ones $end
$var wire 1 1 tc_mins $end
$var wire 4 2 sec_tens [3:0] $end
$var wire 4 3 sec_ones [3:0] $end
$var wire 4 4 mins [3:0] $end
$scope module mins_module $end
$var wire 1 % clk $end
$var wire 1 & clrn $end
$var wire 1 ) loadn $end
$var wire 1 1 tc $end
$var wire 1 / en $end
$var wire 4 5 data [3:0] $end
$var reg 4 6 out [3:0] $end
$var reg 1 . zero $end
$upscope $end
$scope module sec_ones_module $end
$var wire 1 % clk $end
$var wire 1 & clrn $end
$var wire 4 7 data [3:0] $end
$var wire 1 ( en $end
$var wire 1 ) loadn $end
$var wire 1 0 tc $end
$var reg 4 8 out [3:0] $end
$var reg 1 - zero $end
$upscope $end
$scope module sec_tens_module $end
$var wire 1 % clk $end
$var wire 1 & clrn $end
$var wire 4 9 data [3:0] $end
$var wire 1 0 en $end
$var wire 1 ) loadn $end
$var wire 1 / tc $end
$var reg 4 : out [3:0] $end
$var reg 1 , zero $end
$upscope $end
$upscope $end
$upscope $end
$enddefinitions $end
#0
$dumpvars
b0 :
b0 9
b0 8
bx 7
b0 6
b0 5
b0 4
b0 3
b0 2
x1
x0
x/
0.
0-
0,
bx +
b0 *
0)
x(
bx '
0&
1%
b0 $
b0 #
b0 "
0!
$end
#2000
1&
#5000
b1 *
0%
#10000
01
0/
00
1.
1,
b1001 #
b1001 3
b1001 8
b1001 9
b10 *
1%
b1001 '
b1001 +
b1001 7
#15000
b11 *
0%
#20000
b1000 #
b1000 3
b1000 8
b1000 9
0,
b1001 "
b1001 2
b1001 5
b1001 :
b100 *
1%
b1000 '
b1000 +
b1000 7
#25000
b101 *
0%
#30000
00
b111 #
b111 3
b111 8
b111 9
b110 *
1%
1(
1)
#35000
b111 *
0%
#40000
b110 #
b110 3
b110 8
b110 9
b1000 *
1%
#45000
b1001 *
0%
#50000
b101 #
b101 3
b101 8
b101 9
b1010 *
1%
#55000
b1011 *
0%
#60000
b100 #
b100 3
b100 8
b100 9
b1100 *
1%
#65000
b1101 *
0%
#70000
00
b11 #
b11 3
b11 8
b11 9
b1110 *
1%
#75000
b1111 *
0%
#80000
b10 #
b10 3
b10 8
b10 9
b10000 *
1%
#85000
b10001 *
0%
#90000
00
b1 #
b1 3
b1 8
b1 9
b10010 *
1%
#95000
b10011 *
0%
#100000
10
1-
b0 #
b0 3
b0 8
b0 9
b10100 *
1%
#105000
b10101 *
0%
#110000
00
b1000 "
b1000 2
b1000 5
b1000 :
0-
b1001 #
b1001 3
b1001 8
b1001 9
b10110 *
1%
#115000
b10111 *
0%
#120000
b1000 #
b1000 3
b1000 8
b1000 9
b11000 *
1%
#125000
b11001 *
0%
#130000
00
b111 #
b111 3
b111 8
b111 9
b11010 *
1%
#135000
b11011 *
0%
#140000
b110 #
b110 3
b110 8
b110 9
b11100 *
1%
#145000
b11101 *
0%
#150000
b101 #
b101 3
b101 8
b101 9
b11110 *
1%
#155000
b11111 *
0%
#160000
b100 #
b100 3
b100 8
b100 9
b100000 *
1%
#165000
b100001 *
0%
#170000
00
b11 #
b11 3
b11 8
b11 9
b100010 *
1%
#175000
b100011 *
0%
#180000
b10 #
b10 3
b10 8
b10 9
b100100 *
1%
#185000
b100101 *
0%
#190000
00
b1 #
b1 3
b1 8
b1 9
b100110 *
1%
#195000
b100111 *
0%
#200000
10
1-
b0 #
b0 3
b0 8
b0 9
b101000 *
1%
#205000
b101001 *
0%
#210000
01
0/
00
b111 "
b111 2
b111 5
b111 :
0-
b1001 #
b1001 3
b1001 8
b1001 9
b101010 *
1%
#215000
b101011 *
0%
#220000
b1000 #
b1000 3
b1000 8
b1000 9
b101100 *
1%
#225000
b101101 *
0%
#230000
00
b111 #
b111 3
b111 8
b111 9
b101110 *
1%
#235000
b101111 *
0%
#240000
b110 #
b110 3
b110 8
b110 9
b110000 *
1%
#245000
b110001 *
0%
#250000
b101 #
b101 3
b101 8
b101 9
b110010 *
1%
#255000
b110011 *
0%
#260000
b100 #
b100 3
b100 8
b100 9
b110100 *
1%
#265000
b110101 *
0%
#270000
00
b11 #
b11 3
b11 8
b11 9
b110110 *
1%
#275000
b110111 *
0%
#280000
b10 #
b10 3
b10 8
b10 9
b111000 *
1%
#285000
b111001 *
0%
#290000
00
b1 #
b1 3
b1 8
b1 9
b111010 *
1%
#295000
b111011 *
0%
#300000
10
1-
b0 #
b0 3
b0 8
b0 9
b111100 *
1%
#305000
b111101 *
0%
#310000
00
b110 "
b110 2
b110 5
b110 :
0-
b1001 #
b1001 3
b1001 8
b1001 9
b111110 *
1%
#315000
b111111 *
0%
#320000
b1000 #
b1000 3
b1000 8
b1000 9
b1000000 *
1%
#325000
b1000001 *
0%
#330000
00
b111 #
b111 3
b111 8
b111 9
b1000010 *
1%
#335000
b1000011 *
0%
#340000
b110 #
b110 3
b110 8
b110 9
b1000100 *
1%
#345000
b1000101 *
0%
#350000
b101 #
b101 3
b101 8
b101 9
b1000110 *
1%
#355000
b1000111 *
0%
#360000
b100 #
b100 3
b100 8
b100 9
b1001000 *
1%
#365000
b1001001 *
0%
#370000
00
b11 #
b11 3
b11 8
b11 9
b1001010 *
1%
#375000
b1001011 *
0%
#380000
b10 #
b10 3
b10 8
b10 9
b1001100 *
1%
#385000
b1001101 *
0%
#390000
00
b1 #
b1 3
b1 8
b1 9
b1001110 *
1%
#395000
b1001111 *
0%
#400000
10
1-
b0 #
b0 3
b0 8
b0 9
b1010000 *
1%
#405000
b1010001 *
0%
#410000
00
b101 "
b101 2
b101 5
b101 :
0-
b1001 #
b1001 3
b1001 8
b1001 9
b1010010 *
1%
#415000
b1010011 *
0%
#420000
b1000 #
b1000 3
b1000 8
b1000 9
b1010100 *
1%
#425000
b1010101 *
0%
#430000
00
b111 #
b111 3
b111 8
b111 9
b1010110 *
1%
#435000
b1010111 *
0%
#440000
b110 #
b110 3
b110 8
b110 9
b1011000 *
1%
#445000
b1011001 *
0%
#450000
b101 #
b101 3
b101 8
b101 9
b1011010 *
1%
#455000
b1011011 *
0%
#460000
b100 #
b100 3
b100 8
b100 9
b1011100 *
1%
#465000
b1011101 *
0%
#470000
00
b11 #
b11 3
b11 8
b11 9
b1011110 *
1%
#475000
b1011111 *
0%
#480000
b10 #
b10 3
b10 8
b10 9
b1100000 *
1%
#485000
b1100001 *
0%
#490000
00
b1 #
b1 3
b1 8
b1 9
b1100010 *
1%
#495000
b1100011 *
0%
#500000
10
1-
b0 #
b0 3
b0 8
b0 9
b1100100 *
1%
#505000
b1100101 *
0%
#510000
00
b100 "
b100 2
b100 5
b100 :
0-
b1001 #
b1001 3
b1001 8
b1001 9
b1100110 *
1%
#515000
b1100111 *
0%
#520000
b1000 #
b1000 3
b1000 8
b1000 9
b1101000 *
1%
#525000
b1101001 *
0%
#530000
00
b111 #
b111 3
b111 8
b111 9
b1101010 *
1%
#535000
b1101011 *
0%
#540000
b110 #
b110 3
b110 8
b110 9
b1101100 *
1%
#545000
b1101101 *
0%
#550000
b101 #
b101 3
b101 8
b101 9
b1101110 *
1%
#555000
b1101111 *
0%
#560000
b100 #
b100 3
b100 8
b100 9
b1110000 *
1%
#565000
b1110001 *
0%
#570000
00
b11 #
b11 3
b11 8
b11 9
b1110010 *
1%
#575000
b1110011 *
0%
#580000
b10 #
b10 3
b10 8
b10 9
b1110100 *
1%
#585000
b1110101 *
0%
#590000
00
b1 #
b1 3
b1 8
b1 9
b1110110 *
1%
#595000
b1110111 *
0%
#600000
10
1-
b0 #
b0 3
b0 8
b0 9
b1111000 *
1%
#605000
b1111001 *
0%
#610000
01
0/
00
b11 "
b11 2
b11 5
b11 :
0-
b1001 #
b1001 3
b1001 8
b1001 9
b1111010 *
1%
#615000
b1111011 *
0%
#620000
b1000 #
b1000 3
b1000 8
b1000 9
b1111100 *
1%
#625000
b1111101 *
0%
#630000
00
b111 #
b111 3
b111 8
b111 9
b1111110 *
1%
#635000
b1111111 *
0%
#640000
b110 #
b110 3
b110 8
b110 9
b10000000 *
1%
#645000
b10000001 *
0%
#650000
b101 #
b101 3
b101 8
b101 9
b10000010 *
1%
#655000
b10000011 *
0%
#660000
b100 #
b100 3
b100 8
b100 9
b10000100 *
1%
#665000
b10000101 *
0%
#670000
00
b11 #
b11 3
b11 8
b11 9
b10000110 *
1%
#675000
b10000111 *
0%
#680000
b10 #
b10 3
b10 8
b10 9
b10001000 *
1%
#685000
b10001001 *
0%
#690000
00
b1 #
b1 3
b1 8
b1 9
b10001010 *
1%
#695000
b10001011 *
0%
#700000
10
1-
b0 #
b0 3
b0 8
b0 9
b10001100 *
1%
#705000
b10001101 *
0%
#710000
00
b10 "
b10 2
b10 5
b10 :
0-
b1001 #
b1001 3
b1001 8
b1001 9
b10001110 *
1%
#715000
b10001111 *
0%
#720000
b1000 #
b1000 3
b1000 8
b1000 9
b10010000 *
1%
#725000
b10010001 *
0%
#730000
00
b111 #
b111 3
b111 8
b111 9
b10010010 *
1%
#735000
b10010011 *
0%
#740000
b110 #
b110 3
b110 8
b110 9
b10010100 *
1%
#745000
b10010101 *
0%
#750000
b101 #
b101 3
b101 8
b101 9
b10010110 *
1%
#755000
b10010111 *
0%
#760000
b100 #
b100 3
b100 8
b100 9
b10011000 *
1%
#765000
b10011001 *
0%
#770000
00
b11 #
b11 3
b11 8
b11 9
b10011010 *
1%
#775000
b10011011 *
0%
#780000
b10 #
b10 3
b10 8
b10 9
b10011100 *
1%
#785000
b10011101 *
0%
#790000
00
b1 #
b1 3
b1 8
b1 9
b10011110 *
1%
#795000
b10011111 *
0%
#800000
10
1-
b0 #
b0 3
b0 8
b0 9
b10100000 *
1%
#805000
b10100001 *
0%
#810000
01
0/
00
b1 "
b1 2
b1 5
b1 :
0-
b1001 #
b1001 3
b1001 8
b1001 9
b10100010 *
1%
#815000
b10100011 *
0%
#820000
b1000 #
b1000 3
b1000 8
b1000 9
b10100100 *
1%
#825000
b10100101 *
0%
#830000
00
b111 #
b111 3
b111 8
b111 9
b10100110 *
1%
#835000
b10100111 *
0%
#840000
b110 #
b110 3
b110 8
b110 9
b10101000 *
1%
#845000
b10101001 *
0%
#850000
b101 #
b101 3
b101 8
b101 9
b10101010 *
1%
#855000
b10101011 *
0%
#860000
b100 #
b100 3
b100 8
b100 9
b10101100 *
1%
#865000
b10101101 *
0%
#870000
00
b11 #
b11 3
b11 8
b11 9
b10101110 *
1%
#875000
b10101111 *
0%
#880000
b10 #
b10 3
b10 8
b10 9
b10110000 *
1%
#885000
b10110001 *
0%
#890000
00
b1 #
b1 3
b1 8
b1 9
b10110010 *
1%
#895000
b10110011 *
0%
#900000
10
1-
b0 #
b0 3
b0 8
b0 9
b10110100 *
1%
#905000
b10110101 *
0%
#910000
00
1,
b0 "
b0 2
b0 5
b0 :
0-
b1001 #
b1001 3
b1001 8
b1001 9
b10110110 *
1%
#915000
b10110111 *
0%
#920000
b1000 #
b1000 3
b1000 8
b1000 9
b10111000 *
1%
#925000
b10111001 *
0%
#930000
01
0/
00
b111 #
b111 3
b111 8
b111 9
b10111010 *
1%
#935000
b10111011 *
0%
#940000
b110 #
b110 3
b110 8
b110 9
b10111100 *
1%
#945000
b10111101 *
0%
#950000
b101 #
b101 3
b101 8
b101 9
b10111110 *
1%
#955000
b10111111 *
0%
#960000
b100 #
b100 3
b100 8
b100 9
b11000000 *
1%
#965000
b11000001 *
0%
#970000
01
0/
00
b11 #
b11 3
b11 8
b11 9
b11000010 *
1%
#975000
b11000011 *
0%
#980000
b10 #
b10 3
b10 8
b10 9
b11000100 *
1%
#985000
b11000101 *
0%
#990000
01
0/
00
b1 #
b1 3
b1 8
b1 9
b11000110 *
1%
#995000
b11000111 *
0%
#1000000
11
1/
10
1!
1-
b0 #
b0 3
b0 8
b0 9
b11001000 *
1%
#1005000
b11001001 *
0%
