src/timer/mod10.v
`timescale 1ns/1ps

//  TODO checar o *tc*

module mod10(
    input wire [3:0] data,
    input wire loadn, clrn, clk, en,
    output reg [3:0] out,
    output wire tc, output reg zero
);

    assign tc = (en & ~out[0] & ~out[1] & ~out[2] & ~out[3]);

    always @ (posedge clk or negedge clrn) begin
        
        if(~clrn) begin
            out <= 0;
            zero <= 0;
        end
        else if(~loadn) begin
            out <= data;
            zero <= (data == 0)? 1 : 0;
        end
        else begin
            if(en) begin
                if(out == 1) begin
                    out <= out -1;
                    zero <= 1;   
                end
                else if(out == 0) begin
                    out <= 9;
                    zero <= 0;
                end
                else begin
                    out <= out -1;
                    zero <= 0;    
                end
            end 
        end
    end


endmodule

src/timer/mod6.v
module mod6(output reg [3:0] out,
                     output reg tc, zero,
                     input wire [3:0] data,
                     input wire loadn, clrn, clk, en);

always @(posedge clk or negedge clrn) begin

  if(!clrn)
    out <= 0;
  else if(!loadn)
    out <= data;

  else begin
    if (en)
      begin
        if(out==1)
          begin
            out<=out-1;
            #20 tc<=1;
          end
        else if(out==0)
          begin
            tc<=0;
            zero<=1;
            out<=5;
          end
        else begin
          tc<=0;
          zero<=0;
          out<=out-1;        
        end
      end  
    else
      begin
        tc<=0;
      end    
  end
end
endmodule

src/timer/timer.v
module timer(
    input wire [3:0] data,
    input wire loadn, clrn, clk, en,
    output wire [3:0] sec_ones, 
    output wire [3:0] sec_tens, 
    output wire [3:0] mins,
    output wire zero 
);
    wire tc_ones, tc_tens, tc_mins, zero_ones, zero_tens, zero_mins;

    mod10 sec_ones_module ( .data(data), .loadn(loadn), .clrn(clrn), .clk(clk), .en(en), .out(sec_ones), .tc(tc_ones), .zero(zero_ones) );

    mod6 sec_tens_module ( .data(sec_ones), .loadn(loadn), .clrn(clrn), .clk(clk), .en(tc_ones), .out(sec_tens), .tc(tc_tens), .zero(zero_tens) );
    
    mod10 mins_module ( .data(sec_tens), .loadn(loadn), .clrn(clrn), .clk(clk), .en(tc_mins), .out(mins), .tc(tc_mins), .zero(zero_mins) );

    assign zero = zero_mins & zero_ones & zero_tens;

endmodule

testbenches/tb_timer.v
`timescale 1ns / 1ps


module tb_timer;
    // Inputs
  reg clk ;
  reg clrn;
  reg loadn;
  reg en;
  reg [3:0] data;
  // Output
  wire[3:0] sec_ones, sec_tens, mins;
  wire tc;
  wire zero;
  integer ticks = 0;
  // Instantiate the Timer
   timer t(
      .clk(clk), 
      .clrn(clrn),
      .loadn(loadn),
      .en(en),
      .data(data),
      .sec_ones(sec_ones),
      .sec_tens(sec_tens),
      .mins(mins),
      .zero(zero)
  );
 
 	initial begin
 	     clrn = 0;
 	     #2 clrn = 1;
 	end
	
	initial clk = 1;

	always begin
		#5 clk = ~clk; ticks++;
		if(loadn & zero) $finish;
	end

  	initial begin
  	  	$dumpfile("vcd/timer.vcd");
  	  	$dumpvars;
		loadn=0;
  	  	#10 data = 3;
  	  	#10 data = 5;
		#10 data = 9;
  	  	#10 loadn =1; en = 1;
  	end

  //always @(zero) begin
  //  if(zero==1 & loadn==1) $finish;
  //end


  initial
    #1 $monitor(sec_ones, sec_tens, mins);

 
endmodule

vcd/timer.vcd
$date
	Thu Apr 29 11:52:54 2021
$end
$version
	Icarus Verilog
$end
$timescale
	1ps
$end
$scope module tb_timer $end
$var wire 1 ! zero $end
$var wire 4 " sec_tens [3:0] $end
$var wire 4 # sec_ones [3:0] $end
$var wire 4 $ mins [3:0] $end
$var reg 1 % clk $end
$var reg 1 & clrn $end
$var reg 4 ' data [3:0] $end
$var reg 1 ( en $end
$var reg 1 ) loadn $end
$var integer 32 * ticks [31:0] $end
$scope module t $end
$var wire 1 % clk $end
$var wire 1 & clrn $end
$var wire 4 + data [3:0] $end
$var wire 1 ( en $end
$var wire 1 ) loadn $end
$var wire 1 ! zero $end
$var wire 1 , zero_tens $end
$var wire 1 - zero_ones $end
$var wire 1 . zero_mins $end
$var wire 1 / tc_tens $end
$var wire 1 0 tc_ones $end
$var wire 1 1 tc_mins $end
$var wire 4 2 sec_tens [3:0] $end
$var wire 4 3 sec_ones [3:0] $end
$var wire 4 4 mins [3:0] $end
$scope module mins_module $end
$var wire 1 % clk $end
$var wire 1 & clrn $end
$var wire 1 ) loadn $end
$var wire 1 1 tc $end
$var wire 1 / en $end
$var wire 4 5 data [3:0] $end
$var reg 4 6 out [3:0] $end
$var reg 1 . zero $end
$upscope $end
$scope module sec_ones_module $end
$var wire 1 % clk $end
$var wire 1 & clrn $end
$var wire 4 7 data [3:0] $end
$var wire 1 ( en $end
$var wire 1 ) loadn $end
$var wire 1 0 tc $end
$var reg 4 8 out [3:0] $end
$var reg 1 - zero $end
$upscope $end
$scope module sec_tens_module $end
$var wire 1 % clk $end
$var wire 1 & clrn $end
$var wire 4 9 data [3:0] $end
$var wire 1 0 en $end
$var wire 1 ) loadn $end
$var wire 1 / tc $end
$var reg 4 : out [3:0] $end
$var reg 1 , zero $end
$upscope $end
$upscope $end
$upscope $end
$enddefinitions $end
#0
$dumpvars
b0 :
b0 9
b0 8
bx 7
b0 6
b0 5
b0 4
b0 3
b0 2
x1
x0
x/
0.
0-
0,
bx +
b0 *
0)
x(
bx '
0&
1%
b0 $
b0 #
b0 "
0!
$end
#2000
1&
#5000
b1 *
0%
#10000
01
0/
00
1.
1,
b11 #
b11 3
b11 8
b11 9
b10 *
1%
b11 '
b11 +
b11 7
#15000
b11 *
0%
#20000
b101 #
b101 3
b101 8
b101 9
0,
b11 "
b11 2
b11 5
b11 :
b100 *
1%
b101 '
b101 +
b101 7
#25000
b101 *
0%
#30000
0.
b11 $
b11 4
b11 6
b101 "
b101 2
b101 5
b101 :
b1001 #
b1001 3
b1001 8
b1001 9
b110 *
1%
b1001 '
b1001 +
b1001 7
#35000
b111 *
0%
#40000
b1000 #
b1000 3
b1000 8
b1000 9
b1000 *
1%
1(
1)
#45000
b1001 *
0%
#50000
00
b111 #
b111 3
b111 8
b111 9
b1010 *
1%
#55000
b1011 *
0%
#60000
b110 #
b110 3
b110 8
b110 9
b1100 *
1%
#65000
b1101 *
0%
#70000
b101 #
b101 3
b101 8
b101 9
b1110 *
1%
#75000
b1111 *
0%
#80000
b100 #
b100 3
b100 8
b100 9
b10000 *
1%
#85000
b10001 *
0%
#90000
00
b11 #
b11 3
b11 8
b11 9
b10010 *
1%
#95000
b10011 *
0%
#100000
b10 #
b10 3
b10 8
b10 9
b10100 *
1%
#105000
b10101 *
0%
#110000
00
b1 #
b1 3
b1 8
b1 9
b10110 *
1%
#115000
b10111 *
0%
#120000
10
1-
b0 #
b0 3
b0 8
b0 9
b11000 *
1%
#125000
b11001 *
0%
#130000
00
b100 "
b100 2
b100 5
b100 :
0-
b1001 #
b1001 3
b1001 8
b1001 9
b11010 *
1%
#135000
b11011 *
0%
#140000
b1000 #
b1000 3
b1000 8
b1000 9
b11100 *
1%
#145000
b11101 *
0%
#150000
00
b111 #
b111 3
b111 8
b111 9
b11110 *
1%
#155000
b11111 *
0%
#160000
b110 #
b110 3
b110 8
b110 9
b100000 *
1%
#165000
b100001 *
0%
#170000
b101 #
b101 3
b101 8
b101 9
b100010 *
1%
#175000
b100011 *
0%
#180000
b100 #
b100 3
b100 8
b100 9
b100100 *
1%
#185000
b100101 *
0%
#190000
00
b11 #
b11 3
b11 8
b11 9
b100110 *
1%
#195000
b100111 *
0%
#200000
b10 #
b10 3
b10 8
b10 9
b101000 *
1%
#205000
b101001 *
0%
#210000
00
b1 #
b1 3
b1 8
b1 9
b101010 *
1%
#215000
b101011 *
0%
#220000
10
1-
b0 #
b0 3
b0 8
b0 9
b101100 *
1%
#225000
b101101 *
0%
#230000
0/
00
b11 "
b11 2
b11 5
b11 :
0-
b1001 #
b1001 3
b1001 8
b1001 9
b101110 *
1%
#235000
b101111 *
0%
#240000
b1000 #
b1000 3
b1000 8
b1000 9
b110000 *
1%
#245000
b110001 *
0%
#250000
00
b111 #
b111 3
b111 8
b111 9
b110010 *
1%
#255000
b110011 *
0%
#260000
b110 #
b110 3
b110 8
b110 9
b110100 *
1%
#265000
b110101 *
0%
#270000
b101 #
b101 3
b101 8
b101 9
b110110 *
1%
#275000
b110111 *
0%
#280000
b100 #
b100 3
b100 8
b100 9
b111000 *
1%
#285000
b111001 *
0%
#290000
00
b11 #
b11 3
b11 8
b11 9
b111010 *
1%
#295000
b111011 *
0%
#300000
b10 #
b10 3
b10 8
b10 9
b111100 *
1%
#305000
b111101 *
0%
#310000
00
b1 #
b1 3
b1 8
b1 9
b111110 *
1%
#315000
b111111 *
0%
#320000
10
1-
b0 #
b0 3
b0 8
b0 9
b1000000 *
1%
#325000
b1000001 *
0%
#330000
00
b10 "
b10 2
b10 5
b10 :
0-
b1001 #
b1001 3
b1001 8
b1001 9
b1000010 *
1%
#335000
b1000011 *
0%
#340000
b1000 #
b1000 3
b1000 8
b1000 9
b1000100 *
1%
#345000
b1000101 *
0%
#350000
00
b111 #
b111 3
b111 8
b111 9
b1000110 *
1%
#355000
b1000111 *
0%
#360000
b110 #
b110 3
b110 8
b110 9
b1001000 *
1%
#365000
b1001001 *
0%
#370000
b101 #
b101 3
b101 8
b101 9
b1001010 *
1%
#375000
b1001011 *
0%
#380000
b100 #
b100 3
b100 8
b100 9
b1001100 *
1%
#385000
b1001101 *
0%
#390000
00
b11 #
b11 3
b11 8
b11 9
b1001110 *
1%
#395000
b1001111 *
0%
#400000
b10 #
b10 3
b10 8
b10 9
b1010000 *
1%
#405000
b1010001 *
0%
#410000
00
b1 #
b1 3
b1 8
b1 9
b1010010 *
1%
#415000
b1010011 *
0%
#420000
10
1-
b0 #
b0 3
b0 8
b0 9
b1010100 *
1%
#425000
b1010101 *
0%
#430000
0/
00
b1 "
b1 2
b1 5
b1 :
0-
b1001 #
b1001 3
b1001 8
b1001 9
b1010110 *
1%
#435000
b1010111 *
0%
#440000
b1000 #
b1000 3
b1000 8
b1000 9
b1011000 *
1%
#445000
b1011001 *
0%
#450000
00
b111 #
b111 3
b111 8
b111 9
b1011010 *
1%
#455000
b1011011 *
0%
#460000
b110 #
b110 3
b110 8
b110 9
b1011100 *
1%
#465000
b1011101 *
0%
#470000
b101 #
b101 3
b101 8
b101 9
b1011110 *
1%
#475000
b1011111 *
0%
#480000
b100 #
b100 3
b100 8
b100 9
b1100000 *
1%
#485000
b1100001 *
0%
#490000
00
b11 #
b11 3
b11 8
b11 9
b1100010 *
1%
#495000
b1100011 *
0%
#500000
b10 #
b10 3
b10 8
b10 9
b1100100 *
1%
#505000
b1100101 *
0%
#510000
00
b1 #
b1 3
b1 8
b1 9
b1100110 *
1%
#515000
b1100111 *
0%
#520000
10
1-
b0 #
b0 3
b0 8
b0 9
b1101000 *
1%
#525000
b1101001 *
0%
#530000
00
1,
b0 "
b0 2
b0 5
b0 :
0-
b1001 #
b1001 3
b1001 8
b1001 9
b1101010 *
1%
#535000
b1101011 *
0%
#540000
b1000 #
b1000 3
b1000 8
b1000 9
b1101100 *
1%
#545000
b1101101 *
0%
#550000
0/
00
b111 #
b111 3
b111 8
b111 9
b1101110 *
1%
#555000
b1101111 *
0%
#560000
b110 #
b110 3
b110 8
b110 9
b1110000 *
1%
#565000
b1110001 *
0%
#570000
b101 #
b101 3
b101 8
b101 9
b1110010 *
1%
#575000
b1110011 *
0%
#580000
b100 #
b100 3
b100 8
b100 9
b1110100 *
1%
#585000
b1110101 *
0%
#590000
0/
00
b11 #
b11 3
b11 8
b11 9
b1110110 *
1%
#595000
b1110111 *
0%
#600000
b10 #
b10 3
b10 8
b10 9
b1111000 *
1%
#605000
b1111001 *
0%
#610000
0/
00
b1 #
b1 3
b1 8
b1 9
b1111010 *
1%
#615000
b1111011 *
0%
#620000
1/
10
1-
b0 #
b0 3
b0 8
b0 9
b1111100 *
1%
#625000
b1111101 *
0%
#630000
0/
00
b10 $
b10 4
b10 6
0,
b101 "
b101 2
b101 5
b101 :
0-
b1001 #
b1001 3
b1001 8
b1001 9
b1111110 *
1%
#635000
b1111111 *
0%
#640000
b1000 #
b1000 3
b1000 8
b1000 9
b10000000 *
1%
#645000
b10000001 *
0%
#650000
00
b111 #
b111 3
b111 8
b111 9
b10000010 *
1%
#655000
b10000011 *
0%
#660000
b110 #
b110 3
b110 8
b110 9
b10000100 *
1%
#665000
b10000101 *
0%
#670000
b101 #
b101 3
b101 8
b101 9
b10000110 *
1%
#675000
b10000111 *
0%
#680000
b100 #
b100 3
b100 8
b100 9
b10001000 *
1%
#685000
b10001001 *
0%
#690000
00
b11 #
b11 3
b11 8
b11 9
b10001010 *
1%
#695000
b10001011 *
0%
#700000
b10 #
b10 3
b10 8
b10 9
b10001100 *
1%
#705000
b10001101 *
0%
#710000
00
b1 #
b1 3
b1 8
b1 9
b10001110 *
1%
#715000
b10001111 *
0%
#720000
10
1-
b0 #
b0 3
b0 8
b0 9
b10010000 *
1%
#725000
b10010001 *
0%
#730000
00
b100 "
b100 2
b100 5
b100 :
0-
b1001 #
b1001 3
b1001 8
b1001 9
b10010010 *
1%
#735000
b10010011 *
0%
#740000
b1000 #
b1000 3
b1000 8
b1000 9
b10010100 *
1%
#745000
b10010101 *
0%
#750000
00
b111 #
b111 3
b111 8
b111 9
b10010110 *
1%
#755000
b10010111 *
0%
#760000
b110 #
b110 3
b110 8
b110 9
b10011000 *
1%
#765000
b10011001 *
0%
#770000
b101 #
b101 3
b101 8
b101 9
b10011010 *
1%
#775000
b10011011 *
0%
#780000
b100 #
b100 3
b100 8
b100 9
b10011100 *
1%
#785000
b10011101 *
0%
#790000
00
b11 #
b11 3
b11 8
b11 9
b10011110 *
1%
#795000
b10011111 *
0%
#800000
b10 #
b10 3
b10 8
b10 9
b10100000 *
1%
#805000
b10100001 *
0%
#810000
00
b1 #
b1 3
b1 8
b1 9
b10100010 *
1%
#815000
b10100011 *
0%
#820000
10
1-
b0 #
b0 3
b0 8
b0 9
b10100100 *
1%
#825000
b10100101 *
0%
#830000
0/
00
b11 "
b11 2
b11 5
b11 :
0-
b1001 #
b1001 3
b1001 8
b1001 9
b10100110 *
1%
#835000
b10100111 *
0%
#840000
b1000 #
b1000 3
b1000 8
b1000 9
b10101000 *
1%
#845000
b10101001 *
0%
#850000
00
b111 #
b111 3
b111 8
b111 9
b10101010 *
1%
#855000
b10101011 *
0%
#860000
b110 #
b110 3
b110 8
b110 9
b10101100 *
1%
#865000
b10101101 *
0%
#870000
b101 #
b101 3
b101 8
b101 9
b10101110 *
1%
#875000
b10101111 *
0%
#880000
b100 #
b100 3
b100 8
b100 9
b10110000 *
1%
#885000
b10110001 *
0%
#890000
00
b11 #
b11 3
b11 8
b11 9
b10110010 *
1%
#895000
b10110011 *
0%
#900000
b10 #
b10 3
b10 8
b10 9
b10110100 *
1%
#905000
b10110101 *
0%
#910000
00
b1 #
b1 3
b1 8
b1 9
b10110110 *
1%
#915000
b10110111 *
0%
#920000
10
1-
b0 #
b0 3
b0 8
b0 9
b10111000 *
1%
#925000
b10111001 *
0%
#930000
00
b10 "
b10 2
b10 5
b10 :
0-
b1001 #
b1001 3
b1001 8
b1001 9
b10111010 *
1%
#935000
b10111011 *
0%
#940000
b1000 #
b1000 3
b1000 8
b1000 9
b10111100 *
1%
#945000
b10111101 *
0%
#950000
00
b111 #
b111 3
b111 8
b111 9
b10111110 *
1%
#955000
b10111111 *
0%
#960000
b110 #
b110 3
b110 8
b110 9
b11000000 *
1%
#965000
b11000001 *
0%
#970000
b101 #
b101 3
b101 8
b101 9
b11000010 *
1%
#975000
b11000011 *
0%
#980000
b100 #
b100 3
b100 8
b100 9
b11000100 *
1%
#985000
b11000101 *
0%
#990000
00
b11 #
b11 3
b11 8
b11 9
b11000110 *
1%
#995000
b11000111 *
0%
#1000000
b10 #
b10 3
b10 8
b10 9
b11001000 *
1%
#1005000
b11001001 *
0%
#1010000
00
b1 #
b1 3
b1 8
b1 9
b11001010 *
1%
#1015000
b11001011 *
0%
#1020000
10
1-
b0 #
b0 3
b0 8
b0 9
b11001100 *
1%
#1025000
b11001101 *
0%
#1030000
0/
00
b1 "
b1 2
b1 5
b1 :
0-
b1001 #
b1001 3
b1001 8
b1001 9
b11001110 *
1%
#1035000
b11001111 *
0%
#1040000
b1000 #
b1000 3
b1000 8
b1000 9
b11010000 *
1%
#1045000
b11010001 *
0%
#1050000
00
b111 #
b111 3
b111 8
b111 9
b11010010 *
1%
#1055000
b11010011 *
0%
#1060000
b110 #
b110 3
b110 8
b110 9
b11010100 *
1%
#1065000
b11010101 *
0%
#1070000
b101 #
b101 3
b101 8
b101 9
b11010110 *
1%
#1075000
b11010111 *
0%
#1080000
b100 #
b100 3
b100 8
b100 9
b11011000 *
1%
#1085000
b11011001 *
0%
#1090000
00
b11 #
b11 3
b11 8
b11 9
b11011010 *
1%
#1095000
b11011011 *
0%
#1100000
b10 #
b10 3
b10 8
b10 9
b11011100 *
1%
#1105000
b11011101 *
0%
#1110000
00
b1 #
b1 3
b1 8
b1 9
b11011110 *
1%
#1115000
b11011111 *
0%
#1120000
10
1-
b0 #
b0 3
b0 8
b0 9
b11100000 *
1%
#1125000
b11100001 *
0%
#1130000
00
1,
b0 "
b0 2
b0 5
b0 :
0-
b1001 #
b1001 3
b1001 8
b1001 9
b11100010 *
1%
#1135000
b11100011 *
0%
#1140000
b1000 #
b1000 3
b1000 8
b1000 9
b11100100 *
1%
#1145000
b11100101 *
0%
#1150000
0/
00
b111 #
b111 3
b111 8
b111 9
b11100110 *
1%
#1155000
b11100111 *
0%
#1160000
b110 #
b110 3
b110 8
b110 9
b11101000 *
1%
#1165000
b11101001 *
0%
#1170000
b101 #
b101 3
b101 8
b101 9
b11101010 *
1%
#1175000
b11101011 *
0%
#1180000
b100 #
b100 3
b100 8
b100 9
b11101100 *
1%
#1185000
b11101101 *
0%
#1190000
0/
00
b11 #
b11 3
b11 8
b11 9
b11101110 *
1%
#1195000
b11101111 *
0%
#1200000
b10 #
b10 3
b10 8
b10 9
b11110000 *
1%
#1205000
b11110001 *
0%
#1210000
0/
00
b1 #
b1 3
b1 8
b1 9
b11110010 *
1%
#1215000
b11110011 *
0%
#1220000
1/
10
1-
b0 #
b0 3
b0 8
b0 9
b11110100 *
1%
#1225000
b11110101 *
0%
#1230000
01
0/
00
b1 $
b1 4
b1 6
0,
b101 "
b101 2
b101 5
b101 :
0-
b1001 #
b1001 3
b1001 8
b1001 9
b11110110 *
1%
#1235000
b11110111 *
0%
#1240000
b1000 #
b1000 3
b1000 8
b1000 9
b11111000 *
1%
#1245000
b11111001 *
0%
#1250000
00
b111 #
b111 3
b111 8
b111 9
b11111010 *
1%
#1255000
b11111011 *
0%
#1260000
b110 #
b110 3
b110 8
b110 9
b11111100 *
1%
#1265000
b11111101 *
0%
#1270000
b101 #
b101 3
b101 8
b101 9
b11111110 *
1%
#1275000
b11111111 *
0%
#1280000
b100 #
b100 3
b100 8
b100 9
b100000000 *
1%
#1285000
b100000001 *
0%
#1290000
00
b11 #
b11 3
b11 8
b11 9
b100000010 *
1%
#1295000
b100000011 *
0%
#1300000
b10 #
b10 3
b10 8
b10 9
b100000100 *
1%
#1305000
b100000101 *
0%
#1310000
00
b1 #
b1 3
b1 8
b1 9
b100000110 *
1%
#1315000
b100000111 *
0%
#1320000
10
1-
b0 #
b0 3
b0 8
b0 9
b100001000 *
1%
#1325000
b100001001 *
0%
#1330000
00
b100 "
b100 2
b100 5
b100 :
0-
b1001 #
b1001 3
b1001 8
b1001 9
b100001010 *
1%
#1335000
b100001011 *
0%
#1340000
b1000 #
b1000 3
b1000 8
b1000 9
b100001100 *
1%
#1345000
b100001101 *
0%
#1350000
00
b111 #
b111 3
b111 8
b111 9
b100001110 *
1%
#1355000
b100001111 *
0%
#1360000
b110 #
b110 3
b110 8
b110 9
b100010000 *
1%
#1365000
b100010001 *
0%
#1370000
b101 #
b101 3
b101 8
b101 9
b100010010 *
1%
#1375000
b100010011 *
0%
#1380000
b100 #
b100 3
b100 8
b100 9
b100010100 *
1%
#1385000
b100010101 *
0%
#1390000
00
b11 #
b11 3
b11 8
b11 9
b100010110 *
1%
#1395000
b100010111 *
0%
#1400000
b10 #
b10 3
b10 8
b10 9
b100011000 *
1%
#1405000
b100011001 *
0%
#1410000
00
b1 #
b1 3
b1 8
b1 9
b100011010 *
1%
#1415000
b100011011 *
0%
#1420000
10
1-
b0 #
b0 3
b0 8
b0 9
b100011100 *
1%
#1425000
b100011101 *
0%
#1430000
0/
00
b11 "
b11 2
b11 5
b11 :
0-
b1001 #
b1001 3
b1001 8
b1001 9
b100011110 *
1%
#1435000
b100011111 *
0%
#1440000
b1000 #
b1000 3
b1000 8
b1000 9
b100100000 *
1%
#1445000
b100100001 *
0%
#1450000
00
b111 #
b111 3
b111 8
b111 9
b100100010 *
1%
#1455000
b100100011 *
0%
#1460000
b110 #
b110 3
b110 8
b110 9
b100100100 *
1%
#1465000
b100100101 *
0%
#1470000
b101 #
b101 3
b101 8
b101 9
b100100110 *
1%
#1475000
b100100111 *
0%
#1480000
b100 #
b100 3
b100 8
b100 9
b100101000 *
1%
#1485000
b100101001 *
0%
#1490000
00
b11 #
b11 3
b11 8
b11 9
b100101010 *
1%
#1495000
b100101011 *
0%
#1500000
b10 #
b10 3
b10 8
b10 9
b100101100 *
1%
#1505000
b100101101 *
0%
#1510000
00
b1 #
b1 3
b1 8
b1 9
b100101110 *
1%
#1515000
b100101111 *
0%
#1520000
10
1-
b0 #
b0 3
b0 8
b0 9
b100110000 *
1%
#1525000
b100110001 *
0%
#1530000
00
b10 "
b10 2
b10 5
b10 :
0-
b1001 #
b1001 3
b1001 8
b1001 9
b100110010 *
1%
#1535000
b100110011 *
0%
#1540000
b1000 #
b1000 3
b1000 8
b1000 9
b100110100 *
1%
#1545000
b100110101 *
0%
#1550000
00
b111 #
b111 3
b111 8
b111 9
b100110110 *
1%
#1555000
b100110111 *
0%
#1560000
b110 #
b110 3
b110 8
b110 9
b100111000 *
1%
#1565000
b100111001 *
0%
#1570000
b101 #
b101 3
b101 8
b101 9
b100111010 *
1%
#1575000
b100111011 *
0%
#1580000
b100 #
b100 3
b100 8
b100 9
b100111100 *
1%
#1585000
b100111101 *
0%
#1590000
00
b11 #
b11 3
b11 8
b11 9
b100111110 *
1%
#1595000
b100111111 *
0%
#1600000
b10 #
b10 3
b10 8
b10 9
b101000000 *
1%
#1605000
b101000001 *
0%
#1610000
00
b1 #
b1 3
b1 8
b1 9
b101000010 *
1%
#1615000
b101000011 *
0%
#1620000
10
1-
b0 #
b0 3
b0 8
b0 9
b101000100 *
1%
#1625000
b101000101 *
0%
#1630000
0/
00
b1 "
b1 2
b1 5
b1 :
0-
b1001 #
b1001 3
b1001 8
b1001 9
b101000110 *
1%
#1635000
b101000111 *
0%
#1640000
b1000 #
b1000 3
b1000 8
b1000 9
b101001000 *
1%
#1645000
b101001001 *
0%
#1650000
00
b111 #
b111 3
b111 8
b111 9
b101001010 *
1%
#1655000
b101001011 *
0%
#1660000
b110 #
b110 3
b110 8
b110 9
b101001100 *
1%
#1665000
b101001101 *
0%
#1670000
b101 #
b101 3
b101 8
b101 9
b101001110 *
1%
#1675000
b101001111 *
0%
#1680000
b100 #
b100 3
b100 8
b100 9
b101010000 *
1%
#1685000
b101010001 *
0%
#1690000
00
b11 #
b11 3
b11 8
b11 9
b101010010 *
1%
#1695000
b101010011 *
0%
#1700000
b10 #
b10 3
b10 8
b10 9
b101010100 *
1%
#1705000
b101010101 *
0%
#1710000
00
b1 #
b1 3
b1 8
b1 9
b101010110 *
1%
#1715000
b101010111 *
0%
#1720000
10
1-
b0 #
b0 3
b0 8
b0 9
b101011000 *
1%
#1725000
b101011001 *
0%
#1730000
00
1,
b0 "
b0 2
b0 5
b0 :
0-
b1001 #
b1001 3
b1001 8
b1001 9
b101011010 *
1%
#1735000
b101011011 *
0%
#1740000
b1000 #
b1000 3
b1000 8
b1000 9
b101011100 *
1%
#1745000
b101011101 *
0%
#1750000
0/
00
b111 #
b111 3
b111 8
b111 9
b101011110 *
1%
#1755000
b101011111 *
0%
#1760000
b110 #
b110 3
b110 8
b110 9
b101100000 *
1%
#1765000
b101100001 *
0%
#1770000
b101 #
b101 3
b101 8
b101 9
b101100010 *
1%
#1775000
b101100011 *
0%
#1780000
b100 #
b100 3
b100 8
b100 9
b101100100 *
1%
#1785000
b101100101 *
0%
#1790000
0/
00
b11 #
b11 3
b11 8
b11 9
b101100110 *
1%
#1795000
b101100111 *
0%
#1800000
b10 #
b10 3
b10 8
b10 9
b101101000 *
1%
#1805000
b101101001 *
0%
#1810000
0/
00
b1 #
b1 3
b1 8
b1 9
b101101010 *
1%
#1815000
b101101011 *
0%
#1820000
1/
10
1-
b0 #
b0 3
b0 8
b0 9
b101101100 *
1%
#1825000
b101101101 *
0%
#1830000
01
0/
00
1.
b0 $
b0 4
b0 6
0,
b101 "
b101 2
b101 5
b101 :
0-
b1001 #
b1001 3
b1001 8
b1001 9
b101101110 *
1%
#1835000
b101101111 *
0%
#1840000
b1000 #
b1000 3
b1000 8
b1000 9
b101110000 *
1%
#1845000
b101110001 *
0%
#1850000
00
b111 #
b111 3
b111 8
b111 9
b101110010 *
1%
#1855000
b101110011 *
0%
#1860000
b110 #
b110 3
b110 8
b110 9
b101110100 *
1%
#1865000
b101110101 *
0%
#1870000
b101 #
b101 3
b101 8
b101 9
b101110110 *
1%
#1875000
b101110111 *
0%
#1880000
b100 #
b100 3
b100 8
b100 9
b101111000 *
1%
#1885000
b101111001 *
0%
#1890000
00
b11 #
b11 3
b11 8
b11 9
b101111010 *
1%
#1895000
b101111011 *
0%
#1900000
b10 #
b10 3
b10 8
b10 9
b101111100 *
1%
#1905000
b101111101 *
0%
#1910000
00
b1 #
b1 3
b1 8
b1 9
b101111110 *
1%
#1915000
b101111111 *
0%
#1920000
10
1-
b0 #
b0 3
b0 8
b0 9
b110000000 *
1%
#1925000
b110000001 *
0%
#1930000
00
b100 "
b100 2
b100 5
b100 :
0-
b1001 #
b1001 3
b1001 8
b1001 9
b110000010 *
1%
#1935000
b110000011 *
0%
#1940000
b1000 #
b1000 3
b1000 8
b1000 9
b110000100 *
1%
#1945000
b110000101 *
0%
#1950000
00
b111 #
b111 3
b111 8
b111 9
b110000110 *
1%
#1955000
b110000111 *
0%
#1960000
b110 #
b110 3
b110 8
b110 9
b110001000 *
1%
#1965000
b110001001 *
0%
#1970000
b101 #
b101 3
b101 8
b101 9
b110001010 *
1%
#1975000
b110001011 *
0%
#1980000
b100 #
b100 3
b100 8
b100 9
b110001100 *
1%
#1985000
b110001101 *
0%
#1990000
00
b11 #
b11 3
b11 8
b11 9
b110001110 *
1%
#1995000
b110001111 *
0%
#2000000
b10 #
b10 3
b10 8
b10 9
b110010000 *
1%
#2005000
b110010001 *
0%
#2010000
00
b1 #
b1 3
b1 8
b1 9
b110010010 *
1%
#2015000
b110010011 *
0%
#2020000
10
1-
b0 #
b0 3
b0 8
b0 9
b110010100 *
1%
#2025000
b110010101 *
0%
#2030000
01
0/
00
b11 "
b11 2
b11 5
b11 :
0-
b1001 #
b1001 3
b1001 8
b1001 9
b110010110 *
1%
#2035000
b110010111 *
0%
#2040000
b1000 #
b1000 3
b1000 8
b1000 9
b110011000 *
1%
#2045000
b110011001 *
0%
#2050000
00
b111 #
b111 3
b111 8
b111 9
b110011010 *
1%
#2055000
b110011011 *
0%
#2060000
b110 #
b110 3
b110 8
b110 9
b110011100 *
1%
#2065000
b110011101 *
0%
#2070000
b101 #
b101 3
b101 8
b101 9
b110011110 *
1%
#2075000
b110011111 *
0%
#2080000
b100 #
b100 3
b100 8
b100 9
b110100000 *
1%
#2085000
b110100001 *
0%
#2090000
00
b11 #
b11 3
b11 8
b11 9
b110100010 *
1%
#2095000
b110100011 *
0%
#2100000
b10 #
b10 3
b10 8
b10 9
b110100100 *
1%
#2105000
b110100101 *
0%
#2110000
00
b1 #
b1 3
b1 8
b1 9
b110100110 *
1%
#2115000
b110100111 *
0%
#2120000
10
1-
b0 #
b0 3
b0 8
b0 9
b110101000 *
1%
#2125000
b110101001 *
0%
#2130000
00
b10 "
b10 2
b10 5
b10 :
0-
b1001 #
b1001 3
b1001 8
b1001 9
b110101010 *
1%
#2135000
b110101011 *
0%
#2140000
b1000 #
b1000 3
b1000 8
b1000 9
b110101100 *
1%
#2145000
b110101101 *
0%
#2150000
00
b111 #
b111 3
b111 8
b111 9
b110101110 *
1%
#2155000
b110101111 *
0%
#2160000
b110 #
b110 3
b110 8
b110 9
b110110000 *
1%
#2165000
b110110001 *
0%
#2170000
b101 #
b101 3
b101 8
b101 9
b110110010 *
1%
#2175000
b110110011 *
0%
#2180000
b100 #
b100 3
b100 8
b100 9
b110110100 *
1%
#2185000
b110110101 *
0%
#2190000
00
b11 #
b11 3
b11 8
b11 9
b110110110 *
1%
#2195000
b110110111 *
0%
#2200000
b10 #
b10 3
b10 8
b10 9
b110111000 *
1%
#2205000
b110111001 *
0%
#2210000
00
b1 #
b1 3
b1 8
b1 9
b110111010 *
1%
#2215000
b110111011 *
0%
#2220000
10
1-
b0 #
b0 3
b0 8
b0 9
b110111100 *
1%
#2225000
b110111101 *
0%
#2230000
01
0/
00
b1 "
b1 2
b1 5
b1 :
0-
b1001 #
b1001 3
b1001 8
b1001 9
b110111110 *
1%
#2235000
b110111111 *
0%
#2240000
b1000 #
b1000 3
b1000 8
b1000 9
b111000000 *
1%
#2245000
b111000001 *
0%
#2250000
00
b111 #
b111 3
b111 8
b111 9
b111000010 *
1%
#2255000
b111000011 *
0%
#2260000
b110 #
b110 3
b110 8
b110 9
b111000100 *
1%
#2265000
b111000101 *
0%
#2270000
b101 #
b101 3
b101 8
b101 9
b111000110 *
1%
#2275000
b111000111 *
0%
