src/timer/mod10.v
`timescale 1ns/1ps

//  TODO checar o *tc*

module mod10(
    input wire [3:0] data,
    input wire loadn, clrn, clk, en,
    output reg [3:0] out,
    output reg tc, zero
);

    always @ (posedge clk or negedge clrn) begin
        
        if(!clrn) begin
            out = 0;
            tc = 0;
            zero = 0;
        end
        else if(!loadn) begin
            out <= data;
        end 
        else begin
            if(en) begin
               if(out == 0)  begin
                    out <= 9;
                    tc =  1;
                    zero <= 1;
                end
                else begin
                     out <= out-1;
                     tc <= 0;
                     zero <= 0;
                end 
            end
            else
                tc <= 0;
        end
    end


endmodule

src/timer/mod6.v
`timescale 1ns/1ps

//  TODO checar o *tc*

module mod6(
    input wire [3:0] data,
    input wire loadn, clrn, clk, en,
    output reg [3:0] out,
    output reg tc, zero
);

    always @ (posedge clk or negedge clrn) begin
        
        if(!clrn) begin
            out = 0;
            tc = 0;
            zero = 0;
        end
        else if(!loadn) begin
            out <= data;
        end 
        else begin
            if(en) begin
                if(out == 0)  begin
                    out <= 5;
                    tc =  1;
                    zero <= 1;
                end
                else begin
                    out <= out-1;
                    tc <= 0;
                    zero <= 0;
                end
             
            end
            else
                tc <= 0;
        end
    end
    


endmodule

src/timer/timer.v
module timer(
    input wire [3:0] data,
    input wire loadn, clrn, clk, en,
    output wire [3:0] sec_ones, 
    output wire [3:0] sec_tens, 
    output wire [3:0] mins,
    output wire zero 
);
    wire tc_ones, tc_tens, tc_mins, zero_ones, zero_tens, zero_mins;

    mod10 sec_ones_module ( .data(data), .loadn(loadn), .clrn(clrn), .clk(clk), .en(en), .out(sec_ones), .tc(tc_ones), .zero(zero_ones) );

    mod6 sec_tens_module ( .data(sec_ones), .loadn(loadn), .clrn(clrn), .clk(clk), .en(tc_ones), .out(sec_tens), .tc(tc_tens), .zero(zero_tens) );
    
    mod10 mins_module ( .data(sec_tens), .loadn(loadn), .clrn(clrn), .clk(clk), .en(tc_mins), .out(mins), .tc(tc_mins), .zero(zero_mins) );

    assign zero = zero_mins & zero_ones & zero_tens;

endmodule

testbenches/tb_timer.v
`timescale 1ns/1ps

module tb_timer;

    reg [3:0] data;
    reg loadn, clk, en, clrn;
    wire [3:0] sec_ones, sec_tens, mins;
    wire tc, zero;
    integer ticks=0;

    timer t(.data(data), .loadn(loadn), .clrn(clrn), .clk(clk), .en(en), .sec_ones(sec_ones), .sec_tens(sec_tens), .mins(mins), .zero(zero) );

    initial begin
        clrn = 0;
        #5 clrn = 1;
    end
    
    initial 
        clk = 1;
    
    always begin
        #10 clk = ~clk; ticks++;
        if(ticks == 200) 
            $finish;
    end  
    

    initial begin
        loadn = 0; en = 1;
        #20
        data = 4;
        #20;
        data = 3;
        #20
        data = 2;
        #10
        loadn = 1;
    end

    initial begin
        $dumpfile("vcd/timer.vcd");
        $dumpvars;
    end

    initial
    #1 $monitor("%d %d %d", mins, sec_tens, sec_ones);
    


endmodule

vcd/timer.vcd
$date
	Wed Apr 28 16:19:03 2021
$end
$version
	Icarus Verilog
$end
$timescale
	1ps
$end
$scope module tb_timer $end
$var wire 1 ! zero $end
$var wire 4 " sec_tens [3:0] $end
$var wire 4 # sec_ones [3:0] $end
$var wire 4 $ mins [3:0] $end
$var reg 1 % clk $end
$var reg 1 & clrn $end
$var reg 4 ' data [3:0] $end
$var reg 1 ( en $end
$var reg 1 ) loadn $end
$var integer 32 * ticks [31:0] $end
$scope module t $end
$var wire 1 % clk $end
$var wire 1 & clrn $end
$var wire 4 + data [3:0] $end
$var wire 1 ( en $end
$var wire 1 ) loadn $end
$var wire 1 ! zero $end
$var wire 1 , zero_tens $end
$var wire 1 - zero_ones $end
$var wire 1 . zero_mins $end
$var wire 1 / tc_tens $end
$var wire 1 0 tc_ones $end
$var wire 1 1 tc_mins $end
$var wire 4 2 sec_tens [3:0] $end
$var wire 4 3 sec_ones [3:0] $end
$var wire 4 4 mins [3:0] $end
$scope module mins_module $end
$var wire 1 % clk $end
$var wire 1 & clrn $end
$var wire 1 ) loadn $end
$var wire 1 / en $end
$var wire 4 5 data [3:0] $end
$var reg 4 6 out [3:0] $end
$var reg 1 1 tc $end
$var reg 1 . zero $end
$upscope $end
$scope module sec_ones_module $end
$var wire 1 % clk $end
$var wire 1 & clrn $end
$var wire 4 7 data [3:0] $end
$var wire 1 ( en $end
$var wire 1 ) loadn $end
$var reg 4 8 out [3:0] $end
$var reg 1 0 tc $end
$var reg 1 - zero $end
$upscope $end
$scope module sec_tens_module $end
$var wire 1 % clk $end
$var wire 1 & clrn $end
$var wire 4 9 data [3:0] $end
$var wire 1 0 en $end
$var wire 1 ) loadn $end
$var reg 4 : out [3:0] $end
$var reg 1 / tc $end
$var reg 1 , zero $end
$upscope $end
$upscope $end
$upscope $end
$enddefinitions $end
#0
$dumpvars
b0 :
b0 9
b0 8
bx 7
b0 6
b0 5
b0 4
b0 3
b0 2
01
00
0/
0.
0-
0,
bx +
b0 *
0)
1(
bx '
0&
1%
b0 $
b0 #
b0 "
0!
$end
#5000
1&
#10000
b1 *
0%
#20000
b100 #
b100 3
b100 8
b100 9
b10 *
1%
b100 '
b100 +
b100 7
#30000
b11 *
0%
#40000
b11 #
b11 3
b11 8
b11 9
b100 "
b100 2
b100 5
b100 :
b100 *
1%
b11 '
b11 +
b11 7
#50000
b101 *
0%
#60000
b100 $
b100 4
b100 6
b11 "
b11 2
b11 5
b11 :
b10 #
b10 3
b10 8
b10 9
b110 *
1%
b10 '
b10 +
b10 7
#70000
b111 *
0%
1)
#80000
b1 #
b1 3
b1 8
b1 9
b1000 *
1%
#90000
b1001 *
0%
#100000
b0 #
b0 3
b0 8
b0 9
b1010 *
1%
#110000
b1011 *
0%
#120000
1-
10
b1001 #
b1001 3
b1001 8
b1001 9
b1100 *
1%
#130000
b1101 *
0%
#140000
b10 "
b10 2
b10 5
b10 :
0-
00
b1000 #
b1000 3
b1000 8
b1000 9
b1110 *
1%
#150000
b1111 *
0%
#160000
b111 #
b111 3
b111 8
b111 9
b10000 *
1%
#170000
b10001 *
0%
#180000
b110 #
b110 3
b110 8
b110 9
b10010 *
1%
#190000
b10011 *
0%
#200000
b101 #
b101 3
b101 8
b101 9
b10100 *
1%
#210000
b10101 *
0%
#220000
b100 #
b100 3
b100 8
b100 9
b10110 *
1%
#230000
b10111 *
0%
#240000
b11 #
b11 3
b11 8
b11 9
b11000 *
1%
#250000
b11001 *
0%
#260000
b10 #
b10 3
b10 8
b10 9
b11010 *
1%
#270000
b11011 *
0%
#280000
b1 #
b1 3
b1 8
b1 9
b11100 *
1%
#290000
b11101 *
0%
#300000
b0 #
b0 3
b0 8
b0 9
b11110 *
1%
#310000
b11111 *
0%
#320000
1-
10
b1001 #
b1001 3
b1001 8
b1001 9
b100000 *
1%
#330000
b100001 *
0%
#340000
b1 "
b1 2
b1 5
b1 :
0-
00
b1000 #
b1000 3
b1000 8
b1000 9
b100010 *
1%
#350000
b100011 *
0%
#360000
b111 #
b111 3
b111 8
b111 9
b100100 *
1%
#370000
b100101 *
0%
#380000
b110 #
b110 3
b110 8
b110 9
b100110 *
1%
#390000
b100111 *
0%
#400000
b101 #
b101 3
b101 8
b101 9
b101000 *
1%
#410000
b101001 *
0%
#420000
b100 #
b100 3
b100 8
b100 9
b101010 *
1%
#430000
b101011 *
0%
#440000
b11 #
b11 3
b11 8
b11 9
b101100 *
1%
#450000
b101101 *
0%
#460000
b10 #
b10 3
b10 8
b10 9
b101110 *
1%
#470000
b101111 *
0%
#480000
b1 #
b1 3
b1 8
b1 9
b110000 *
1%
#490000
b110001 *
0%
#500000
b0 #
b0 3
b0 8
b0 9
b110010 *
1%
#510000
b110011 *
0%
#520000
1-
10
b1001 #
b1001 3
b1001 8
b1001 9
b110100 *
1%
#530000
b110101 *
0%
#540000
1/
b0 "
b0 2
b0 5
b0 :
0-
00
b1000 #
b1000 3
b1000 8
b1000 9
b110110 *
1%
#550000
b110111 *
0%
#560000
b111 #
b111 3
b111 8
b111 9
0/
b11 $
b11 4
b11 6
b111000 *
1%
#570000
b111001 *
0%
#580000
b110 #
b110 3
b110 8
b110 9
b111010 *
1%
#590000
b111011 *
0%
#600000
b101 #
b101 3
b101 8
b101 9
b111100 *
1%
#610000
b111101 *
0%
#620000
b100 #
b100 3
b100 8
b100 9
b111110 *
1%
#630000
b111111 *
0%
#640000
b11 #
b11 3
b11 8
b11 9
b1000000 *
1%
#650000
b1000001 *
0%
#660000
b10 #
b10 3
b10 8
b10 9
b1000010 *
1%
#670000
b1000011 *
0%
#680000
b1 #
b1 3
b1 8
b1 9
b1000100 *
1%
#690000
b1000101 *
0%
#700000
b0 #
b0 3
b0 8
b0 9
b1000110 *
1%
#710000
b1000111 *
0%
#720000
1-
10
b1001 #
b1001 3
b1001 8
b1001 9
b1001000 *
1%
#730000
b1001001 *
0%
#740000
1,
b101 "
b101 2
b101 5
b101 :
0-
00
b1000 #
b1000 3
b1000 8
b1000 9
b1001010 *
1%
#750000
b1001011 *
0%
#760000
b111 #
b111 3
b111 8
b111 9
b1001100 *
1%
#770000
b1001101 *
0%
#780000
b110 #
b110 3
b110 8
b110 9
b1001110 *
1%
#790000
b1001111 *
0%
#800000
b101 #
b101 3
b101 8
b101 9
b1010000 *
1%
#810000
b1010001 *
0%
#820000
b100 #
b100 3
b100 8
b100 9
b1010010 *
1%
#830000
b1010011 *
0%
#840000
b11 #
b11 3
b11 8
b11 9
b1010100 *
1%
#850000
b1010101 *
0%
#860000
b10 #
b10 3
b10 8
b10 9
b1010110 *
1%
#870000
b1010111 *
0%
#880000
b1 #
b1 3
b1 8
b1 9
b1011000 *
1%
#890000
b1011001 *
0%
#900000
b0 #
b0 3
b0 8
b0 9
b1011010 *
1%
#910000
b1011011 *
0%
#920000
1-
10
b1001 #
b1001 3
b1001 8
b1001 9
b1011100 *
1%
#930000
b1011101 *
0%
#940000
0,
b100 "
b100 2
b100 5
b100 :
0-
00
b1000 #
b1000 3
b1000 8
b1000 9
b1011110 *
1%
#950000
b1011111 *
0%
#960000
b111 #
b111 3
b111 8
b111 9
b1100000 *
1%
#970000
b1100001 *
0%
#980000
b110 #
b110 3
b110 8
b110 9
b1100010 *
1%
#990000
b1100011 *
0%
#1000000
b101 #
b101 3
b101 8
b101 9
b1100100 *
1%
#1010000
b1100101 *
0%
#1020000
b100 #
b100 3
b100 8
b100 9
b1100110 *
1%
#1030000
b1100111 *
0%
#1040000
b11 #
b11 3
b11 8
b11 9
b1101000 *
1%
#1050000
b1101001 *
0%
#1060000
b10 #
b10 3
b10 8
b10 9
b1101010 *
1%
#1070000
b1101011 *
0%
#1080000
b1 #
b1 3
b1 8
b1 9
b1101100 *
1%
#1090000
b1101101 *
0%
#1100000
b0 #
b0 3
b0 8
b0 9
b1101110 *
1%
#1110000
b1101111 *
0%
#1120000
1-
10
b1001 #
b1001 3
b1001 8
b1001 9
b1110000 *
1%
#1130000
b1110001 *
0%
#1140000
b11 "
b11 2
b11 5
b11 :
0-
00
b1000 #
b1000 3
b1000 8
b1000 9
b1110010 *
1%
#1150000
b1110011 *
0%
#1160000
b111 #
b111 3
b111 8
b111 9
b1110100 *
1%
#1170000
b1110101 *
0%
#1180000
b110 #
b110 3
b110 8
b110 9
b1110110 *
1%
#1190000
b1110111 *
0%
#1200000
b101 #
b101 3
b101 8
b101 9
b1111000 *
1%
#1210000
b1111001 *
0%
#1220000
b100 #
b100 3
b100 8
b100 9
b1111010 *
1%
#1230000
b1111011 *
0%
#1240000
b11 #
b11 3
b11 8
b11 9
b1111100 *
1%
#1250000
b1111101 *
0%
#1260000
b10 #
b10 3
b10 8
b10 9
b1111110 *
1%
#1270000
b1111111 *
0%
#1280000
b1 #
b1 3
b1 8
b1 9
b10000000 *
1%
#1290000
b10000001 *
0%
#1300000
b0 #
b0 3
b0 8
b0 9
b10000010 *
1%
#1310000
b10000011 *
0%
#1320000
1-
10
b1001 #
b1001 3
b1001 8
b1001 9
b10000100 *
1%
#1330000
b10000101 *
0%
#1340000
b10 "
b10 2
b10 5
b10 :
0-
00
b1000 #
b1000 3
b1000 8
b1000 9
b10000110 *
1%
#1350000
b10000111 *
0%
#1360000
b111 #
b111 3
b111 8
b111 9
b10001000 *
1%
#1370000
b10001001 *
0%
#1380000
b110 #
b110 3
b110 8
b110 9
b10001010 *
1%
#1390000
b10001011 *
0%
#1400000
b101 #
b101 3
b101 8
b101 9
b10001100 *
1%
#1410000
b10001101 *
0%
#1420000
b100 #
b100 3
b100 8
b100 9
b10001110 *
1%
#1430000
b10001111 *
0%
#1440000
b11 #
b11 3
b11 8
b11 9
b10010000 *
1%
#1450000
b10010001 *
0%
#1460000
b10 #
b10 3
b10 8
b10 9
b10010010 *
1%
#1470000
b10010011 *
0%
#1480000
b1 #
b1 3
b1 8
b1 9
b10010100 *
1%
#1490000
b10010101 *
0%
#1500000
b0 #
b0 3
b0 8
b0 9
b10010110 *
1%
#1510000
b10010111 *
0%
#1520000
1-
10
b1001 #
b1001 3
b1001 8
b1001 9
b10011000 *
1%
#1530000
b10011001 *
0%
#1540000
b1 "
b1 2
b1 5
b1 :
0-
00
b1000 #
b1000 3
b1000 8
b1000 9
b10011010 *
1%
#1550000
b10011011 *
0%
#1560000
b111 #
b111 3
b111 8
b111 9
b10011100 *
1%
#1570000
b10011101 *
0%
#1580000
b110 #
b110 3
b110 8
b110 9
b10011110 *
1%
#1590000
b10011111 *
0%
#1600000
b101 #
b101 3
b101 8
b101 9
b10100000 *
1%
#1610000
b10100001 *
0%
#1620000
b100 #
b100 3
b100 8
b100 9
b10100010 *
1%
#1630000
b10100011 *
0%
#1640000
b11 #
b11 3
b11 8
b11 9
b10100100 *
1%
#1650000
b10100101 *
0%
#1660000
b10 #
b10 3
b10 8
b10 9
b10100110 *
1%
#1670000
b10100111 *
0%
#1680000
b1 #
b1 3
b1 8
b1 9
b10101000 *
1%
#1690000
b10101001 *
0%
#1700000
b0 #
b0 3
b0 8
b0 9
b10101010 *
1%
#1710000
b10101011 *
0%
#1720000
1-
10
b1001 #
b1001 3
b1001 8
b1001 9
b10101100 *
1%
#1730000
b10101101 *
0%
#1740000
1/
b0 "
b0 2
b0 5
b0 :
0-
00
b1000 #
b1000 3
b1000 8
b1000 9
b10101110 *
1%
#1750000
b10101111 *
0%
#1760000
b111 #
b111 3
b111 8
b111 9
0/
b10 $
b10 4
b10 6
b10110000 *
1%
#1770000
b10110001 *
0%
#1780000
b110 #
b110 3
b110 8
b110 9
b10110010 *
1%
#1790000
b10110011 *
0%
#1800000
b101 #
b101 3
b101 8
b101 9
b10110100 *
1%
#1810000
b10110101 *
0%
#1820000
b100 #
b100 3
b100 8
b100 9
b10110110 *
1%
#1830000
b10110111 *
0%
#1840000
b11 #
b11 3
b11 8
b11 9
b10111000 *
1%
#1850000
b10111001 *
0%
#1860000
b10 #
b10 3
b10 8
b10 9
b10111010 *
1%
#1870000
b10111011 *
0%
#1880000
b1 #
b1 3
b1 8
b1 9
b10111100 *
1%
#1890000
b10111101 *
0%
#1900000
b0 #
b0 3
b0 8
b0 9
b10111110 *
1%
#1910000
b10111111 *
0%
#1920000
1-
10
b1001 #
b1001 3
b1001 8
b1001 9
b11000000 *
1%
#1930000
b11000001 *
0%
#1940000
1,
b101 "
b101 2
b101 5
b101 :
0-
00
b1000 #
b1000 3
b1000 8
b1000 9
b11000010 *
1%
#1950000
b11000011 *
0%
#1960000
b111 #
b111 3
b111 8
b111 9
b11000100 *
1%
#1970000
b11000101 *
0%
#1980000
b110 #
b110 3
b110 8
b110 9
b11000110 *
1%
#1990000
b11000111 *
0%
#2000000
b101 #
b101 3
b101 8
b101 9
b11001000 *
1%
